Workbook
Name budget: 'Budget Dashboard'!$L1
Name budget_range: 'Budget Dashboard'!$Q1
Name budget_rank: 'Budget Dashboard'!$R1
Name categorized_transactions: SOURCE!$A$432:$D$531
Name categorized_transactions_1: SOURCE!$A$1:$D$217
Name categorized_transactions_2: SOURCE!$I$1:$L$219
Name categorized_transactions_3: SOURCE!$A$218:$D$302
Name categorized_transactions_4: SOURCE!$A$303:$D$431
Name cc_budget: Calculations!$K1
Name cc_delta: Calculations!$L1
Name cc_in_focus: Calculations!$G1
Name cc_month_number: Calculations!$F1
Name cc_show_remaining_budget: Calculations!$I1
Name cc_show_type: Calculations!$H1
Name cc_tracked: Calculations!$J1
Name cc_type: Calculations!$E1
Name comb_rank: 'Budget Dashboard'!$S1
Name comb_rank_norm: 'Budget Dashboard'!$U1
Name comb_rank_norm_run_range: 'Budget Dashboard'!$V1
Name comb_rank_range: 'Budget Dashboard'!$T1
Name comb_rank_unique: 'Budget Dashboard'!$W1
Name current_date: DATE(2025,3,15)
Name expenses_header_row: ROW(Expenses[[#Headers],[Expenses]])
Name expenses_max_row: MAX(ROW(Expenses[]))
Name expenses_min_row: MIN(ROW(Expenses[]))
Name expenses_total_row: ROW('Budget Planning'!$C$52)
Name header_row_id: 'Budget Dashboard'!$D1
Name income_header_row: ROW(Income[[#Headers],[Income]])
Name income_max_row: MAX(ROW(Income[]))
Name income_min_row: MIN(ROW(Income[]))
Name income_total_row: ROW('Budget Planning'!$C$24)
Name is_cat: 'Budget Dashboard'!$F1
Name is_empty: 'Budget Dashboard'!$H1
Name is_header: 'Budget Dashboard'!$E1
Name is_total: 'Budget Dashboard'!$G1
Name item: 'Budget Dashboard'!$J1
Name out_budget: 'Budget Dashboard'!$AA1
Name out_percentage_completed: 'Budget Dashboard'!$AB1
Name out_tracked: 'Budget Dashboard'!$Z1
Name row_id: 'Budget Dashboard'!$C1
Name savings_header_row: ROW(Savings[[#Headers],[Savings]])
Name savings_max_row: MAX(ROW(Savings[]))
Name savings_min_row: MIN(ROW(Savings[]))
Name savings_total_row: ROW('Budget Planning'!$C$66)
Name selected_period: Calculations!$E$20
Name selected_period_display: Calculations!$E$21
Name selected_year: Calculations!$E$19
Name shift_late_income_starting_date: Settings!$E$18
Name shift_late_income_status: Settings!$E$16
Name Slicer_Category: #N/A
Name sort_max_row: 'Budget Dashboard'!$N1
Name sort_min_row: 'Budget Dashboard'!$M1
Name starting_year: Settings!$E$8
Name tracked: 'Budget Dashboard'!$K1
Name tracked_range: 'Budget Dashboard'!$O1
Name tracked_rank: 'Budget Dashboard'!$P1
Name type: 'Budget Dashboard'!$I1

Sheet Notes & Logs
A1: Step by Step Updating Process
A3: 1. Go to Source > Check latest transactions
A4: 2. Go to Ebanking > Extract cc_invoice + ubs_transactions
A5: 3. Move files from download to raw_ds
A6: 4. Run script in > Lucas_Sandbox_Budget_Script
A7: 5. Select next cell from last row in Source and import output.csv file
A8: 6. Check & Label
A9: 7. Budget Tracking > drag table
A10: 8. Budget Planning Compute Diff for extra savings
A11: 9. Expenses_Add update rows (drag) + pivot

Sheet SOURCE
A1: date | B1: Type | C1: Category | D1: Amount | E1: abs_Amount | I1: date | J1: Type | K1: Category | L1: Amount | O1: Income
A2: 45870 | B2: Expenses | C2: Digital Goods | D2: -0.05 | E2: =ABS(D2) -> 0.05 | I2: 45870 | J2: No-Label | K2: digital goods - google cloud mwgb4h dublin irl [CC] | L2: -0.05 | O2: Employment
A3: 45870 | B3: Expenses | C3: Train | D3: -18 | E3: =ABS(D3) -> 18 | I3: 45870 | J3: Expenses | K3: Train | L3: -18 | O3: Side Hustle
A4: 45870 | B4: Expenses | C4: Restaurants | D4: -13.5 | E4: =ABS(D4) -> 13.5 | I4: 45870 | J4: Expenses | K4: coop pronto nyon;1260 nyon [UBS] | L4: -13.5 | O4: Extras / Twint Chargeback
A5: 45870 | B5: Expenses | C5: Train | D5: -4.7 | E5: =ABS(D5) -> 4.7 | I5: 45870 | J5: Expenses | K5: Train | L5: -4.7 | O5: Enter income Category…
A6: 45870 | B6: Expenses | C6: Train | D6: -3.9 | E6: =ABS(D6) -> 3.9 | I6: 45870 | J6: Expenses | K6: Train | L6: -3.9 | O6: Enter income Category…
A7: 45872 | B7: Expenses | C7: Car | D7: -49.11 | E7: =ABS(D7) -> 49.11 | I7: 45901 | J7: Expenses | K7: Groceries | L7: -1.65 | O7: Enter income Category…
A8: 45872 | B8: Income | C8: Extras / Twint Chargeback | D8: 44 | E8: =ABS(D8) -> 44 | I8: 45901 | J8: Expenses | K8: Train | L8: -4.7 | O8: Enter income Category…
A9: 45873 | B9: Expenses | C9: Train | D9: -4.7 | E9: =ABS(D9) -> 4.7 | I9: 45901 | J9: Expenses | K9: Train | L9: -4.7 | O9: Enter income Category…
A10: 45873 | B10: Expenses | C10: Restaurants | D10: -31.5 | E10: =ABS(D10) -> 31.5 | I10: 45901 | J10: CC_Refund | K10: Card Refund Luca | L10: -726.2 | O10: Enter income Category…
A11: 45874 | B11: Expenses | C11: Restaurants | D11: -8 | E11: =ABS(D11) -> 8 | I11: 45901 | J11: Expenses | K11: Train | L11: -3.6 | O11: Enter income Category…
A12: 45874 | B12: Expenses | C12: Train | D12: -4.7 | E12: =ABS(D12) -> 4.7 | I12: 45901 | J12: No-Label | K12: data processing services - google cloud mjvxr6 dublin irl [CC] | L12: -0.01 | O12: Total
A13: 45875 | B13: Expenses | C13: Groceries | D13: -9.5 | E13: =ABS(D13) -> 9.5 | I13: 45901 | J13: Expenses | K13: Restaurants | L13: -18.9
A14: 45875 | B14: Expenses | C14: Train | D14: -4.7 | E14: =ABS(D14) -> 4.7 | I14: 45901 | J14: Expenses | K14: Groceries | L14: -3.8 | O14: Expenses
A15: 45875 | B15: Expenses | C15: Train | D15: -4.7 | E15: =ABS(D15) -> 4.7 | I15: 45902 | J15: Expenses | K15: Train | L15: -4.7 | O15: Housing
A16: 45876 | B16: Expenses | C16: Wellbeing | D16: -10 | E16: =ABS(D16) -> 10 | I16: 45902 | J16: Expenses | K16: assura-basis sa;1009 pully; ch [UBS] | L16: -501.35 | O16: Home Utils
A17: 45876 | B17: Expenses | C17: Train | D17: -7.8 | E17: =ABS(D17) -> 7.8 | I17: 45872 | J17: Expenses | K17: Car | L17: -49.11 | O17: Groceries
A18: 45876 | B18: Expenses | C18: Groceries | D18: -40.35 | E18: =ABS(D18) -> 40.35 | I18: 45872 | J18: Income | K18: Extras / Twint Chargeback | L18: 44 | O18: Restaurants
A19: 45876 | B19: Expenses | C19: Digital Goods | D19: -7 | E19: =ABS(D19) -> 7 | I19: 45903 | J19: Expenses | K19: Restaurants | L19: -18 | O19: Train
A20: 45876 | B20: Expenses | C20: Restaurants | D20: -8.2 | E20: =ABS(D20) -> 8.2 | I20: 45873 | J20: Expenses | K20: Train | L20: -4.7 | O20: Internet + Mobile
A21: 45876 | B21: Expenses | C21: Restaurants | D21: -14 | E21: =ABS(D21) -> 14 | I21: 45873 | J21: Expenses | K21: , eldrick; debit ubs twint [UBS] | L21: -31.5 | O21: Car
A22: 45877 | B22: Expenses | C22: Internet + Mobile | D22: -49 | E22: =ABS(D22) -> 49 | I22: 45904 | J22: Expenses | K22: Train | L22: -4.7 | O22: Health Insurance
A23: 45877 | B23: Expenses | C23: Internet + Mobile | D23: -28.85 | E23: =ABS(D23) -> 28.85 | I23: 45904 | J23: Expenses | K23: Health Other | L23: -9.2 | O23: Health Other
A24: 45877 | B24: Expenses | C24: Groceries | D24: -4.9 | E24: =ABS(D24) -> 4.9 | I24: 45904 | J24: Expenses | K24: Groceries | L24: -3.1 | O24: Clothing
A25: 45877 | B25: Expenses | C25: Restaurants | D25: -15.5 | E25: =ABS(D25) -> 15.5 | I25: 45904 | J25: Expenses | K25: grossmann, dany; debit ubs twint [UBS] | L25: -150 | O25: Media
... A39: 45882 | B39: Income | C39: Side Hustle | D39: 1465.3 | E39: =ABS(D39) -> 1465.3 | I39: 45876 | J39: No-Label | K39: computer software stores - heroku* jul-107212674 san franciscousaca [CC] | L39: -7 | O39: Total
A40: 45882 | B40: Income | C40: Side Hustle | D40: 852 | E40: =ABS(D40) -> 852 | I40: 45876 | J40: Expenses | K40: tabac du rhone;1205 geneve [UBS] | L40: -8.2
A41: 45882 | B41: Income | C41: Side Hustle | D41: 400 | E41: =ABS(D41) -> 400 | I41: 45876 | J41: Expenses | K41: ls lavandieres;1204 geneve [UBS] | L41: -14 | O41: Savings
A42: 45882 | B42: Income | C42: Side Hustle | D42: 320 | E42: =ABS(D42) -> 320 | I42: 45907 | J42: Expenses | K42: Train | L42: -4.7 | O42: Emergency Fund
A43: 45882 | B43: Income | C43: Side Hustle | D43: 320 | E43: =ABS(D43) -> 320 | I43: 45907 | J43: Expenses | K43: lavorent; payment ubs twint [UBS] | L43: -55 | O43: Retirement Account
A44: 45882 | B44: Expenses | C44: Groceries | D44: -25.9 | E44: =ABS(D44) -> 25.9 | I44: 45907 | J44: Expenses | K44: Groceries | L44: -1.95 | O44: Stock Portofolio
A45: 45883 | B45: Expenses | C45: Train | D45: -4.7 | E45: =ABS(D45) -> 4.7 | I45: 45907 | J45: Expenses | K45: Train | L45: -4.7 | O45: Sinking Fund Dow Payment
A46: 45883 | B46: Expenses | C46: Train | D46: -4.7 | E46: =ABS(D46) -> 4.7 | I46: 45877 | J46: Expenses | K46: swisscom (schweiz) ag /; payment ubs twint [UBS] | L46: -49 | O46: Sinking Fund Rest
A47: 45883 | B47: Expenses | C47: Car | D47: -9.75 | E47: =ABS(D47) -> 9.75 | I47: 45877 | J47: Expenses | K47: swisscom (schweiz) ag /; payment ubs twint [UBS] | L47: -28.85 | O47: Enter Savings Category…
A48: 45884 | B48: Expenses | C48: Groceries | D48: -10.1 | E48: =ABS(D48) -> 10.1 | I48: 45877 | J48: Expenses | K48: migros mm jonction;1205 gen√®ve [UBS] | L48: -4.9 | O48: Enter Savings Category…
A49: 45884 | B49: Expenses | C49: Restaurants | D49: -33 | E49: =ABS(D49) -> 33 | I49: 45877 | J49: Expenses | K49: Restaurants | L49: -15.5 | O49: Enter Savings Category…
A50: 45884 | B50: Expenses | C50: Restaurants | D50: -21 | E50: =ABS(D50) -> 21 | I50: 45877 | J50: Income | K50: Extras / Twint Chargeback | L50: 30 | O50: Enter Savings Category…
A51: 45884 | B51: Expenses | C51: Digital Goods | D51: -26.6 | E51: =ABS(D51) -> 26.6 | I51: 45877 | J51: Income | K51: Side Hustle | L51: 4 | O51: Enter Savings Category…
A52: 45885 | B52: Expenses | C52: Train | D52: -4.7 | E52: =ABS(D52) -> 4.7 | I52: 45877 | J52: Expenses | K52: Train | L52: -4.7 | O52: Total
A53: 45885 | B53: Expenses | C53: Train | D53: -4.7 | E53: =ABS(D53) -> 4.7 | I53: 45877 | J53: Expenses | K53: Restaurants | L53: -32
A54: 45885 | B54: Expenses | C54: Restaurants | D54: -53.9 | E54: =ABS(D54) -> 53.9 | I54: 45908 | J54: Expenses | K54: Groceries | L54: -16.5
A55: 45886 | B55: Expenses | C55: Train | D55: -3.4 | E55: =ABS(D55) -> 3.4 | I55: 45908 | J55: No-Label | K55: computer software stores - heroku* aug-107758056 san franciscousaca [CC] | L55: -7
A56: 45886 | B56: Expenses | C56: Restaurants | D56: -14.5 | E56: =ABS(D56) -> 14.5 | I56: 45878 | J56: Income | K56: Extras / Twint Chargeback | L56: 23
A57: 45887 | B57: Expenses | C57: Train | D57: -4.7 | E57: =ABS(D57) -> 4.7 | I57: 45909 | J57: Expenses | K57: Train | L57: -4.7
A58: 45887 | B58: Expenses | C58: Health Other | D58: -8.3 | E58: =ABS(D58) -> 8.3 | I58: 45909 | J58: Expenses | K58: Train | L58: -4.7
A59: 45887 | B59: Expenses | C59: Train | D59: -3.3 | E59: =ABS(D59) -> 3.3 | I59: 45910 | J59: Expenses | K59: Restaurants | L59: -13.7
A60: 45887 | B60: Expenses | C60: Groceries | D60: -1.95 | E60: =ABS(D60) -> 1.95 | I60: 45910 | J60: Expenses | K60: Health Other | L60: -11.95
A61: 45888 | B61: Expenses | C61: Train | D61: -3.4 | E61: =ABS(D61) -> 3.4 | I61: 45910 | J61: Expenses | K61: Restaurants | L61: -18.1
A62: 45888 | B62: Expenses | C62: Train | D62: -4.7 | E62: =ABS(D62) -> 4.7 | I62: 45910 | J62: Expenses | K62: , yanni; debit ubs twint [UBS] | L62: -40
A63: 45888 | B63: Expenses | C63: Restaurants | D63: -9.5 | E63: =ABS(D63) -> 9.5 | I63: 45880 | J63: Expenses | K63: Restaurants | L63: -10
A64: 45888 | B64: Expenses | C64: Digital Goods | D64: -49.95 | E64: =ABS(D64) -> 49.95 | I64: 45880 | J64: Expenses | K64: coop pronto 4824 nyon; payment ubs twint [UBS] | L64: -18.55
... A219: 45931 | B219: No-Label | C219: digital goods - google cloud xnxvwt dublin irl [CC] | D219: -0.01 | E219: =ABS(D219) -> 0.01 | I219: 45900 | J219: Expenses | K219: Restaurants | L219: -40
A220: 45931 | B220: Expenses | C220: Train | D220: -4.7 | E220: =ABS(D220) -> 4.7
A221: 45931 | B221: Expenses | C221: Train | D221: -4.7 | E221: =ABS(D221) -> 4.7
A222: 45931 | B222: Expenses | C222: Restaurants | D222: -12.5 | E222: =ABS(D222) -> 12.5
A223: 45932 | B223: Expenses | C223: Groceries | D223: -15.2 | E223: =ABS(D223) -> 15.2
A224: 45932 | B224: Expenses | C224: assura-basis sa;1009 pully; ch [UBS] | D224: -501.35 | E224: =ABS(D224) -> 501.35
A225: 45932 | B225: CC_Refund | C225: Card Refund Luca | D225: -838.5 | E225: =ABS(D225) -> 838.5
A226: 45933 | B226: Expenses | C226: Restaurants | D226: -30 | E226: =ABS(D226) -> 30
A227: 45933 | B227: Expenses | C227: Groceries | D227: -5.9 | E227: =ABS(D227) -> 5.9
A228: 45933 | B228: Expenses | C228: Train | D228: -4.7 | E228: =ABS(D228) -> 4.7
A229: 45933 | B229: Expenses | C229: Train | D229: -4.7 | E229: =ABS(D229) -> 4.7
A230: 45933 | B230: Expenses | C230: grossmann, dany; debit ubs twint [UBS] | D230: -150 | E230: =ABS(D230) -> 150
A231: 45934 | B231: Expenses | C231: Groceries | D231: -21.3 | E231: =ABS(D231) -> 21.3
... A294: 45951 | B294: Expenses | C294: Train | D294: -11.9 | E294: =ABS(D294) -> 11.9
A295: 45951 | B295: Expenses | C295: Train | D295: -9.6 | E295: =ABS(D295) -> 9.6 | I295: 45955 | J295: Expenses | K295: ubs switzerland ag;c/o ubs card center [UBS] | L295: -1296.35
A296: 45951 | B296: Expenses | C296: Train | D296: -4.7 | E296: =ABS(D296) -> 4.7 | I296: 45982 | J296: No-Label | K296: hotels - hotel adlon gmbh berlin deu [CC] | L296: -200
A297: 45952 | B297: Expenses | C297: office des poursuites; payment ubs twint [UBS] | D297: -17 | E297: =ABS(D297) -> 17 | I297: 45986 | J297: Expenses | K297: ubs switzerland ag;c/o ubs card center [UBS] | L297: -1044.6
A298: 45953 | B298: No-Label | C298: aparments - cb-billetweb rueil-malmais fra [CC] | D298: -54 | E298: =ABS(D298) -> 54
A299: 45953 | B299: Expenses | C299: Groceries | D299: -2.3 | E299: =ABS(D299) -> 2.3
A300: 45953 | B300: Expenses | C300: Groceries | D300: -9.5 | E300: =ABS(D300) -> 9.5
A301: 45954 | B301: Income | C301: Employment | D301: 8204.85 | E301: =ABS(D301) -> 8204.85
A302: 45954 | B302: Expenses | C302: Housing | D302: -1912 | E302: =ABS(D302) -> 1912
A303: 45955 | B303: Expenses | C303: Train | D303: -4.7 | E303: =ABS(D303) -> 4.7 | M303: Employment
A304: 45955 | B304: Expenses | C304: Train | D304: -4.7 | E304: =ABS(D304) -> 4.7 | M304: Side Hustle
A305: 45956 | B305: Expenses | C305: Groceries | D305: -18 | E305: =ABS(D305) -> 18 | M305: Extras / Twint Chargeback
A306: 45957 | B306: Expenses | C306: Restaurants | D306: -11 | E306: =ABS(D306) -> 11
A307: 45957 | B307: Expenses | C307: Extras | D307: -18 | E307: =ABS(D307) -> 18
A308: 45957 | B308: Expenses | C308: Groceries | D308: -6.05 | E308: =ABS(D308) -> 6.05
A309: 45958 | B309: Expenses | C309: Groceries | D309: -5.9 | E309: =ABS(D309) -> 5.9
A310: 45958 | B310: Expenses | C310: Groceries | D310: -19.9 | E310: =ABS(D310) -> 19.9
A311: 45958 | B311: Expenses | C311: Restaurants | D311: -35 | E311: =ABS(D311) -> 35
A312: 45958 | B312: Expenses | C312: Restaurants | D312: -16 | E312: =ABS(D312) -> 16
A313: 45958 | B313: Expenses | C313: Train | D313: -4.7 | E313: =ABS(D313) -> 4.7
A314: 45958 | B314: Expenses | C314: Train | D314: -4.7 | E314: =ABS(D314) -> 4.7
A315: 45959 | B315: Expenses | C315: Groceries | D315: -2.3 | E315: =ABS(D315) -> 2.3 | M315: Expenses
A316: 45959 | B316: Expenses | C316: Restaurants | D316: -15.5 | E316: =ABS(D316) -> 15.5 | M316: Housing
A317: 45959 | B317: Expenses | C317: Digital Goods | D317: -50 | E317: =ABS(D317) -> 50 | M317: Home Utils
A318: 45960 | B318: Expenses | C318: Train | D318: -4.7 | E318: =ABS(D318) -> 4.7 | M318: Groceries
A319: 45960 | B319: Expenses | C319: Train | D319: -4.7 | E319: =ABS(D319) -> 4.7 | M319: Restaurants
A320: 45960 | B320: Expenses | C320: Car | D320: -9.9 | E320: =ABS(D320) -> 9.9 | M320: Train
A321: 45960 | B321: Expenses | C321: Groceries | D321: -1.95 | E321: =ABS(D321) -> 1.95 | M321: Internet + Mobile
A322: 45961 | B322: Expenses | C322: CC fees | D322: -10 | E322: =ABS(D322) -> 10 | M322: Car
A323: 45961 | B323: Expenses | C323: Car | D323: -13.7 | E323: =ABS(D323) -> 13.7 | M323: Health Insurance
A324: 45961 | B324: Expenses | C324: Groceries | D324: -6.65 | E324: =ABS(D324) -> 6.65 | M324: Health Other
A325: 45961 | B325: Expenses | C325: Train | D325: -11.9 | E325: =ABS(D325) -> 11.9 | M325: Clothing
A326: 45962 | B326: Income | C326: Extras / Twint Chargeback | D326: 16.5 | E326: =ABS(D326) -> 16.5 | M326: Media
... A335: 45965 | B335: Expenses | C335: Restaurants | D335: -40 | E335: =ABS(D335) -> 40 | M335: Debt
A336: 45965 | B336: Expenses | C336: Train | D336: -11.9 | E336: =ABS(D336) -> 11.9
A337: 45965 | B337: Expenses | C337: Train | D337: -9.6 | E337: =ABS(D337) -> 9.6
...

Sheet Settings
C2: Settings
C6: General
D8: Starting Year: | E8: 2025 | G8: Set the starting year (yyyy) once at the beginning and do not change it
C12: Budget Tracking & Dashboard
D14: Late Monthly Income
D16: Shift late income: | E16: Inactive | G16: Activate this option to treat late income received on or after a certain day of the month as income for the next month. This is especially recommended in case you receive your monthly paycheck towards the end of the month and prefer to consider this income as the disposable income for the next month
D18: Starting on day x in month: | E18: 25
D29: Video | E29: https://www.youtube.com/watch?v=eKyAOjH3Crk

Sheet Budget Planning
C2: Budget Planning
C4: Savings | Q4: =Q24-Q52 -> 15415.6 | AE4: =AE24-AE52 -> 46633.08
C5: Ratio | Q5: =Q52/Q24 -> 0.67600639 | AE5: =AE52/AE24 -> 0.52637538
C6: Define starting year in Settings → | E6: =starting_year -> 2025 | S6: =E6 + 1 -> 2026 | AG6: =S6 + 1 -> 2027 | AU6: =AG6 + 1 -> 2028 | BI6: =AU6 + 1 -> 2029 | BW6: =BI6 + 1 -> 2030 | CK6: =BW6 + 1 -> 2031 | CY6: =CK6 + 1 -> 2032 | DM6: =CY6 + 1 -> 2033 | EA6: =DM6 + 1 -> 2034 | EO6: =EA6 + 1 -> 2035 | FC6: =EO6 + 1 -> 2036 | FQ6: =FC6 + 1 -> 2037 | GE6: =FQ6 + 1 -> 2038 | GS6: =GE6 + 1 -> 2039 | HG6: =GS6 + 1 -> 2040 | HU6: =HG6 + 1 -> 2041
E7: =IF(E8=0,"Jan ✓", "Jan") -> Jan ✓ | F7: =IF(F8=0,"Feb ✓", "Feb") -> Feb ✓ | G7: =IF(G8=0,"Mar ✓", "Mar") -> Mar ✓ | H7: =IF(H8=0,"Apr ✓", "Apr") -> Apr ✓ | I7: =IF(I8=0,"May ✓", "May") -> May ✓ | J7: =IF(J8=0,"Jun ✓", "Jun") -> Jun ✓ | K7: =IF(K8=0,"Jul ✓", "Jul") -> Jul ✓ | L7: =IF(L8=0,"Aug ✓", "Aug") -> Aug | M7: =IF(M8=0,"Sep ✓", "Sep") -> Sep | N7: =IF(N8=0,"Oct ✓", "Oct") -> Oct | O7: =IF(O8=0,"Nov ✓", "Nov") -> Nov | P7: =IF(P8=0,"Dec ✓", "Dec") -> Dec | Q7: =IF(Q8=0,"Total ✓", "Total") -> Total | S7: =IF(S8=0,"Jan ✓", "Jan") -> Jan | T7: =IF(T8=0,"Feb ✓", "Feb") -> Feb | U7: =IF(U8=0,"Mar ✓", "Mar") -> Mar | V7: =IF(V8=0,"Apr ✓", "Apr") -> Apr | W7: =IF(W8=0,"May ✓", "May") -> May | X7: =IF(X8=0,"Jun ✓", "Jun") -> Jun | Y7: =IF(Y8=0,"Jul ✓", "Jul") -> Jul | Z7: =IF(Z8=0,"Aug ✓", "Aug") -> Aug | AA7: =IF(AA8=0,"Sep ✓", "Sep") -> Sep | AB7: =IF(AB8=0,"Oct ✓", "Oct") -> Oct | AC7: =IF(AC8=0,"Nov ✓", "Nov") -> Nov | AD7: =IF(AD8=0,"Dec ✓", "Dec") -> Dec | AE7: =IF(AE8=0,"Total ✓", "Total") -> Total | AG7: =IF(AG8=0,"Jan ✓", "Jan") -> Jan ✓ | AH7: =IF(AH8=0,"Feb ✓", "Feb") -> Feb ✓ | AI7: =IF(AI8=0,"Mar ✓", "Mar") -> Mar ✓ | AJ7: =IF(AJ8=0,"Apr ✓", "Apr") -> Apr ✓ | AK7: =IF(AK8=0,"May ✓", "May") -> May ✓ | AL7: =IF(AL8=0,"Jun ✓", "Jun") -> Jun ✓ | AM7: =IF(AM8=0,"Jul ✓", "Jul") -> Jul ✓ | AN7: =IF(AN8=0,"Aug ✓", "Aug") -> Aug ✓ | AO7: =IF(AO8=0,"Sep ✓", "Sep") -> Sep ✓ | AP7: =IF(AP8=0,"Oct ✓", "Oct") -> Oct ✓ | AQ7: =IF(AQ8=0,"Nov ✓", "Nov") -> Nov ✓ | AR7: =IF(AR8=0,"Dec ✓", "Dec") -> Dec ✓ | AS7: =IF(AS8=0,"Total ✓", "Total") -> Total ✓ | AU7: =IF(AU8=0,"Jan ✓", "Jan") -> Jan ✓ | AV7: =IF(AV8=0,"Feb ✓", "Feb") -> Feb ✓ | AW7: =IF(AW8=0,"Mar ✓", "Mar") -> Mar ✓ | AX7: =IF(AX8=0,"Apr ✓", "Apr") -> Apr ✓ | AY7: =IF(AY8=0,"May ✓", "May") -> May ✓ | AZ7: =IF(AZ8=0,"Jun ✓", "Jun") -> Jun ✓ | BA7: =IF(BA8=0,"Jul ✓", "Jul") -> Jul ✓ | BB7: =IF(BB8=0,"Aug ✓", "Aug") -> Aug ✓ | BC7: =IF(BC8=0,"Sep ✓", "Sep") -> Sep ✓ | BD7: =IF(BD8=0,"Oct ✓", "Oct") -> Oct ✓ | BE7: =IF(BE8=0,"Nov ✓", "Nov") -> Nov ✓ | BF7: =IF(BF8=0,"Dec ✓", "Dec") -> Dec ✓ | BG7: =IF(BG8=0,"Total ✓", "Total") -> Total ✓ | BI7: =IF(BI8=0,"Jan ✓", "Jan") -> Jan ✓ | BJ7: =IF(BJ8=0,"Feb ✓", "Feb") -> Feb ✓ | BK7: =IF(BK8=0,"Mar ✓", "Mar") -> Mar ✓ | BL7: =IF(BL8=0,"Apr ✓", "Apr") -> Apr ✓ | BM7: =IF(BM8=0,"May ✓", "May") -> May ✓ | BN7: =IF(BN8=0,"Jun ✓", "Jun") -> Jun ✓ | BO7: =IF(BO8=0,"Jul ✓", "Jul") -> Jul ✓ | BP7: =IF(BP8=0,"Aug ✓", "Aug") -> Aug ✓ | BQ7: =IF(BQ8=0,"Sep ✓", "Sep") -> Sep ✓ | BR7: =IF(BR8=0,"Oct ✓", "Oct") -> Oct ✓ | BS7: =IF(BS8=0,"Nov ✓", "Nov") -> Nov ✓ | BT7: =IF(BT8=0,"Dec ✓", "Dec") -> Dec ✓ | BU7: =IF(BU8=0,"Total ✓", "Total") -> Total ✓ | BW7: =IF(BW8=0,"Jan ✓", "Jan") -> Jan ✓ | BX7: =IF(BX8=0,"Feb ✓", "Feb") -> Feb ✓ | BY7: =IF(BY8=0,"Mar ✓", "Mar") -> Mar ✓ | BZ7: =IF(BZ8=0,"Apr ✓", "Apr") -> Apr ✓ | CA7: =IF(CA8=0,"May ✓", "May") -> May ✓ | CB7: =IF(CB8=0,"Jun ✓", "Jun") -> Jun ✓ | CC7: =IF(CC8=0,"Jul ✓", "Jul") -> Jul ✓ | CD7: =IF(CD8=0,"Aug ✓", "Aug") -> Aug ✓ | CE7: =IF(CE8=0,"Sep ✓", "Sep") -> Sep ✓ | CF7: =IF(CF8=0,"Oct ✓", "Oct") -> Oct ✓ | CG7: =IF(CG8=0,"Nov ✓", "Nov") -> Nov ✓ | CH7: =IF(CH8=0,"Dec ✓", "Dec") -> Dec ✓ | CI7: =IF(CI8=0,"Total ✓", "Total") -> Total ✓ | CK7: =IF(CK8=0,"Jan ✓", "Jan") -> Jan ✓ | CL7: =IF(CL8=0,"Feb ✓", "Feb") -> Feb ✓ | CM7: =IF(CM8=0,"Mar ✓", "Mar") -> Mar ✓ | CN7: =IF(CN8=0,"Apr ✓", "Apr") -> Apr ✓ | CO7: =IF(CO8=0,"May ✓", "May") -> May ✓ | CP7: =IF(CP8=0,"Jun ✓", "Jun") -> Jun ✓ | CQ7: =IF(CQ8=0,"Jul ✓", "Jul") -> Jul ✓ | CR7: =IF(CR8=0,"Aug ✓", "Aug") -> Aug ✓ | CS7: =IF(CS8=0,"Sep ✓", "Sep") -> Sep ✓ | CT7: =IF(CT8=0,"Oct ✓", "Oct") -> Oct ✓ | CU7: =IF(CU8=0,"Nov ✓", "Nov") -> Nov ✓ | CV7: =IF(CV8=0,"Dec ✓", "Dec") -> Dec ✓ | CW7: =IF(CW8=0,"Total ✓", "Total") -> Total ✓ | CY7: =IF(CY8=0,"Jan ✓", "Jan") -> Jan ✓ | CZ7: =IF(CZ8=0,"Feb ✓", "Feb") -> Feb ✓ | DA7: =IF(DA8=0,"Mar ✓", "Mar") -> Mar ✓ | DB7: =IF(DB8=0,"Apr ✓", "Apr") -> Apr ✓ | DC7: =IF(DC8=0,"May ✓", "May") -> May ✓ | DD7: =IF(DD8=0,"Jun ✓", "Jun") -> Jun ✓ | DE7: =IF(DE8=0,"Jul ✓", "Jul") -> Jul ✓ | DF7: =IF(DF8=0,"Aug ✓", "Aug") -> Aug ✓ | DG7: =IF(DG8=0,"Sep ✓", "Sep") -> Sep ✓ | DH7: =IF(DH8=0,"Oct ✓", "Oct") -> Oct ✓ | DI7: =IF(DI8=0,"Nov ✓", "Nov") -> Nov ✓ | DJ7: =IF(DJ8=0,"Dec ✓", "Dec") -> Dec ✓ | DK7: =IF(DK8=0,"Total ✓", "Total") -> Total ✓ | DM7: =IF(DM8=0,"Jan ✓", "Jan") -> Jan ✓ | DN7: =IF(DN8=0,"Feb ✓", "Feb") -> Feb ✓ | DO7: =IF(DO8=0,"Mar ✓", "Mar") -> Mar ✓ | DP7: =IF(DP8=0,"Apr ✓", "Apr") -> Apr ✓ | DQ7: =IF(DQ8=0,"May ✓", "May") -> May ✓ | DR7: =IF(DR8=0,"Jun ✓", "Jun") -> Jun ✓ | DS7: =IF(DS8=0,"Jul ✓", "Jul") -> Jul ✓ | DT7: =IF(DT8=0,"Aug ✓", "Aug") -> Aug ✓ | DU7: =IF(DU8=0,"Sep ✓", "Sep") -> Sep ✓ | DV7: =IF(DV8=0,"Oct ✓", "Oct") -> Oct ✓ | DW7: =IF(DW8=0,"Nov ✓", "Nov") -> Nov ✓ | DX7: =IF(DX8=0,"Dec ✓", "Dec") -> Dec ✓ | DY7: =IF(DY8=0,"Total ✓", "Total") -> Total ✓ | EA7: =IF(EA8=0,"Jan ✓", "Jan") -> Jan ✓ | EB7: =IF(EB8=0,"Feb ✓", "Feb") -> Feb ✓ | EC7: =IF(EC8=0,"Mar ✓", "Mar") -> Mar ✓ | ED7: =IF(ED8=0,"Apr ✓", "Apr") -> Apr ✓ | EE7: =IF(EE8=0,"May ✓", "May") -> May ✓ | EF7: =IF(EF8=0,"Jun ✓", "Jun") -> Jun ✓ | EG7: =IF(EG8=0,"Jul ✓", "Jul") -> Jul ✓ | EH7: =IF(EH8=0,"Aug ✓", "Aug") -> Aug ✓ | EI7: =IF(EI8=0,"Sep ✓", "Sep") -> Sep ✓ | EJ7: =IF(EJ8=0,"Oct ✓", "Oct") -> Oct ✓ | EK7: =IF(EK8=0,"Nov ✓", "Nov") -> Nov ✓ | EL7: =IF(EL8=0,"Dec ✓", "Dec") -> Dec ✓ | EM7: =IF(EM8=0,"Total ✓", "Total") -> Total ✓ | EO7: =IF(EO8=0,"Jan ✓", "Jan") -> Jan ✓ | EP7: =IF(EP8=0,"Feb ✓", "Feb") -> Feb ✓ | EQ7: =IF(EQ8=0,"Mar ✓", "Mar") -> Mar ✓ | ER7: =IF(ER8=0,"Apr ✓", "Apr") -> Apr ✓ | ES7: =IF(ES8=0,"May ✓", "May") -> May ✓ | ET7: =IF(ET8=0,"Jun ✓", "Jun") -> Jun ✓ | EU7: =IF(EU8=0,"Jul ✓", "Jul") -> Jul ✓ | EV7: =IF(EV8=0,"Aug ✓", "Aug") -> Aug ✓ | EW7: =IF(EW8=0,"Sep ✓", "Sep") -> Sep ✓ | EX7: =IF(EX8=0,"Oct ✓", "Oct") -> Oct ✓ | EY7: =IF(EY8=0,"Nov ✓", "Nov") -> Nov ✓ | EZ7: =IF(EZ8=0,"Dec ✓", "Dec") -> Dec ✓ | FA7: =IF(FA8=0,"Total ✓", "Total") -> Total ✓ | FC7: =IF(FC8=0,"Jan ✓", "Jan") -> Jan ✓ | FD7: =IF(FD8=0,"Feb ✓", "Feb") -> Feb ✓ | FE7: =IF(FE8=0,"Mar ✓", "Mar") -> Mar ✓ | FF7: =IF(FF8=0,"Apr ✓", "Apr") -> Apr ✓ | FG7: =IF(FG8=0,"May ✓", "May") -> May ✓ | FH7: =IF(FH8=0,"Jun ✓", "Jun") -> Jun ✓ | FI7: =IF(FI8=0,"Jul ✓", "Jul") -> Jul ✓ | FJ7: =IF(FJ8=0,"Aug ✓", "Aug") -> Aug ✓ | FK7: =IF(FK8=0,"Sep ✓", "Sep") -> Sep ✓ | FL7: =IF(FL8=0,"Oct ✓", "Oct") -> Oct ✓ | FM7: =IF(FM8=0,"Nov ✓", "Nov") -> Nov ✓ | FN7: =IF(FN8=0,"Dec ✓", "Dec") -> Dec ✓ | FO7: =IF(FO8=0,"Total ✓", "Total") -> Total ✓ | FQ7: =IF(FQ8=0,"Jan ✓", "Jan") -> Jan ✓ | FR7: =IF(FR8=0,"Feb ✓", "Feb") -> Feb ✓ | FS7: =IF(FS8=0,"Mar ✓", "Mar") -> Mar ✓ | FT7: =IF(FT8=0,"Apr ✓", "Apr") -> Apr ✓ | FU7: =IF(FU8=0,"May ✓", "May") -> May ✓ | FV7: =IF(FV8=0,"Jun ✓", "Jun") -> Jun ✓ | FW7: =IF(FW8=0,"Jul ✓", "Jul") -> Jul ✓ | FX7: =IF(FX8=0,"Aug ✓", "Aug") -> Aug ✓ | FY7: =IF(FY8=0,"Sep ✓", "Sep") -> Sep ✓ | FZ7: =IF(FZ8=0,"Oct ✓", "Oct") -> Oct ✓ | GA7: =IF(GA8=0,"Nov ✓", "Nov") -> Nov ✓ | GB7: =IF(GB8=0,"Dec ✓", "Dec") -> Dec ✓ | GC7: =IF(GC8=0,"Total ✓", "Total") -> Total ✓ | GE7: =IF(GE8=0,"Jan ✓", "Jan") -> Jan ✓ | GF7: =IF(GF8=0,"Feb ✓", "Feb") -> Feb ✓ | GG7: =IF(GG8=0,"Mar ✓", "Mar") -> Mar ✓ | GH7: =IF(GH8=0,"Apr ✓", "Apr") -> Apr ✓ | GI7: =IF(GI8=0,"May ✓", "May") -> May ✓ | GJ7: =IF(GJ8=0,"Jun ✓", "Jun") -> Jun ✓ | GK7: =IF(GK8=0,"Jul ✓", "Jul") -> Jul ✓ | GL7: =IF(GL8=0,"Aug ✓", "Aug") -> Aug ✓ | GM7: =IF(GM8=0,"Sep ✓", "Sep") -> Sep ✓ | GN7: =IF(GN8=0,"Oct ✓", "Oct") -> Oct ✓ | GO7: =IF(GO8=0,"Nov ✓", "Nov") -> Nov ✓ | GP7: =IF(GP8=0,"Dec ✓", "Dec") -> Dec ✓ | GQ7: =IF(GQ8=0,"Total ✓", "Total") -> Total ✓ | GS7: =IF(GS8=0,"Jan ✓", "Jan") -> Jan ✓ | GT7: =IF(GT8=0,"Feb ✓", "Feb") -> Feb ✓ | GU7: =IF(GU8=0,"Mar ✓", "Mar") -> Mar ✓ | GV7: =IF(GV8=0,"Apr ✓", "Apr") -> Apr ✓ | GW7: =IF(GW8=0,"May ✓", "May") -> May ✓ | GX7: =IF(GX8=0,"Jun ✓", "Jun") -> Jun ✓ | GY7: =IF(GY8=0,"Jul ✓", "Jul") -> Jul ✓ | GZ7: =IF(GZ8=0,"Aug ✓", "Aug") -> Aug ✓ | HA7: =IF(HA8=0,"Sep ✓", "Sep") -> Sep ✓ | HB7: =IF(HB8=0,"Oct ✓", "Oct") -> Oct ✓ | HC7: =IF(HC8=0,"Nov ✓", "Nov") -> Nov ✓ | HD7: =IF(HD8=0,"Dec ✓", "Dec") -> Dec ✓ | HE7: =IF(HE8=0,"Total ✓", "Total") -> Total ✓ | HG7: =IF(HG8=0,"Jan ✓", "Jan") -> Jan ✓ | HH7: =IF(HH8=0,"Feb ✓", "Feb") -> Feb ✓ | HI7: =IF(HI8=0,"Mar ✓", "Mar") -> Mar ✓ | HJ7: =IF(HJ8=0,"Apr ✓", "Apr") -> Apr ✓ | HK7: =IF(HK8=0,"May ✓", "May") -> May ✓ | HL7: =IF(HL8=0,"Jun ✓", "Jun") -> Jun ✓ | HM7: =IF(HM8=0,"Jul ✓", "Jul") -> Jul ✓ | HN7: =IF(HN8=0,"Aug ✓", "Aug") -> Aug ✓ | HO7: =IF(HO8=0,"Sep ✓", "Sep") -> Sep ✓ | HP7: =IF(HP8=0,"Oct ✓", "Oct") -> Oct ✓ | HQ7: =IF(HQ8=0,"Nov ✓", "Nov") -> Nov ✓ | HR7: =IF(HR8=0,"Dec ✓", "Dec") -> Dec ✓ | HS7: =IF(HS8=0,"Total ✓", "Total") -> Total ✓ | HU7: =IF(HU8=0,"Jan ✓", "Jan") -> Jan ✓ | HV7: =IF(HV8=0,"Feb ✓", "Feb") -> Feb ✓ | HW7: =IF(HW8=0,"Mar ✓", "Mar") -> Mar ✓ | HX7: =IF(HX8=0,"Apr ✓", "Apr") -> Apr ✓ | HY7: =IF(HY8=0,"May ✓", "May") -> May ✓ | HZ7: =IF(HZ8=0,"Jun ✓", "Jun") -> Jun ✓ | IA7: =IF(IA8=0,"Jul ✓", "Jul") -> Jul ✓ | IB7: =IF(IB8=0,"Aug ✓", "Aug") -> Aug ✓ | IC7: =IF(IC8=0,"Sep ✓", "Sep") -> Sep ✓ | ID7: =IF(ID8=0,"Oct ✓", "Oct") -> Oct ✓ | IE7: =IF(IE8=0,"Nov ✓", "Nov") -> Nov ✓ | IF7: =IF(IF8=0,"Dec ✓", "Dec") -> Dec ✓ | IG7: =IF(IG8=0,"Total ✓", "Total") -> Total ✓
C8: To be allocated: | E8: =E24-(E52+E66) -> 0 | F8: =F24-(F52+F66) -> 0 | G8: =G24-(G52+G66) -> 0 | H8: =H24-(H52+H66) -> 0 | I8: =I24-(I52+I66) -> 0 | J8: =J24-(J52+J66) -> 0 | K8: =K24-(K52+K66) -> 0 | L8: =L24-(L52+L66) -> 782.6 | ... Q8: =Q24-(Q52+Q66) -> 15415.6 | S8: =S24-(S52+S66) -> 3886.0967 | T8: =T24-(T52+T66) -> 3886.3467 | U8: =U24-(U52+U66) -> 3886.3467 | V8: =V24-(V52+V66) -> 3886.3467 | W8: =W24-(W52+W66) -> 3886.3467 | X8: =X24-(X52+X66) -> 3886.3467 | Y8: =Y24-(Y52+Y66) -> 3886.3467 | Z8: =Z24-(Z52+Z66) -> 3886.3467 | ... AE8: =AE24-(AE52+AE66) -> 46633.08 | AG8: =AG24-(AG52+AG66) -> 0 | AH8: =AH24-(AH52+AH66) -> 0 | AI8: =AI24-(AI52+AI66) -> 0 | AJ8: =AJ24-(AJ52+AJ66) -> 0 | AK8: =AK24-(AK52+AK66) -> 0 | AL8: =AL24-(AL52+AL66) -> 0 | AM8: =AM24-(AM52+AM66) -> 0 | AN8: =AN24-(AN52+AN66) -> 0 | ... AS8: =AS24-(AS52+AS66) -> 0 | AU8: =AU24-(AU52+AU66) -> 0 | AV8: =AV24-(AV52+AV66) -> 0 | AW8: =AW24-(AW52+AW66) -> 0 | AX8: =AX24-(AX52+AX66) -> 0 | AY8: =AY24-(AY52+AY66) -> 0 | AZ8: =AZ24-(AZ52+AZ66) -> 0 | BA8: =BA24-(BA52+BA66) -> 0 | BB8: =BB24-(BB52+BB66) -> 0 | ... BG8: =BG24-(BG52+BG66) -> 0 | BI8: =BI24-(BI52+BI66) -> 0 | BJ8: =BJ24-(BJ52+BJ66) -> 0 | BK8: =BK24-(BK52+BK66) -> 0 | BL8: =BL24-(BL52+BL66) -> 0 | BM8: =BM24-(BM52+BM66) -> 0 | BN8: =BN24-(BN52+BN66) -> 0 | BO8: =BO24-(BO52+BO66) -> 0 | BP8: =BP24-(BP52+BP66) -> 0 | ... BU8: =BU24-(BU52+BU66) -> 0 | BW8: =BW24-(BW52+BW66) -> 0 | BX8: =BX24-(BX52+BX66) -> 0 | BY8: =BY24-(BY52+BY66) -> 0 | BZ8: =BZ24-(BZ52+BZ66) -> 0 | CA8: =CA24-(CA52+CA66) -> 0 | CB8: =CB24-(CB52+CB66) -> 0 | CC8: =CC24-(CC52+CC66) -> 0 | CD8: =CD24-(CD52+CD66) -> 0 | ... CI8: =CI24-(CI52+CI66) -> 0 | CK8: =CK24-(CK52+CK66) -> 0 | CL8: =CL24-(CL52+CL66) -> 0 | CM8: =CM24-(CM52+CM66) -> 0 | CN8: =CN24-(CN52+CN66) -> 0 | CO8: =CO24-(CO52+CO66) -> 0 | CP8: =CP24-(CP52+CP66) -> 0 | CQ8: =CQ24-(CQ52+CQ66) -> 0 | CR8: =CR24-(CR52+CR66) -> 0 | ... CW8: =CW24-(CW52+CW66) -> 0 | CY8: =CY24-(CY52+CY66) -> 0 | CZ8: =CZ24-(CZ52+CZ66) -> 0 | DA8: =DA24-(DA52+DA66) -> 0 | DB8: =DB24-(DB52+DB66) -> 0 | DC8: =DC24-(DC52+DC66) -> 0 | DD8: =DD24-(DD52+DD66) -> 0 | DE8: =DE24-(DE52+DE66) -> 0 | DF8: =DF24-(DF52+DF66) -> 0 | ... DK8: =DK24-(DK52+DK66) -> 0 | DM8: =DM24-(DM52+DM66) -> 0 | DN8: =DN24-(DN52+DN66) -> 0 | DO8: =DO24-(DO52+DO66) -> 0 | DP8: =DP24-(DP52+DP66) -> 0 | DQ8: =DQ24-(DQ52+DQ66) -> 0 | DR8: =DR24-(DR52+DR66) -> 0 | DS8: =DS24-(DS52+DS66) -> 0 | DT8: =DT24-(DT52+DT66) -> 0 | ... DY8: =DY24-(DY52+DY66) -> 0 | EA8: =EA24-(EA52+EA66) -> 0 | EB8: =EB24-(EB52+EB66) -> 0 | EC8: =EC24-(EC52+EC66) -> 0 | ED8: =ED24-(ED52+ED66) -> 0 | EE8: =EE24-(EE52+EE66) -> 0 | EF8: =EF24-(EF52+EF66) -> 0 | EG8: =EG24-(EG52+EG66) -> 0 | EH8: =EH24-(EH52+EH66) -> 0 | ... EM8: =EM24-(EM52+EM66) -> 0 | EO8: =EO24-(EO52+EO66) -> 0 | EP8: =EP24-(EP52+EP66) -> 0 | EQ8: =EQ24-(EQ52+EQ66) -> 0 | ER8: =ER24-(ER52+ER66) -> 0 | ES8: =ES24-(ES52+ES66) -> 0 | ET8: =ET24-(ET52+ET66) -> 0 | EU8: =EU24-(EU52+EU66) -> 0 | EV8: =EV24-(EV52+EV66) -> 0 | ... FA8: =FA24-(FA52+FA66) -> 0 | FC8: =FC24-(FC52+FC66) -> 0 | FD8: =FD24-(FD52+FD66) -> 0 | FE8: =FE24-(FE52+FE66) -> 0 | FF8: =FF24-(FF52+FF66) -> 0 | FG8: =FG24-(FG52+FG66) -> 0 | FH8: =FH24-(FH52+FH66) -> 0 | FI8: =FI24-(FI52+FI66) -> 0 | FJ8: =FJ24-(FJ52+FJ66) -> 0 | ... FO8: =FO24-(FO52+FO66) -> 0 | FQ8: =FQ24-(FQ52+FQ66) -> 0 | FR8: =FR24-(FR52+FR66) -> 0 | FS8: =FS24-(FS52+FS66) -> 0 | FT8: =FT24-(FT52+FT66) -> 0 | FU8: =FU24-(FU52+FU66) -> 0 | FV8: =FV24-(FV52+FV66) -> 0 | FW8: =FW24-(FW52+FW66) -> 0 | FX8: =FX24-(FX52+FX66) -> 0 | ... GC8: =GC24-(GC52+GC66) -> 0 | GE8: =GE24-(GE52+GE66) -> 0 | GF8: =GF24-(GF52+GF66) -> 0 | GG8: =GG24-(GG52+GG66) -> 0 | GH8: =GH24-(GH52+GH66) -> 0 | GI8: =GI24-(GI52+GI66) -> 0 | GJ8: =GJ24-(GJ52+GJ66) -> 0 | GK8: =GK24-(GK52+GK66) -> 0 | GL8: =GL24-(GL52+GL66) -> 0 | ... GQ8: =GQ24-(GQ52+GQ66) -> 0 | GS8: =GS24-(GS52+GS66) -> 0 | GT8: =GT24-(GT52+GT66) -> 0 | GU8: =GU24-(GU52+GU66) -> 0 | GV8: =GV24-(GV52+GV66) -> 0 | GW8: =GW24-(GW52+GW66) -> 0 | GX8: =GX24-(GX52+GX66) -> 0 | GY8: =GY24-(GY52+GY66) -> 0 | GZ8: =GZ24-(GZ52+GZ66) -> 0 | ... HE8: =HE24-(HE52+HE66) -> 0 | HG8: =HG24-(HG52+HG66) -> 0 | HH8: =HH24-(HH52+HH66) -> 0 | HI8: =HI24-(HI52+HI66) -> 0 | HJ8: =HJ24-(HJ52+HJ66) -> 0 | HK8: =HK24-(HK52+HK66) -> 0 | HL8: =HL24-(HL52+HL66) -> 0 | HM8: =HM24-(HM52+HM66) -> 0 | HN8: =HN24-(HN52+HN66) -> 0 | ... HS8: =HS24-(HS52+HS66) -> 0 | HU8: =HU24-(HU52+HU66) -> 0 | HV8: =HV24-(HV52+HV66) -> 0 | HW8: =HW24-(HW52+HW66) -> 0 | HX8: =HX24-(HX52+HX66) -> 0 | HY8: =HY24-(HY52+HY66) -> 0 | HZ8: =HZ24-(HZ52+HZ66) -> 0 | IA8: =IA24-(IA52+IA66) -> 0 | IB8: =IB24-(IB52+IB66) -> 0 | ... IG8: =IG24-(IG52+IG66) -> 0
C9: % Diff | L9: =(L10-L8)/L8 -> 2.9063251 | M9: =(M10-M8)/M8 -> 0.24992392 | N9: =(N10-N8)/N8 -> 0.68699348 | O9: =(O10-O8)/O8 -> 0.73632899 | P9: =(P10-P8)/P8 -> 2.9041729 | Q9: =(Q10-Q8)/Q8 -> -0.22552479
C10: Reality | L10: {=SUMPRODUCT( (INDEX(Tracking[Year],0)=$E$6) * (INDEX(Tracking[Month],0)=MONTH(DATEVALUE(L7 & " 1"))) * (INDEX(Tracking[Amount],0)) * (INDEX(Tracking[Type],0)="Income") ) - SUMPRODUCT( (INDEX(Tracking[Year],0)=$E$6) * (INDEX(Tracking[Month],0)=MONTH(DATEVALUE(L7 & " 1"))) * (INDEX(Tracking[Amount],0)) * (INDEX(Tracking[Type],0)="Expenses") )} -> 3057.09 | M10: {=SUMPRODUCT( (INDEX(Tracking[Year],0)=$E$6) * (INDEX(Tracking[Month],0)=MONTH(DATEVALUE(M7 & " 1"))) * (INDEX(Tracking[Amount],0)) * (INDEX(Tracking[Type],0)="Income") ) - SUMPRODUCT( (INDEX(Tracking[Year],0)=$E$6) * (INDEX(Tracking[Month],0)=MONTH(DATEVALUE(M7 & " 1"))) * (INDEX(Tracking[Amount],0)) * (INDEX(Tracking[Type],0)="Expenses") )} -> 5092.69 | N10: {=SUMPRODUCT( (INDEX(Tracking[Year],0)=$E$6) * (INDEX(Tracking[Month],0)=MONTH(DATEVALUE(N7 & " 1"))) * (INDEX(Tracking[Amount],0)) * (INDEX(Tracking[Type],0)="Income") ) - SUMPRODUCT( (INDEX(Tracking[Year],0)=$E$6) * (INDEX(Tracking[Month],0)=MONTH(DATEVALUE(N7 & " 1"))) * (INDEX(Tracking[Amount],0)) * (INDEX(Tracking[Type],0)="Expenses") )} -> 2560.35 | O10: {=SUMPRODUCT( (INDEX(Tracking[Year],0)=$E$6) * (INDEX(Tracking[Month],0)=MONTH(DATEVALUE(O7 & " 1"))) * (INDEX(Tracking[Amount],0)) * (INDEX(Tracking[Type],0)="Income") )- SUMPRODUCT( (INDEX(Tracking[Type],0)=2025) * (INDEX(Tracking[Date],0)=MONTH(DATEVALUE(O7 & " 1"))) * (INDEX(Tracking[Balance],0)) * (INDEX(Tracking[Amount],0)="Expenses") )} -> 12529.35 | P10: {=SUMPRODUCT( (INDEX(Tracking[Year],0)=$E$6) * (INDEX(Tracking[Month],0)=MONTH(DATEVALUE(P7 & " 1"))) * (INDEX(Tracking[Amount],0)) * (INDEX(Tracking[Type],0)="Income") )- SUMPRODUCT( (INDEX(Tracking[Type],0)=2025) * (INDEX(Tracking[Date],0)=MONTH(DATEVALUE(P7 & " 1"))) * (INDEX(Tracking[Balance],0)) * (INDEX(Tracking[Amount],0)="Expenses") )} -> 9075.25 | Q10: 11939
C12: Income | E12: =DATE(E$6,1,1) -> 45658 | F12: =DATE(E$6,2,1) -> 45689 | G12: =DATE(E$6,3,1) -> 45717 | H12: =DATE(E$6,4,1) -> 45748 | I12: =DATE(E$6,5,1) -> 45778 | J12: =DATE(E$6,6,1) -> 45809 | K12: =DATE(E$6,7,1) -> 45839 | L12: =DATE(E$6,8,1) -> 45870 | M12: =DATE(E$6,9,1) -> 45901 | N12: =DATE(E$6,10,1) -> 45931 | O12: =DATE(E$6,11,1) -> 45962 | P12: =DATE(E$6,12,1) -> 45992 | Q12: =E$6 -> 2025 | S12: =DATE(S$6,1,1) -> 46023 | T12: =DATE(S$6,2,1) -> 46054 | U12: =DATE(S$6,3,1) -> 46082 | V12: =DATE(S$6,4,1) -> 46113 | W12: =DATE(S$6,5,1) -> 46143 | X12: =DATE(S$6,6,1) -> 46174 | Y12: =DATE(S$6,7,1) -> 46204 | Z12: =DATE(S$6,8,1) -> 46235 | AA12: =DATE(S$6,9,1) -> 46266 | AB12: =DATE(S$6,10,1) -> 46296 | AC12: =DATE(S$6,11,1) -> 46327 | AD12: =DATE(S$6,12,1) -> 46357 | AE12: =S$6 -> 2026 | AG12: =DATE(AG$6,1,1) -> 46388 | AH12: =DATE(AG$6,2,1) -> 46419 | AI12: =DATE(AG$6,3,1) -> 46447 | AJ12: =DATE(AG$6,4,1) -> 46478 | AK12: =DATE(AG$6,5,1) -> 46508 | AL12: =DATE(AG$6,6,1) -> 46539 | AM12: =DATE(AG$6,7,1) -> 46569 | AN12: =DATE(AG$6,8,1) -> 46600 | AO12: =DATE(AG$6,9,1) -> 46631 | AP12: =DATE(AG$6,10,1) -> 46661 | AQ12: =DATE(AG$6,11,1) -> 46692 | AR12: =DATE(AG$6,12,1) -> 46722 | AS12: =AG$6 -> 2027 | AU12: =DATE(AU$6,1,1) -> 46753 | AV12: =DATE(AU$6,2,1) -> 46784 | AW12: =DATE(AU$6,3,1) -> 46813 | AX12: =DATE(AU$6,4,1) -> 46844 | AY12: =DATE(AU$6,5,1) -> 46874 | AZ12: =DATE(AU$6,6,1) -> 46905 | BA12: =DATE(AU$6,7,1) -> 46935 | BB12: =DATE(AU$6,8,1) -> 46966 | BC12: =DATE(AU$6,9,1) -> 46997 | BD12: =DATE(AU$6,10,1) -> 47027 | BE12: =DATE(AU$6,11,1) -> 47058 | BF12: =DATE(AU$6,12,1) -> 47088 | BG12: =AU$6 -> 2028 | BI12: =DATE(BI$6,1,1) -> 47119 | BJ12: =DATE(BI$6,2,1) -> 47150 | BK12: =DATE(BI$6,3,1) -> 47178 | BL12: =DATE(BI$6,4,1) -> 47209 | BM12: =DATE(BI$6,5,1) -> 47239 | BN12: =DATE(BI$6,6,1) -> 47270 | BO12: =DATE(BI$6,7,1) -> 47300 | BP12: =DATE(BI$6,8,1) -> 47331 | BQ12: =DATE(BI$6,9,1) -> 47362 | BR12: =DATE(BI$6,10,1) -> 47392 | BS12: =DATE(BI$6,11,1) -> 47423 | BT12: =DATE(BI$6,12,1) -> 47453 | BU12: =BI$6 -> 2029 | BW12: =DATE(BW$6,1,1) -> 47484 | BX12: =DATE(BW$6,2,1) -> 47515 | BY12: =DATE(BW$6,3,1) -> 47543 | BZ12: =DATE(BW$6,4,1) -> 47574 | CA12: =DATE(BW$6,5,1) -> 47604 | CB12: =DATE(BW$6,6,1) -> 47635 | CC12: =DATE(BW$6,7,1) -> 47665 | CD12: =DATE(BW$6,8,1) -> 47696 | CE12: =DATE(BW$6,9,1) -> 47727 | CF12: =DATE(BW$6,10,1) -> 47757 | CG12: =DATE(BW$6,11,1) -> 47788 | CH12: =DATE(BW$6,12,1) -> 47818 | CI12: =BW$6 -> 2030 | CK12: =DATE(CK$6,1,1) -> 47849 | CL12: =DATE(CK$6,2,1) -> 47880 | CM12: =DATE(CK$6,3,1) -> 47908 | CN12: =DATE(CK$6,4,1) -> 47939 | CO12: =DATE(CK$6,5,1) -> 47969 | CP12: =DATE(CK$6,6,1) -> 48000 | CQ12: =DATE(CK$6,7,1) -> 48030 | CR12: =DATE(CK$6,8,1) -> 48061 | CS12: =DATE(CK$6,9,1) -> 48092 | CT12: =DATE(CK$6,10,1) -> 48122 | CU12: =DATE(CK$6,11,1) -> 48153 | CV12: =DATE(CK$6,12,1) -> 48183 | CW12: =CK$6 -> 2031 | CY12: =DATE(CY$6,1,1) -> 48214 | CZ12: =DATE(CY$6,2,1) -> 48245 | DA12: =DATE(CY$6,3,1) -> 48274 | DB12: =DATE(CY$6,4,1) -> 48305 | DC12: =DATE(CY$6,5,1) -> 48335 | DD12: =DATE(CY$6,6,1) -> 48366 | DE12: =DATE(CY$6,7,1) -> 48396 | DF12: =DATE(CY$6,8,1) -> 48427 | DG12: =DATE(CY$6,9,1) -> 48458 | DH12: =DATE(CY$6,10,1) -> 48488 | DI12: =DATE(CY$6,11,1) -> 48519 | DJ12: =DATE(CY$6,12,1) -> 48549 | DK12: =CY$6 -> 2032 | DM12: =DATE(DM$6,1,1) -> 48580 | DN12: =DATE(DM$6,2,1) -> 48611 | DO12: =DATE(DM$6,3,1) -> 48639 | DP12: =DATE(DM$6,4,1) -> 48670 | DQ12: =DATE(DM$6,5,1) -> 48700 | DR12: =DATE(DM$6,6,1) -> 48731 | DS12: =DATE(DM$6,7,1) -> 48761 | DT12: =DATE(DM$6,8,1) -> 48792 | DU12: =DATE(DM$6,9,1) -> 48823 | DV12: =DATE(DM$6,10,1) -> 48853 | DW12: =DATE(DM$6,11,1) -> 48884 | DX12: =DATE(DM$6,12,1) -> 48914 | DY12: =DM$6 -> 2033 | EA12: =DATE(EA$6,1,1) -> 48945 | EB12: =DATE(EA$6,2,1) -> 48976 | EC12: =DATE(EA$6,3,1) -> 49004 | ED12: =DATE(EA$6,4,1) -> 49035 | EE12: =DATE(EA$6,5,1) -> 49065 | EF12: =DATE(EA$6,6,1) -> 49096 | EG12: =DATE(EA$6,7,1) -> 49126 | EH12: =DATE(EA$6,8,1) -> 49157 | EI12: =DATE(EA$6,9,1) -> 49188 | EJ12: =DATE(EA$6,10,1) -> 49218 | EK12: =DATE(EA$6,11,1) -> 49249 | EL12: =DATE(EA$6,12,1) -> 49279 | EM12: =EA$6 -> 2034 | EO12: =DATE(EO$6,1,1) -> 49310 | EP12: =DATE(EO$6,2,1) -> 49341 | EQ12: =DATE(EO$6,3,1) -> 49369 | ER12: =DATE(EO$6,4,1) -> 49400 | ES12: =DATE(EO$6,5,1) -> 49430 | ET12: =DATE(EO$6,6,1) -> 49461 | EU12: =DATE(EO$6,7,1) -> 49491 | EV12: =DATE(EO$6,8,1) -> 49522 | EW12: =DATE(EO$6,9,1) -> 49553 | EX12: =DATE(EO$6,10,1) -> 49583 | EY12: =DATE(EO$6,11,1) -> 49614 | EZ12: =DATE(EO$6,12,1) -> 49644 | FA12: =EO$6 -> 2035 | FC12: =DATE(FC$6,1,1) -> 49675 | FD12: =DATE(FC$6,2,1) -> 49706 | FE12: =DATE(FC$6,3,1) -> 49735 | FF12: =DATE(FC$6,4,1) -> 49766 | FG12: =DATE(FC$6,5,1) -> 49796 | FH12: =DATE(FC$6,6,1) -> 49827 | FI12: =DATE(FC$6,7,1) -> 49857 | FJ12: =DATE(FC$6,8,1) -> 49888 | FK12: =DATE(FC$6,9,1) -> 49919 | FL12: =DATE(FC$6,10,1) -> 49949 | FM12: =DATE(FC$6,11,1) -> 49980 | FN12: =DATE(FC$6,12,1) -> 50010 | FO12: =FC$6 -> 2036 | FQ12: =DATE(FQ$6,1,1) -> 50041 | FR12: =DATE(FQ$6,2,1) -> 50072 | FS12: =DATE(FQ$6,3,1) -> 50100 | FT12: =DATE(FQ$6,4,1) -> 50131 | FU12: =DATE(FQ$6,5,1) -> 50161 | FV12: =DATE(FQ$6,6,1) -> 50192 | FW12: =DATE(FQ$6,7,1) -> 50222 | FX12: =DATE(FQ$6,8,1) -> 50253 | FY12: =DATE(FQ$6,9,1) -> 50284 | FZ12: =DATE(FQ$6,10,1) -> 50314 | GA12: =DATE(FQ$6,11,1) -> 50345 | GB12: =DATE(FQ$6,12,1) -> 50375 | GC12: =FQ$6 -> 2037 | GE12: =DATE(GE$6,1,1) -> 50406 | GF12: =DATE(GE$6,2,1) -> 50437 | GG12: =DATE(GE$6,3,1) -> 50465 | GH12: =DATE(GE$6,4,1) -> 50496 | GI12: =DATE(GE$6,5,1) -> 50526 | GJ12: =DATE(GE$6,6,1) -> 50557 | GK12: =DATE(GE$6,7,1) -> 50587 | GL12: =DATE(GE$6,8,1) -> 50618 | GM12: =DATE(GE$6,9,1) -> 50649 | GN12: =DATE(GE$6,10,1) -> 50679 | GO12: =DATE(GE$6,11,1) -> 50710 | GP12: =DATE(GE$6,12,1) -> 50740 | GQ12: =GE$6 -> 2038 | GS12: =DATE(GS$6,1,1) -> 50771 | GT12: =DATE(GS$6,2,1) -> 50802 | GU12: =DATE(GS$6,3,1) -> 50830 | GV12: =DATE(GS$6,4,1) -> 50861 | GW12: =DATE(GS$6,5,1) -> 50891 | GX12: =DATE(GS$6,6,1) -> 50922 | GY12: =DATE(GS$6,7,1) -> 50952 | GZ12: =DATE(GS$6,8,1) -> 50983 | HA12: =DATE(GS$6,9,1) -> 51014 | HB12: =DATE(GS$6,10,1) -> 51044 | HC12: =DATE(GS$6,11,1) -> 51075 | HD12: =DATE(GS$6,12,1) -> 51105 | HE12: =GS$6 -> 2039 | HG12: =DATE(HG$6,1,1) -> 51136 | HH12: =DATE(HG$6,2,1) -> 51167 | HI12: =DATE(HG$6,3,1) -> 51196 | HJ12: =DATE(HG$6,4,1) -> 51227 | HK12: =DATE(HG$6,5,1) -> 51257 | HL12: =DATE(HG$6,6,1) -> 51288 | HM12: =DATE(HG$6,7,1) -> 51318 | HN12: =DATE(HG$6,8,1) -> 51349 | HO12: =DATE(HG$6,9,1) -> 51380 | HP12: =DATE(HG$6,10,1) -> 51410 | HQ12: =DATE(HG$6,11,1) -> 51441 | HR12: =DATE(HG$6,12,1) -> 51471 | HS12: =HG$6 -> 2040 | HU12: =DATE(HU$6,1,1) -> 51502 | HV12: =DATE(HU$6,2,1) -> 51533 | HW12: =DATE(HU$6,3,1) -> 51561 | HX12: =DATE(HU$6,4,1) -> 51592 | HY12: =DATE(HU$6,5,1) -> 51622 | HZ12: =DATE(HU$6,6,1) -> 51653 | IA12: =DATE(HU$6,7,1) -> 51683 | IB12: =DATE(HU$6,8,1) -> 51714 | IC12: =DATE(HU$6,9,1) -> 51745 | ID12: =DATE(HU$6,10,1) -> 51775 | IE12: =DATE(HU$6,11,1) -> 51806 | IF12: =DATE(HU$6,12,1) -> 51836 | IG12: =HU$6 -> 2041
C13: Employment | L13: {=SUMPRODUCT((Tracking[Type]="Income")*(Tracking[Category]=Income[[#This Row],[Income]])*(MONTH(Tracking[Date])=8)*(Tracking[Amount])*1)} -> 3587.1 | M13: {=SUMPRODUCT((Tracking[Type]="Income")*(Tracking[Category]=Income[[#This Row],[Income]])*(MONTH(Tracking[Date])=9)*(Tracking[Amount])*1)} -> 8204.85 | N13: {=SUMPRODUCT((Previsions[Type]="Income")*(Previsions[Cat]="Employment")*(Previsions[Final Budget])*1)} -> 8204.85 | O13: {=SUMPRODUCT((Previsions[Type]="Income")*(Previsions[Cat]="Employment")*(Previsions[Final Budget])*1)} -> 8204.85 | P13: {=SUMPRODUCT((Previsions[Type]="Income")*(Previsions[Cat]="Employment")*(Previsions[Final Budget])*1)} -> 8204.85 | Q13: =SUM(E13:P13) -> 36406.5 | S13: 8205 | T13: 8205 | U13: 8205 | V13: 8205 | W13: 8205 | X13: 8205 | Y13: 8205 | Z13: 8205 | AA13: 8205 | AB13: 8205 | AC13: 8205 | AD13: 8205 | AE13: =SUM(S13:AD13) -> 98460 | AS13: =SUM(AG13:AR13) -> 0 | BG13: =SUM(AU13:BF13) -> 0
C14: Grant Payment | O14: {=SUMPRODUCT((Tracking[Type]="Income")*(Tracking[Category]=Income[[#This Row],[Income]])*(MONTH(Tracking[Date])=11)*(Tracking[Amount])*1)} -> 4000 | Q14: 4000
C15: Side Hustle | L15: {=SUMPRODUCT((Tracking[Type]="Income")*(Tracking[Category]=Income[[#This Row],[Income]])*(MONTH(Tracking[Date])=8)*(Tracking[Amount])*1)} -> 4313.3 | M15: {=SUMPRODUCT((Tracking[Type]="Income")*(Tracking[Category]=Income[[#This Row],[Income]])*(MONTH(Tracking[Date])=9)*(Tracking[Amount])*1)} -> 1699.9 | N15: {=SUMPRODUCT((Tracking[Type]="Income")*(Tracking[Category]=Income[[#This Row],[Income]])*(MONTH(Tracking[Date])=10)*(Tracking[Amount])*1)} -> 0 | O15: {=SUMPRODUCT((Tracking[Type]="Income")*(Tracking[Category]=Income[[#This Row],[Income]])*(MONTH(Tracking[Date])=11)*(Tracking[Amount])*1)} -> 0 | P15: {=SUMPRODUCT((Tracking[Type]="Income")*(Tracking[Category]=Income[[#This Row],[Income]])*(MONTH(Tracking[Date])=12)*(Tracking[Amount])*1)} -> 0 | Q15: =SUM(E15:P15) -> 6013.2 | AE15: =SUM(S15:AD15) -> 0 | AS15: =SUM(AG15:AR15) -> 0 | BG15: =SUM(AU15:BF15) -> 0
C16: Extras / Twint Chargeback | L16: {=SUMPRODUCT((Tracking[Type]="Income")*(Tracking[Category]=Income[[#This Row],[Income]])*(MONTH(Tracking[Date])=8)*(Tracking[Amount])*1)} -> 195.55 | M16: {=SUMPRODUCT((Tracking[Type]="Income")*(Tracking[Category]=Income[[#This Row],[Income]])*(MONTH(Tracking[Date])=9)*(Tracking[Amount])*1)} -> 38 | N16: {=SUMPRODUCT((Tracking[Type]="Income")*(Tracking[Category]=Income[[#This Row],[Income]])*(MONTH(Tracking[Date])=10)*(Tracking[Amount])*1)} -> 71.2 | O16: {=SUMPRODUCT((Tracking[Type]="Income")*(Tracking[Category]=Income[[#This Row],[Income]])*(MONTH(Tracking[Date])=11)*(Tracking[Amount])*1)} -> 324.5 | P16: {=SUMPRODUCT((Tracking[Type]="Income")*(Tracking[Category]=Income[[#This Row],[Income]])*(MONTH(Tracking[Date])=12)*(Tracking[Amount])*1)} -> 531 | Q16: =SUM(E16:P16) -> 1160.25 | AE16: =SUM(S16:AD16) -> 0 | AS16: =SUM(AG16:AR16) -> 0 | BG16: =SUM(AU16:BF16) -> 0 | BU16: =SUM(BI16:BT16) -> 0 | CI16: =SUM(BW16:CH16) -> 0 | CW16: =SUM(CK16:CV16) -> 0 | DK16: =SUM(CY16:DJ16) -> 0 | DY16: =SUM(DM16:DX16) -> 0 | EM16: =SUM(EA16:EL16) -> 0 | FA16: =SUM(EO16:EZ16) -> 0 | FO16: =SUM(FC16:FN16) -> 0 | GC16: =SUM(FQ16:GB16) -> 0 | GQ16: =SUM(GE16:GP16) -> 0 | HE16: =SUM(GS16:HD16) -> 0 | HS16: =SUM(HG16:HR16) -> 0 | IG16: =SUM(HU16:IF16) -> 0
C17: Enter income Category…
C18: Enter income Category…
C19: Enter income Category… | Q19: =SUM(E19:P19) -> 0 | AE19: =SUM(S19:AD19) -> 0 | AS19: =SUM(AG19:AR19) -> 0 | BG19: =SUM(AU19:BF19) -> 0 | BU19: =SUM(BI19:BT19) -> 0 | CI19: =SUM(BW19:CH19) -> 0 | CW19: =SUM(CK19:CV19) -> 0 | DK19: =SUM(CY19:DJ19) -> 0 | DY19: =SUM(DM19:DX19) -> 0 | EM19: =SUM(EA19:EL19) -> 0 | FA19: =SUM(EO19:EZ19) -> 0 | FO19: =SUM(FC19:FN19) -> 0 | GC19: =SUM(FQ19:GB19) -> 0 | GQ19: =SUM(GE19:GP19) -> 0 | HE19: =SUM(GS19:HD19) -> 0 | HS19: =SUM(HG19:HR19) -> 0 | IG19: =SUM(HU19:IF19) -> 0
C20: Enter income Category… | Q20: =SUM(E20:P20) -> 0 | AE20: =SUM(S20:AD20) -> 0 | AS20: =SUM(AG20:AR20) -> 0 | BG20: =SUM(AU20:BF20) -> 0 | BU20: =SUM(BI20:BT20) -> 0 | CI20: =SUM(BW20:CH20) -> 0 | CW20: =SUM(CK20:CV20) -> 0 | DK20: =SUM(CY20:DJ20) -> 0 | DY20: =SUM(DM20:DX20) -> 0 | EM20: =SUM(EA20:EL20) -> 0 | FA20: =SUM(EO20:EZ20) -> 0 | FO20: =SUM(FC20:FN20) -> 0 | GC20: =SUM(FQ20:GB20) -> 0 | GQ20: =SUM(GE20:GP20) -> 0 | HE20: =SUM(GS20:HD20) -> 0 | HS20: =SUM(HG20:HR20) -> 0 | IG20: =SUM(HU20:IF20) -> 0
C21: Enter income Category… | Q21: =SUM(E21:P21) -> 0 | AE21: =SUM(S21:AD21) -> 0 | AS21: =SUM(AG21:AR21) -> 0 | BG21: =SUM(AU21:BF21) -> 0 | BU21: =SUM(BI21:BT21) -> 0 | CI21: =SUM(BW21:CH21) -> 0 | CW21: =SUM(CK21:CV21) -> 0 | DK21: =SUM(CY21:DJ21) -> 0 | DY21: =SUM(DM21:DX21) -> 0 | EM21: =SUM(EA21:EL21) -> 0 | FA21: =SUM(EO21:EZ21) -> 0 | FO21: =SUM(FC21:FN21) -> 0 | GC21: =SUM(FQ21:GB21) -> 0 | GQ21: =SUM(GE21:GP21) -> 0 | HE21: =SUM(GS21:HD21) -> 0 | HS21: =SUM(HG21:HR21) -> 0 | IG21: =SUM(HU21:IF21) -> 0
C22: Enter income Category… | Q22: =SUM(E22:P22) -> 0 | AE22: =SUM(S22:AD22) -> 0 | AS22: =SUM(AG22:AR22) -> 0 | BG22: =SUM(AU22:BF22) -> 0 | BU22: =SUM(BI22:BT22) -> 0 | CI22: =SUM(BW22:CH22) -> 0 | CW22: =SUM(CK22:CV22) -> 0 | DK22: =SUM(CY22:DJ22) -> 0 | DY22: =SUM(DM22:DX22) -> 0 | EM22: =SUM(EA22:EL22) -> 0 | FA22: =SUM(EO22:EZ22) -> 0 | FO22: =SUM(FC22:FN22) -> 0 | GC22: =SUM(FQ22:GB22) -> 0 | GQ22: =SUM(GE22:GP22) -> 0 | HE22: =SUM(GS22:HD22) -> 0 | HS22: =SUM(HG22:HR22) -> 0 | IG22: =SUM(HU22:IF22) -> 0
C23: Enter income Category… | Q23: =SUM(E23:P23) -> 0 | AE23: =SUM(S23:AD23) -> 0 | AS23: =SUM(AG23:AR23) -> 0 | BG23: =SUM(AU23:BF23) -> 0 | BU23: =SUM(BI23:BT23) -> 0 | CI23: =SUM(BW23:CH23) -> 0 | CW23: =SUM(CK23:CV23) -> 0 | DK23: =SUM(CY23:DJ23) -> 0 | DY23: =SUM(DM23:DX23) -> 0 | EM23: =SUM(EA23:EL23) -> 0 | FA23: =SUM(EO23:EZ23) -> 0 | FO23: =SUM(FC23:FN23) -> 0 | GC23: =SUM(FQ23:GB23) -> 0 | GQ23: =SUM(GE23:GP23) -> 0 | HE23: =SUM(GS23:HD23) -> 0 | HS23: =SUM(HG23:HR23) -> 0 | IG23: =SUM(HU23:IF23) -> 0
C24: Total | E24: {=SUM(INDIRECT(ADDRESS(income_min_row, COLUMN()) & ":" & ADDRESS(income_max_row, COLUMN())))} -> 0 | F24: {=SUM(INDIRECT(ADDRESS(income_min_row, COLUMN()) & ":" & ADDRESS(income_max_row, COLUMN())))} -> 0 | G24: {=SUM(INDIRECT(ADDRESS(income_min_row, COLUMN()) & ":" & ADDRESS(income_max_row, COLUMN())))} -> 0 | H24: {=SUM(INDIRECT(ADDRESS(income_min_row, COLUMN()) & ":" & ADDRESS(income_max_row, COLUMN())))} -> 0 | I24: {=SUM(INDIRECT(ADDRESS(income_min_row, COLUMN()) & ":" & ADDRESS(income_max_row, COLUMN())))} -> 0 | J24: {=SUM(INDIRECT(ADDRESS(income_min_row, COLUMN()) & ":" & ADDRESS(income_max_row, COLUMN())))} -> 0 | K24: {=SUM(INDIRECT(ADDRESS(income_min_row, COLUMN()) & ":" & ADDRESS(income_max_row, COLUMN())))} -> 0 | L24: {=SUM(INDIRECT(ADDRESS(income_min_row, COLUMN()) & ":" & ADDRESS(income_max_row, COLUMN())))} -> 8095.95 | ... Q24: {=SUM(INDIRECT(ADDRESS(income_min_row, COLUMN()) & ":" & ADDRESS(income_max_row, COLUMN())))} -> 47579.95 | S24: {=SUM(INDIRECT(ADDRESS(income_min_row, COLUMN()) & ":" & ADDRESS(income_max_row, COLUMN())))} -> 8205 | T24: {=SUM(INDIRECT(ADDRESS(income_min_row, COLUMN()) & ":" & ADDRESS(income_max_row, COLUMN())))} -> 8205 | U24: {=SUM(INDIRECT(ADDRESS(income_min_row, COLUMN()) & ":" & ADDRESS(income_max_row, COLUMN())))} -> 8205 | V24: {=SUM(INDIRECT(ADDRESS(income_min_row, COLUMN()) & ":" & ADDRESS(income_max_row, COLUMN())))} -> 8205 | W24: {=SUM(INDIRECT(ADDRESS(income_min_row, COLUMN()) & ":" & ADDRESS(income_max_row, COLUMN())))} -> 8205 | X24: {=SUM(INDIRECT(ADDRESS(income_min_row, COLUMN()) & ":" & ADDRESS(income_max_row, COLUMN())))} -> 8205 | Y24: {=SUM(INDIRECT(ADDRESS(income_min_row, COLUMN()) & ":" & ADDRESS(income_max_row, COLUMN())))} -> 8205 | Z24: {=SUM(INDIRECT(ADDRESS(income_min_row, COLUMN()) & ":" & ADDRESS(income_max_row, COLUMN())))} -> 8205 | ... AE24: {=SUM(INDIRECT(ADDRESS(income_min_row, COLUMN()) & ":" & ADDRESS(income_max_row, COLUMN())))} -> 98460 | AG24: {=SUM(INDIRECT(ADDRESS(income_min_row, COLUMN()) & ":" & ADDRESS(income_max_row, COLUMN())))} -> 0 | AH24: {=SUM(INDIRECT(ADDRESS(income_min_row, COLUMN()) & ":" & ADDRESS(income_max_row, COLUMN())))} -> 0 | AI24: {=SUM(INDIRECT(ADDRESS(income_min_row, COLUMN()) & ":" & ADDRESS(income_max_row, COLUMN())))} -> 0 | AJ24: {=SUM(INDIRECT(ADDRESS(income_min_row, COLUMN()) & ":" & ADDRESS(income_max_row, COLUMN())))} -> 0 | AK24: {=SUM(INDIRECT(ADDRESS(income_min_row, COLUMN()) & ":" & ADDRESS(income_max_row, COLUMN())))} -> 0 | AL24: {=SUM(INDIRECT(ADDRESS(income_min_row, COLUMN()) & ":" & ADDRESS(income_max_row, COLUMN())))} -> 0 | AM24: {=SUM(INDIRECT(ADDRESS(income_min_row, COLUMN()) & ":" & ADDRESS(income_max_row, COLUMN())))} -> 0 | AN24: {=SUM(INDIRECT(ADDRESS(income_min_row, COLUMN()) & ":" & ADDRESS(income_max_row, COLUMN())))} -> 0 | ... AS24: {=SUM(INDIRECT(ADDRESS(income_min_row, COLUMN()) & ":" & ADDRESS(income_max_row, COLUMN())))} -> 0 | AU24: {=SUM(INDIRECT(ADDRESS(income_min_row, COLUMN()) & ":" & ADDRESS(income_max_row, COLUMN())))} -> 0 | AV24: {=SUM(INDIRECT(ADDRESS(income_min_row, COLUMN()) & ":" & ADDRESS(income_max_row, COLUMN())))} -> 0 | AW24: {=SUM(INDIRECT(ADDRESS(income_min_row, COLUMN()) & ":" & ADDRESS(income_max_row, COLUMN())))} -> 0 | AX24: {=SUM(INDIRECT(ADDRESS(income_min_row, COLUMN()) & ":" & ADDRESS(income_max_row, COLUMN())))} -> 0 | AY24: {=SUM(INDIRECT(ADDRESS(income_min_row, COLUMN()) & ":" & ADDRESS(income_max_row, COLUMN())))} -> 0 | AZ24: {=SUM(INDIRECT(ADDRESS(income_min_row, COLUMN()) & ":" & ADDRESS(income_max_row, COLUMN())))} -> 0 | BA24: {=SUM(INDIRECT(ADDRESS(income_min_row, COLUMN()) & ":" & ADDRESS(income_max_row, COLUMN())))} -> 0 | BB24: {=SUM(INDIRECT(ADDRESS(income_min_row, COLUMN()) & ":" & ADDRESS(income_max_row, COLUMN())))} -> 0 | ... BG24: {=SUM(INDIRECT(ADDRESS(income_min_row, COLUMN()) & ":" & ADDRESS(income_max_row, COLUMN())))} -> 0 | BI24: {=SUM(INDIRECT(ADDRESS(income_min_row, COLUMN()) & ":" & ADDRESS(income_max_row, COLUMN())))} -> 0 | BJ24: {=SUM(INDIRECT(ADDRESS(income_min_row, COLUMN()) & ":" & ADDRESS(income_max_row, COLUMN())))} -> 0 | BK24: {=SUM(INDIRECT(ADDRESS(income_min_row, COLUMN()) & ":" & ADDRESS(income_max_row, COLUMN())))} -> 0 | BL24: {=SUM(INDIRECT(ADDRESS(income_min_row, COLUMN()) & ":" & ADDRESS(income_max_row, COLUMN())))} -> 0 | BM24: {=SUM(INDIRECT(ADDRESS(income_min_row, COLUMN()) & ":" & ADDRESS(income_max_row, COLUMN())))} -> 0 | BN24: {=SUM(INDIRECT(ADDRESS(income_min_row, COLUMN()) & ":" & ADDRESS(income_max_row, COLUMN())))} -> 0 | BO24: {=SUM(INDIRECT(ADDRESS(income_min_row, COLUMN()) & ":" & ADDRESS(income_max_row, COLUMN())))} -> 0 | BP24: {=SUM(INDIRECT(ADDRESS(income_min_row, COLUMN()) & ":" & ADDRESS(income_max_row, COLUMN())))} -> 0 | ... BU24: {=SUM(INDIRECT(ADDRESS(income_min_row, COLUMN()) & ":" & ADDRESS(income_max_row, COLUMN())))} -> 0 | BW24: {=SUM(INDIRECT(ADDRESS(income_min_row, COLUMN()) & ":" & ADDRESS(income_max_row, COLUMN())))} -> 0 | BX24: {=SUM(INDIRECT(ADDRESS(income_min_row, COLUMN()) & ":" & ADDRESS(income_max_row, COLUMN())))} -> 0 | BY24: {=SUM(INDIRECT(ADDRESS(income_min_row, COLUMN()) & ":" & ADDRESS(income_max_row, COLUMN())))} -> 0 | BZ24: {=SUM(INDIRECT(ADDRESS(income_min_row, COLUMN()) & ":" & ADDRESS(income_max_row, COLUMN())))} -> 0 | CA24: {=SUM(INDIRECT(ADDRESS(income_min_row, COLUMN()) & ":" & ADDRESS(income_max_row, COLUMN())))} -> 0 | CB24: {=SUM(INDIRECT(ADDRESS(income_min_row, COLUMN()) & ":" & ADDRESS(income_max_row, COLUMN())))} -> 0 | CC24: {=SUM(INDIRECT(ADDRESS(income_min_row, COLUMN()) & ":" & ADDRESS(income_max_row, COLUMN())))} -> 0 | CD24: {=SUM(INDIRECT(ADDRESS(income_min_row, COLUMN()) & ":" & ADDRESS(income_max_row, COLUMN())))} -> 0 | ... CI24: {=SUM(INDIRECT(ADDRESS(income_min_row, COLUMN()) & ":" & ADDRESS(income_max_row, COLUMN())))} -> 0 | CK24: {=SUM(INDIRECT(ADDRESS(income_min_row, COLUMN()) & ":" & ADDRESS(income_max_row, COLUMN())))} -> 0 | CL24: {=SUM(INDIRECT(ADDRESS(income_min_row, COLUMN()) & ":" & ADDRESS(income_max_row, COLUMN())))} -> 0 | CM24: {=SUM(INDIRECT(ADDRESS(income_min_row, COLUMN()) & ":" & ADDRESS(income_max_row, COLUMN())))} -> 0 | CN24: {=SUM(INDIRECT(ADDRESS(income_min_row, COLUMN()) & ":" & ADDRESS(income_max_row, COLUMN())))} -> 0 | CO24: {=SUM(INDIRECT(ADDRESS(income_min_row, COLUMN()) & ":" & ADDRESS(income_max_row, COLUMN())))} -> 0 | CP24: {=SUM(INDIRECT(ADDRESS(income_min_row, COLUMN()) & ":" & ADDRESS(income_max_row, COLUMN())))} -> 0 | CQ24: {=SUM(INDIRECT(ADDRESS(income_min_row, COLUMN()) & ":" & ADDRESS(income_max_row, COLUMN())))} -> 0 | CR24: {=SUM(INDIRECT(ADDRESS(income_min_row, COLUMN()) & ":" & ADDRESS(income_max_row, COLUMN())))} -> 0 | ... CW24: {=SUM(INDIRECT(ADDRESS(income_min_row, COLUMN()) & ":" & ADDRESS(income_max_row, COLUMN())))} -> 0 | CY24: {=SUM(INDIRECT(ADDRESS(income_min_row, COLUMN()) & ":" & ADDRESS(income_max_row, COLUMN())))} -> 0 | CZ24: {=SUM(INDIRECT(ADDRESS(income_min_row, COLUMN()) & ":" & ADDRESS(income_max_row, COLUMN())))} -> 0 | DA24: {=SUM(INDIRECT(ADDRESS(income_min_row, COLUMN()) & ":" & ADDRESS(income_max_row, COLUMN())))} -> 0 | DB24: {=SUM(INDIRECT(ADDRESS(income_min_row, COLUMN()) & ":" & ADDRESS(income_max_row, COLUMN())))} -> 0 | DC24: {=SUM(INDIRECT(ADDRESS(income_min_row, COLUMN()) & ":" & ADDRESS(income_max_row, COLUMN())))} -> 0 | DD24: {=SUM(INDIRECT(ADDRESS(income_min_row, COLUMN()) & ":" & ADDRESS(income_max_row, COLUMN())))} -> 0 | DE24: {=SUM(INDIRECT(ADDRESS(income_min_row, COLUMN()) & ":" & ADDRESS(income_max_row, COLUMN())))} -> 0 | DF24: {=SUM(INDIRECT(ADDRESS(income_min_row, COLUMN()) & ":" & ADDRESS(income_max_row, COLUMN())))} -> 0 | ... DK24: {=SUM(INDIRECT(ADDRESS(income_min_row, COLUMN()) & ":" & ADDRESS(income_max_row, COLUMN())))} -> 0 | DM24: {=SUM(INDIRECT(ADDRESS(income_min_row, COLUMN()) & ":" & ADDRESS(income_max_row, COLUMN())))} -> 0 | DN24: {=SUM(INDIRECT(ADDRESS(income_min_row, COLUMN()) & ":" & ADDRESS(income_max_row, COLUMN())))} -> 0 | DO24: {=SUM(INDIRECT(ADDRESS(income_min_row, COLUMN()) & ":" & ADDRESS(income_max_row, COLUMN())))} -> 0 | DP24: {=SUM(INDIRECT(ADDRESS(income_min_row, COLUMN()) & ":" & ADDRESS(income_max_row, COLUMN())))} -> 0 | DQ24: {=SUM(INDIRECT(ADDRESS(income_min_row, COLUMN()) & ":" & ADDRESS(income_max_row, COLUMN())))} -> 0 | DR24: {=SUM(INDIRECT(ADDRESS(income_min_row, COLUMN()) & ":" & ADDRESS(income_max_row, COLUMN())))} -> 0 | DS24: {=SUM(INDIRECT(ADDRESS(income_min_row, COLUMN()) & ":" & ADDRESS(income_max_row, COLUMN())))} -> 0 | DT24: {=SUM(INDIRECT(ADDRESS(income_min_row, COLUMN()) & ":" & ADDRESS(income_max_row, COLUMN())))} -> 0 | ... DY24: {=SUM(INDIRECT(ADDRESS(income_min_row, COLUMN()) & ":" & ADDRESS(income_max_row, COLUMN())))} -> 0 | EA24: {=SUM(INDIRECT(ADDRESS(income_min_row, COLUMN()) & ":" & ADDRESS(income_max_row, COLUMN())))} -> 0 | EB24: {=SUM(INDIRECT(ADDRESS(income_min_row, COLUMN()) & ":" & ADDRESS(income_max_row, COLUMN())))} -> 0 | EC24: {=SUM(INDIRECT(ADDRESS(income_min_row, COLUMN()) & ":" & ADDRESS(income_max_row, COLUMN())))} -> 0 | ED24: {=SUM(INDIRECT(ADDRESS(income_min_row, COLUMN()) & ":" & ADDRESS(income_max_row, COLUMN())))} -> 0 | EE24: {=SUM(INDIRECT(ADDRESS(income_min_row, COLUMN()) & ":" & ADDRESS(income_max_row, COLUMN())))} -> 0 | EF24: {=SUM(INDIRECT(ADDRESS(income_min_row, COLUMN()) & ":" & ADDRESS(income_max_row, COLUMN())))} -> 0 | EG24: {=SUM(INDIRECT(ADDRESS(income_min_row, COLUMN()) & ":" & ADDRESS(income_max_row, COLUMN())))} -> 0 | EH24: {=SUM(INDIRECT(ADDRESS(income_min_row, COLUMN()) & ":" & ADDRESS(income_max_row, COLUMN())))} -> 0 | ... EM24: {=SUM(INDIRECT(ADDRESS(income_min_row, COLUMN()) & ":" & ADDRESS(income_max_row, COLUMN())))} -> 0 | EO24: {=SUM(INDIRECT(ADDRESS(income_min_row, COLUMN()) & ":" & ADDRESS(income_max_row, COLUMN())))} -> 0 | EP24: {=SUM(INDIRECT(ADDRESS(income_min_row, COLUMN()) & ":" & ADDRESS(income_max_row, COLUMN())))} -> 0 | EQ24: {=SUM(INDIRECT(ADDRESS(income_min_row, COLUMN()) & ":" & ADDRESS(income_max_row, COLUMN())))} -> 0 | ER24: {=SUM(INDIRECT(ADDRESS(income_min_row, COLUMN()) & ":" & ADDRESS(income_max_row, COLUMN())))} -> 0 | ES24: {=SUM(INDIRECT(ADDRESS(income_min_row, COLUMN()) & ":" & ADDRESS(income_max_row, COLUMN())))} -> 0 | ET24: {=SUM(INDIRECT(ADDRESS(income_min_row, COLUMN()) & ":" & ADDRESS(income_max_row, COLUMN())))} -> 0 | EU24: {=SUM(INDIRECT(ADDRESS(income_min_row, COLUMN()) & ":" & ADDRESS(income_max_row, COLUMN())))} -> 0 | EV24: {=SUM(INDIRECT(ADDRESS(income_min_row, COLUMN()) & ":" & ADDRESS(income_max_row, COLUMN())))} -> 0 | ... FA24: {=SUM(INDIRECT(ADDRESS(income_min_row, COLUMN()) & ":" & ADDRESS(income_max_row, COLUMN())))} -> 0 | FC24: {=SUM(INDIRECT(ADDRESS(income_min_row, COLUMN()) & ":" & ADDRESS(income_max_row, COLUMN())))} -> 0 | FD24: {=SUM(INDIRECT(ADDRESS(income_min_row, COLUMN()) & ":" & ADDRESS(income_max_row, COLUMN())))} -> 0 | FE24: {=SUM(INDIRECT(ADDRESS(income_min_row, COLUMN()) & ":" & ADDRESS(income_max_row, COLUMN())))} -> 0 | FF24: {=SUM(INDIRECT(ADDRESS(income_min_row, COLUMN()) & ":" & ADDRESS(income_max_row, COLUMN())))} -> 0 | FG24: {=SUM(INDIRECT(ADDRESS(income_min_row, COLUMN()) & ":" & ADDRESS(income_max_row, COLUMN())))} -> 0 | FH24: {=SUM(INDIRECT(ADDRESS(income_min_row, COLUMN()) & ":" & ADDRESS(income_max_row, COLUMN())))} -> 0 | FI24: {=SUM(INDIRECT(ADDRESS(income_min_row, COLUMN()) & ":" & ADDRESS(income_max_row, COLUMN())))} -> 0 | FJ24: {=SUM(INDIRECT(ADDRESS(income_min_row, COLUMN()) & ":" & ADDRESS(income_max_row, COLUMN())))} -> 0 | ... FO24: {=SUM(INDIRECT(ADDRESS(income_min_row, COLUMN()) & ":" & ADDRESS(income_max_row, COLUMN())))} -> 0 | FQ24: {=SUM(INDIRECT(ADDRESS(income_min_row, COLUMN()) & ":" & ADDRESS(income_max_row, COLUMN())))} -> 0 | FR24: {=SUM(INDIRECT(ADDRESS(income_min_row, COLUMN()) & ":" & ADDRESS(income_max_row, COLUMN())))} -> 0 | FS24: {=SUM(INDIRECT(ADDRESS(income_min_row, COLUMN()) & ":" & ADDRESS(income_max_row, COLUMN())))} -> 0 | FT24: {=SUM(INDIRECT(ADDRESS(income_min_row, COLUMN()) & ":" & ADDRESS(income_max_row, COLUMN())))} -> 0 | FU24: {=SUM(INDIRECT(ADDRESS(income_min_row, COLUMN()) & ":" & ADDRESS(income_max_row, COLUMN())))} -> 0 | FV24: {=SUM(INDIRECT(ADDRESS(income_min_row, COLUMN()) & ":" & ADDRESS(income_max_row, COLUMN())))} -> 0 | FW24: {=SUM(INDIRECT(ADDRESS(income_min_row, COLUMN()) & ":" & ADDRESS(income_max_row, COLUMN())))} -> 0 | FX24: {=SUM(INDIRECT(ADDRESS(income_min_row, COLUMN()) & ":" & ADDRESS(income_max_row, COLUMN())))} -> 0 | ... GC24: {=SUM(INDIRECT(ADDRESS(income_min_row, COLUMN()) & ":" & ADDRESS(income_max_row, COLUMN())))} -> 0 | GE24: {=SUM(INDIRECT(ADDRESS(income_min_row, COLUMN()) & ":" & ADDRESS(income_max_row, COLUMN())))} -> 0 | GF24: {=SUM(INDIRECT(ADDRESS(income_min_row, COLUMN()) & ":" & ADDRESS(income_max_row, COLUMN())))} -> 0 | GG24: {=SUM(INDIRECT(ADDRESS(income_min_row, COLUMN()) & ":" & ADDRESS(income_max_row, COLUMN())))} -> 0 | GH24: {=SUM(INDIRECT(ADDRESS(income_min_row, COLUMN()) & ":" & ADDRESS(income_max_row, COLUMN())))} -> 0 | GI24: {=SUM(INDIRECT(ADDRESS(income_min_row, COLUMN()) & ":" & ADDRESS(income_max_row, COLUMN())))} -> 0 | GJ24: {=SUM(INDIRECT(ADDRESS(income_min_row, COLUMN()) & ":" & ADDRESS(income_max_row, COLUMN())))} -> 0 | GK24: {=SUM(INDIRECT(ADDRESS(income_min_row, COLUMN()) & ":" & ADDRESS(income_max_row, COLUMN())))} -> 0 | GL24: {=SUM(INDIRECT(ADDRESS(income_min_row, COLUMN()) & ":" & ADDRESS(income_max_row, COLUMN())))} -> 0 | ... GQ24: {=SUM(INDIRECT(ADDRESS(income_min_row, COLUMN()) & ":" & ADDRESS(income_max_row, COLUMN())))} -> 0 | GS24: {=SUM(INDIRECT(ADDRESS(income_min_row, COLUMN()) & ":" & ADDRESS(income_max_row, COLUMN())))} -> 0 | GT24: {=SUM(INDIRECT(ADDRESS(income_min_row, COLUMN()) & ":" & ADDRESS(income_max_row, COLUMN())))} -> 0 | GU24: {=SUM(INDIRECT(ADDRESS(income_min_row, COLUMN()) & ":" & ADDRESS(income_max_row, COLUMN())))} -> 0 | GV24: {=SUM(INDIRECT(ADDRESS(income_min_row, COLUMN()) & ":" & ADDRESS(income_max_row, COLUMN())))} -> 0 | GW24: {=SUM(INDIRECT(ADDRESS(income_min_row, COLUMN()) & ":" & ADDRESS(income_max_row, COLUMN())))} -> 0 | GX24: {=SUM(INDIRECT(ADDRESS(income_min_row, COLUMN()) & ":" & ADDRESS(income_max_row, COLUMN())))} -> 0 | GY24: {=SUM(INDIRECT(ADDRESS(income_min_row, COLUMN()) & ":" & ADDRESS(income_max_row, COLUMN())))} -> 0 | GZ24: {=SUM(INDIRECT(ADDRESS(income_min_row, COLUMN()) & ":" & ADDRESS(income_max_row, COLUMN())))} -> 0 | ... HE24: {=SUM(INDIRECT(ADDRESS(income_min_row, COLUMN()) & ":" & ADDRESS(income_max_row, COLUMN())))} -> 0 | HG24: {=SUM(INDIRECT(ADDRESS(income_min_row, COLUMN()) & ":" & ADDRESS(income_max_row, COLUMN())))} -> 0 | HH24: {=SUM(INDIRECT(ADDRESS(income_min_row, COLUMN()) & ":" & ADDRESS(income_max_row, COLUMN())))} -> 0 | HI24: {=SUM(INDIRECT(ADDRESS(income_min_row, COLUMN()) & ":" & ADDRESS(income_max_row, COLUMN())))} -> 0 | HJ24: {=SUM(INDIRECT(ADDRESS(income_min_row, COLUMN()) & ":" & ADDRESS(income_max_row, COLUMN())))} -> 0 | HK24: {=SUM(INDIRECT(ADDRESS(income_min_row, COLUMN()) & ":" & ADDRESS(income_max_row, COLUMN())))} -> 0 | HL24: {=SUM(INDIRECT(ADDRESS(income_min_row, COLUMN()) & ":" & ADDRESS(income_max_row, COLUMN())))} -> 0 | HM24: {=SUM(INDIRECT(ADDRESS(income_min_row, COLUMN()) & ":" & ADDRESS(income_max_row, COLUMN())))} -> 0 | HN24: {=SUM(INDIRECT(ADDRESS(income_min_row, COLUMN()) & ":" & ADDRESS(income_max_row, COLUMN())))} -> 0 | ... HS24: {=SUM(INDIRECT(ADDRESS(income_min_row, COLUMN()) & ":" & ADDRESS(income_max_row, COLUMN())))} -> 0 | HU24: {=SUM(INDIRECT(ADDRESS(income_min_row, COLUMN()) & ":" & ADDRESS(income_max_row, COLUMN())))} -> 0 | HV24: {=SUM(INDIRECT(ADDRESS(income_min_row, COLUMN()) & ":" & ADDRESS(income_max_row, COLUMN())))} -> 0 | HW24: {=SUM(INDIRECT(ADDRESS(income_min_row, COLUMN()) & ":" & ADDRESS(income_max_row, COLUMN())))} -> 0 | HX24: {=SUM(INDIRECT(ADDRESS(income_min_row, COLUMN()) & ":" & ADDRESS(income_max_row, COLUMN())))} -> 0 | HY24: {=SUM(INDIRECT(ADDRESS(income_min_row, COLUMN()) & ":" & ADDRESS(income_max_row, COLUMN())))} -> 0 | HZ24: {=SUM(INDIRECT(ADDRESS(income_min_row, COLUMN()) & ":" & ADDRESS(income_max_row, COLUMN())))} -> 0 | IA24: {=SUM(INDIRECT(ADDRESS(income_min_row, COLUMN()) & ":" & ADDRESS(income_max_row, COLUMN())))} -> 0 | IB24: {=SUM(INDIRECT(ADDRESS(income_min_row, COLUMN()) & ":" & ADDRESS(income_max_row, COLUMN())))} -> 0 | ... IG24: {=SUM(INDIRECT(ADDRESS(income_min_row, COLUMN()) & ":" & ADDRESS(income_max_row, COLUMN())))} -> 0
C26: Expenses | E26: =DATE(E$6,1,1) -> 45658 | F26: =DATE(E$6,2,1) -> 45689 | G26: =DATE(E$6,3,1) -> 45717 | H26: =DATE(E$6,4,1) -> 45748 | I26: =DATE(E$6,5,1) -> 45778 | J26: =DATE(E$6,6,1) -> 45809 | K26: =DATE(E$6,7,1) -> 45839 | L26: =DATE(E$6,8,1) -> 45870 | M26: =DATE(E$6,9,1) -> 45901 | N26: =DATE(E$6,10,1) -> 45931 | O26: =DATE(E$6,11,1) -> 45962 | P26: =DATE(E$6,12,1) -> 45992 | Q26: =E$6 -> 2025 | S26: =DATE(S$6,1,1) -> 46023 | T26: =DATE(S$6,2,1) -> 46054 | U26: =DATE(S$6,3,1) -> 46082 | V26: =DATE(S$6,4,1) -> 46113 | W26: =DATE(S$6,5,1) -> 46143 | X26: =DATE(S$6,6,1) -> 46174 | Y26: =DATE(S$6,7,1) -> 46204 | Z26: =DATE(S$6,8,1) -> 46235 | AA26: =DATE(S$6,9,1) -> 46266 | AB26: =DATE(S$6,10,1) -> 46296 | AC26: =DATE(S$6,11,1) -> 46327 | AD26: =DATE(S$6,12,1) -> 46357 | AE26: =S$6 -> 2026 | AG26: =DATE(AG$6,1,1) -> 46388 | AH26: =DATE(AG$6,2,1) -> 46419 | AI26: =DATE(AG$6,3,1) -> 46447 | AJ26: =DATE(AG$6,4,1) -> 46478 | AK26: =DATE(AG$6,5,1) -> 46508 | AL26: =DATE(AG$6,6,1) -> 46539 | AM26: =DATE(AG$6,7,1) -> 46569 | AN26: =DATE(AG$6,8,1) -> 46600 | AO26: =DATE(AG$6,9,1) -> 46631 | AP26: =DATE(AG$6,10,1) -> 46661 | AQ26: =DATE(AG$6,11,1) -> 46692 | AR26: =DATE(AG$6,12,1) -> 46722 | AS26: =AG$6 -> 2027 | AU26: =DATE(AU$6,1,1) -> 46753 | AV26: =DATE(AU$6,2,1) -> 46784 | AW26: =DATE(AU$6,3,1) -> 46813 | AX26: =DATE(AU$6,4,1) -> 46844 | AY26: =DATE(AU$6,5,1) -> 46874 | AZ26: =DATE(AU$6,6,1) -> 46905 | BA26: =DATE(AU$6,7,1) -> 46935 | BB26: =DATE(AU$6,8,1) -> 46966 | BC26: =DATE(AU$6,9,1) -> 46997 | BD26: =DATE(AU$6,10,1) -> 47027 | BE26: =DATE(AU$6,11,1) -> 47058 | BF26: =DATE(AU$6,12,1) -> 47088 | BG26: =AU$6 -> 2028 | BI26: =DATE(BI$6,1,1) -> 47119 | BJ26: =DATE(BI$6,2,1) -> 47150 | BK26: =DATE(BI$6,3,1) -> 47178 | BL26: =DATE(BI$6,4,1) -> 47209 | BM26: =DATE(BI$6,5,1) -> 47239 | BN26: =DATE(BI$6,6,1) -> 47270 | BO26: =DATE(BI$6,7,1) -> 47300 | BP26: =DATE(BI$6,8,1) -> 47331 | BQ26: =DATE(BI$6,9,1) -> 47362 | BR26: =DATE(BI$6,10,1) -> 47392 | BS26: =DATE(BI$6,11,1) -> 47423 | BT26: =DATE(BI$6,12,1) -> 47453 | BU26: =BI$6 -> 2029 | BW26: =DATE(BW$6,1,1) -> 47484 | BX26: =DATE(BW$6,2,1) -> 47515 | BY26: =DATE(BW$6,3,1) -> 47543 | BZ26: =DATE(BW$6,4,1) -> 47574 | CA26: =DATE(BW$6,5,1) -> 47604 | CB26: =DATE(BW$6,6,1) -> 47635 | CC26: =DATE(BW$6,7,1) -> 47665 | CD26: =DATE(BW$6,8,1) -> 47696 | CE26: =DATE(BW$6,9,1) -> 47727 | CF26: =DATE(BW$6,10,1) -> 47757 | CG26: =DATE(BW$6,11,1) -> 47788 | CH26: =DATE(BW$6,12,1) -> 47818 | CI26: =BW$6 -> 2030 | CK26: =DATE(CK$6,1,1) -> 47849 | CL26: =DATE(CK$6,2,1) -> 47880 | CM26: =DATE(CK$6,3,1) -> 47908 | CN26: =DATE(CK$6,4,1) -> 47939 | CO26: =DATE(CK$6,5,1) -> 47969 | CP26: =DATE(CK$6,6,1) -> 48000 | CQ26: =DATE(CK$6,7,1) -> 48030 | CR26: =DATE(CK$6,8,1) -> 48061 | CS26: =DATE(CK$6,9,1) -> 48092 | CT26: =DATE(CK$6,10,1) -> 48122 | CU26: =DATE(CK$6,11,1) -> 48153 | CV26: =DATE(CK$6,12,1) -> 48183 | CW26: =CK$6 -> 2031 | CY26: =DATE(CY$6,1,1) -> 48214 | CZ26: =DATE(CY$6,2,1) -> 48245 | DA26: =DATE(CY$6,3,1) -> 48274 | DB26: =DATE(CY$6,4,1) -> 48305 | DC26: =DATE(CY$6,5,1) -> 48335 | DD26: =DATE(CY$6,6,1) -> 48366 | DE26: =DATE(CY$6,7,1) -> 48396 | DF26: =DATE(CY$6,8,1) -> 48427 | DG26: =DATE(CY$6,9,1) -> 48458 | DH26: =DATE(CY$6,10,1) -> 48488 | DI26: =DATE(CY$6,11,1) -> 48519 | DJ26: =DATE(CY$6,12,1) -> 48549 | DK26: =CY$6 -> 2032 | DM26: =DATE(DM$6,1,1) -> 48580 | DN26: =DATE(DM$6,2,1) -> 48611 | DO26: =DATE(DM$6,3,1) -> 48639 | DP26: =DATE(DM$6,4,1) -> 48670 | DQ26: =DATE(DM$6,5,1) -> 48700 | DR26: =DATE(DM$6,6,1) -> 48731 | DS26: =DATE(DM$6,7,1) -> 48761 | DT26: =DATE(DM$6,8,1) -> 48792 | DU26: =DATE(DM$6,9,1) -> 48823 | DV26: =DATE(DM$6,10,1) -> 48853 | DW26: =DATE(DM$6,11,1) -> 48884 | DX26: =DATE(DM$6,12,1) -> 48914 | DY26: =DM$6 -> 2033 | EA26: =DATE(EA$6,1,1) -> 48945 | EB26: =DATE(EA$6,2,1) -> 48976 | EC26: =DATE(EA$6,3,1) -> 49004 | ED26: =DATE(EA$6,4,1) -> 49035 | EE26: =DATE(EA$6,5,1) -> 49065 | EF26: =DATE(EA$6,6,1) -> 49096 | EG26: =DATE(EA$6,7,1) -> 49126 | EH26: =DATE(EA$6,8,1) -> 49157 | EI26: =DATE(EA$6,9,1) -> 49188 | EJ26: =DATE(EA$6,10,1) -> 49218 | EK26: =DATE(EA$6,11,1) -> 49249 | EL26: =DATE(EA$6,12,1) -> 49279 | EM26: =EA$6 -> 2034 | EO26: =DATE(EO$6,1,1) -> 49310 | EP26: =DATE(EO$6,2,1) -> 49341 | EQ26: =DATE(EO$6,3,1) -> 49369 | ER26: =DATE(EO$6,4,1) -> 49400 | ES26: =DATE(EO$6,5,1) -> 49430 | ET26: =DATE(EO$6,6,1) -> 49461 | EU26: =DATE(EO$6,7,1) -> 49491 | EV26: =DATE(EO$6,8,1) -> 49522 | EW26: =DATE(EO$6,9,1) -> 49553 | EX26: =DATE(EO$6,10,1) -> 49583 | EY26: =DATE(EO$6,11,1) -> 49614 | EZ26: =DATE(EO$6,12,1) -> 49644 | FA26: =EO$6 -> 2035 | FC26: =DATE(FC$6,1,1) -> 49675 | FD26: =DATE(FC$6,2,1) -> 49706 | FE26: =DATE(FC$6,3,1) -> 49735 | FF26: =DATE(FC$6,4,1) -> 49766 | FG26: =DATE(FC$6,5,1) -> 49796 | FH26: =DATE(FC$6,6,1) -> 49827 | FI26: =DATE(FC$6,7,1) -> 49857 | FJ26: =DATE(FC$6,8,1) -> 49888 | FK26: =DATE(FC$6,9,1) -> 49919 | FL26: =DATE(FC$6,10,1) -> 49949 | FM26: =DATE(FC$6,11,1) -> 49980 | FN26: =DATE(FC$6,12,1) -> 50010 | FO26: =FC$6 -> 2036 | FQ26: =DATE(FQ$6,1,1) -> 50041 | FR26: =DATE(FQ$6,2,1) -> 50072 | FS26: =DATE(FQ$6,3,1) -> 50100 | FT26: =DATE(FQ$6,4,1) -> 50131 | FU26: =DATE(FQ$6,5,1) -> 50161 | FV26: =DATE(FQ$6,6,1) -> 50192 | FW26: =DATE(FQ$6,7,1) -> 50222 | FX26: =DATE(FQ$6,8,1) -> 50253 | FY26: =DATE(FQ$6,9,1) -> 50284 | FZ26: =DATE(FQ$6,10,1) -> 50314 | GA26: =DATE(FQ$6,11,1) -> 50345 | GB26: =DATE(FQ$6,12,1) -> 50375 | GC26: =FQ$6 -> 2037 | GE26: =DATE(GE$6,1,1) -> 50406 | GF26: =DATE(GE$6,2,1) -> 50437 | GG26: =DATE(GE$6,3,1) -> 50465 | GH26: =DATE(GE$6,4,1) -> 50496 | GI26: =DATE(GE$6,5,1) -> 50526 | GJ26: =DATE(GE$6,6,1) -> 50557 | GK26: =DATE(GE$6,7,1) -> 50587 | GL26: =DATE(GE$6,8,1) -> 50618 | GM26: =DATE(GE$6,9,1) -> 50649 | GN26: =DATE(GE$6,10,1) -> 50679 | GO26: =DATE(GE$6,11,1) -> 50710 | GP26: =DATE(GE$6,12,1) -> 50740 | GQ26: =GE$6 -> 2038 | GS26: =DATE(GS$6,1,1) -> 50771 | GT26: =DATE(GS$6,2,1) -> 50802 | GU26: =DATE(GS$6,3,1) -> 50830 | GV26: =DATE(GS$6,4,1) -> 50861 | GW26: =DATE(GS$6,5,1) -> 50891 | GX26: =DATE(GS$6,6,1) -> 50922 | GY26: =DATE(GS$6,7,1) -> 50952 | GZ26: =DATE(GS$6,8,1) -> 50983 | HA26: =DATE(GS$6,9,1) -> 51014 | HB26: =DATE(GS$6,10,1) -> 51044 | HC26: =DATE(GS$6,11,1) -> 51075 | HD26: =DATE(GS$6,12,1) -> 51105 | HE26: =GS$6 -> 2039 | HG26: =DATE(HG$6,1,1) -> 51136 | HH26: =DATE(HG$6,2,1) -> 51167 | HI26: =DATE(HG$6,3,1) -> 51196 | HJ26: =DATE(HG$6,4,1) -> 51227 | HK26: =DATE(HG$6,5,1) -> 51257 | HL26: =DATE(HG$6,6,1) -> 51288 | HM26: =DATE(HG$6,7,1) -> 51318 | HN26: =DATE(HG$6,8,1) -> 51349 | HO26: =DATE(HG$6,9,1) -> 51380 | HP26: =DATE(HG$6,10,1) -> 51410 | HQ26: =DATE(HG$6,11,1) -> 51441 | HR26: =DATE(HG$6,12,1) -> 51471 | HS26: =HG$6 -> 2040 | HU26: =DATE(HU$6,1,1) -> 51502 | HV26: =DATE(HU$6,2,1) -> 51533 | HW26: =DATE(HU$6,3,1) -> 51561 | HX26: =DATE(HU$6,4,1) -> 51592 | HY26: =DATE(HU$6,5,1) -> 51622 | HZ26: =DATE(HU$6,6,1) -> 51653 | IA26: =DATE(HU$6,7,1) -> 51683 | IB26: =DATE(HU$6,8,1) -> 51714 | IC26: =DATE(HU$6,9,1) -> 51745 | ID26: =DATE(HU$6,10,1) -> 51775 | IE26: =DATE(HU$6,11,1) -> 51806 | IF26: =DATE(HU$6,12,1) -> 51836 | IG26: =HU$6 -> 2041
C27: Housing | L27: {=SUMPRODUCT((Previsions[Type]="Expenses")*(Previsions[Cat]=Expenses[[#This Row],[Expenses]])*(Previsions[Final Budget])*1)} -> 1912 | M27: {=SUMPRODUCT((Previsions[Type]="Expenses")*(Previsions[Cat]=Expenses[[#This Row],[Expenses]])*(Previsions[Final Budget])*1)} -> 1912 | N27: {=SUMPRODUCT((Previsions[Type]="Expenses")*(Previsions[Cat]=Expenses[[#This Row],[Expenses]])*(Previsions[Final Budget])*1)} -> 1912 | O27: {=SUMPRODUCT((Previsions[Type]="Expenses")*(Previsions[Cat]=Expenses[[#This Row],[Expenses]])*(Previsions[Final Budget])*1)} -> 1912 | P27: 1500 | Q27: =SUM(E27:P27) -> 9148 | S27: 1500 | T27: 1500 | U27: 1500 | V27: 1500 | W27: 1500 | X27: 1500 | Y27: 1500 | Z27: 1500 | AA27: 1500 | AB27: 1500 | AC27: 1500 | AD27: 1500 | AE27: =SUM(S27:AD27) -> 18000 | AS27: =SUM(AG27:AR27) -> 0 | BG27: =SUM(AU27:BF27) -> 0 | BU27: =SUM(BI27:BT27) -> 0 | CI27: =SUM(BW27:CH27) -> 0 | CW27: =SUM(CK27:CV27) -> 0 | DK27: =SUM(CY27:DJ27) -> 0 | DY27: =SUM(DM27:DX27) -> 0 | EM27: =SUM(EA27:EL27) -> 0 | FA27: =SUM(EO27:EZ27) -> 0 | FO27: =SUM(FC27:FN27) -> 0 | GC27: =SUM(FQ27:GB27) -> 0 | GQ27: =SUM(GE27:GP27) -> 0 | HE27: =SUM(GS27:HD27) -> 0 | HS27: =SUM(HG27:HR27) -> 0 | IG27: =SUM(HU27:IF27) -> 0
C28: Home Utils | L28: {=SUMPRODUCT((Previsions[Type]="Expenses")*(Previsions[Cat]=Expenses[[#This Row],[Expenses]])*(Previsions[Final Budget])*1)} -> 35 | M28: {=SUMPRODUCT((Previsions[Type]="Expenses")*(Previsions[Cat]=Expenses[[#This Row],[Expenses]])*(Previsions[Final Budget])*1)} -> 35 | N28: {=SUMPRODUCT((Previsions[Type]="Expenses")*(Previsions[Cat]=Expenses[[#This Row],[Expenses]])*(Previsions[Final Budget])*1)} -> 35 | O28: {=SUMPRODUCT((Previsions[Type]="Expenses")*(Previsions[Cat]=Expenses[[#This Row],[Expenses]])*(Previsions[Final Budget])*1)} -> 35 | P28: {=SUMPRODUCT((Previsions[Type]="Expenses")*(Previsions[Cat]=Expenses[[#This Row],[Expenses]])*(Previsions[Final Budget])*1)} -> 35 | Q28: =SUM(E28:P28) -> 175 | AE28: =SUM(S28:AD28) -> 0 | AS28: =SUM(AG28:AR28) -> 0 | BG28: =SUM(AU28:BF28) -> 0 | BU28: =SUM(BI28:BT28) -> 0 | CI28: =SUM(BW28:CH28) -> 0 | CW28: =SUM(CK28:CV28) -> 0 | DK28: =SUM(CY28:DJ28) -> 0 | DY28: =SUM(DM28:DX28) -> 0 | EM28: =SUM(EA28:EL28) -> 0 | FA28: =SUM(EO28:EZ28) -> 0 | FO28: =SUM(FC28:FN28) -> 0 | GC28: =SUM(FQ28:GB28) -> 0 | GQ28: =SUM(GE28:GP28) -> 0 | HE28: =SUM(GS28:HD28) -> 0 | HS28: =SUM(HG28:HR28) -> 0 | IG28: =SUM(HU28:IF28) -> 0
C29: Home Furnitures | P29: 1510 | Q29: 1509.6 | AE29: =SUM(S29:AD29) -> 0
C30: Groceries | L30: {=SUMPRODUCT((Previsions[Type]="Expenses")*(Previsions[Cat]=Expenses[[#This Row],[Expenses]])*(Previsions[Final Budget])*1)} -> 500 | M30: {=SUMPRODUCT((Previsions[Type]="Expenses")*(Previsions[Cat]=Expenses[[#This Row],[Expenses]])*(Previsions[Final Budget])*1)} -> 500 | N30: {=SUMPRODUCT((Previsions[Type]="Expenses")*(Previsions[Cat]=Expenses[[#This Row],[Expenses]])*(Previsions[Final Budget])*1)} -> 500 | O30: {=SUMPRODUCT((Previsions[Type]="Expenses")*(Previsions[Cat]=Expenses[[#This Row],[Expenses]])*(Previsions[Final Budget])*1)} -> 500 | P30: {=SUMPRODUCT((Previsions[Type]="Expenses")*(Previsions[Cat]=Expenses[[#This Row],[Expenses]])*(Previsions[Final Budget])*1)} -> 500 | Q30: =SUM(E30:P30) -> 2500 | S30: 500 | T30: 500 | U30: 500 | V30: 500 | W30: 500 | X30: 500 | Y30: 500 | Z30: 500 | AA30: 500 | AB30: 500 | AC30: 500 | AD30: 500 | AE30: =SUM(S30:AD30) -> 6000 | AS30: =SUM(AG30:AR30) -> 0 | BG30: =SUM(AU30:BF30) -> 0 | BU30: =SUM(BI30:BT30) -> 0 | CI30: =SUM(BW30:CH30) -> 0 | CW30: =SUM(CK30:CV30) -> 0 | DK30: =SUM(CY30:DJ30) -> 0 | DY30: =SUM(DM30:DX30) -> 0 | EM30: =SUM(EA30:EL30) -> 0 | FA30: =SUM(EO30:EZ30) -> 0 | FO30: =SUM(FC30:FN30) -> 0 | GC30: =SUM(FQ30:GB30) -> 0 | GQ30: =SUM(GE30:GP30) -> 0 | HE30: =SUM(GS30:HD30) -> 0 | HS30: =SUM(HG30:HR30) -> 0 | IG30: =SUM(HU30:IF30) -> 0
C31: Restaurants | L31: {=SUMPRODUCT((Previsions[Type]="Expenses")*(Previsions[Cat]=Expenses[[#This Row],[Expenses]])*(Previsions[Final Budget])*1)} -> 600 | M31: {=SUMPRODUCT((Previsions[Type]="Expenses")*(Previsions[Cat]=Expenses[[#This Row],[Expenses]])*(Previsions[Final Budget])*1)} -> 600 | N31: {=SUMPRODUCT((Previsions[Type]="Expenses")*(Previsions[Cat]=Expenses[[#This Row],[Expenses]])*(Previsions[Final Budget])*1)} -> 600 | O31: {=SUMPRODUCT((Previsions[Type]="Expenses")*(Previsions[Cat]=Expenses[[#This Row],[Expenses]])*(Previsions[Final Budget])*1)} -> 600 | P31: {=SUMPRODUCT((Previsions[Type]="Expenses")*(Previsions[Cat]=Expenses[[#This Row],[Expenses]])*(Previsions[Final Budget])*1)} -> 600 | Q31: =SUM(E31:P31) -> 3000 | S31: 600 | T31: 600 | U31: 600 | V31: 600 | W31: 600 | X31: 600 | Y31: 600 | Z31: 600 | AA31: 600 | AB31: 600 | AC31: 600 | AD31: 600 | AE31: =SUM(S31:AD31) -> 7200
C32: Train | L32: {=SUMPRODUCT((Previsions[Type]="Expenses")*(Previsions[Cat]=Expenses[[#This Row],[Expenses]])*(Previsions[Final Budget])*1)} -> 160 | M32: {=SUMPRODUCT((Previsions[Type]="Expenses")*(Previsions[Cat]=Expenses[[#This Row],[Expenses]])*(Previsions[Final Budget])*1)} -> 160 | N32: {=SUMPRODUCT((Previsions[Type]="Expenses")*(Previsions[Cat]=Expenses[[#This Row],[Expenses]])*(Previsions[Final Budget])*1)} -> 160 | O32: {=SUMPRODUCT((Previsions[Type]="Expenses")*(Previsions[Cat]=Expenses[[#This Row],[Expenses]])*(Previsions[Final Budget])*1)} -> 160 | P32: {=SUMPRODUCT((Previsions[Type]="Expenses")*(Previsions[Cat]=Expenses[[#This Row],[Expenses]])*(Previsions[Final Budget])*1)} -> 160 | Q32: =SUM(E32:P32)+500 -> 1300 | S32: 160 | T32: 160 | U32: 160 | V32: 160 | W32: 160 | X32: 160 | Y32: 160 | Z32: 160 | AA32: 160 | AB32: 160 | AC32: 160 | AD32: 160 | AE32: =SUM(S32:AD32) -> 1920 | AS32: =SUM(AG32:AR32) -> 0 | BG32: =SUM(AU32:BF32) -> 0 | BU32: =SUM(BI32:BT32) -> 0 | CI32: =SUM(BW32:CH32) -> 0 | CW32: =SUM(CK32:CV32) -> 0 | DK32: =SUM(CY32:DJ32) -> 0 | DY32: =SUM(DM32:DX32) -> 0 | EM32: =SUM(EA32:EL32) -> 0 | FA32: =SUM(EO32:EZ32) -> 0 | FO32: =SUM(FC32:FN32) -> 0 | GC32: =SUM(FQ32:GB32) -> 0 | GQ32: =SUM(GE32:GP32) -> 0 | HE32: =SUM(GS32:HD32) -> 0 | HS32: =SUM(HG32:HR32) -> 0 | IG32: =SUM(HU32:IF32) -> 0
C33: Internet + Mobile | L33: {=SUMPRODUCT((Previsions[Type]="Expenses")*(Previsions[Cat]=Expenses[[#This Row],[Expenses]])*(Previsions[Final Budget])*1)} -> 80 | M33: {=SUMPRODUCT((Previsions[Type]="Expenses")*(Previsions[Cat]=Expenses[[#This Row],[Expenses]])*(Previsions[Final Budget])*1)} -> 80 | N33: {=SUMPRODUCT((Previsions[Type]="Expenses")*(Previsions[Cat]=Expenses[[#This Row],[Expenses]])*(Previsions[Final Budget])*1)} -> 80 | O33: {=SUMPRODUCT((Previsions[Type]="Expenses")*(Previsions[Cat]=Expenses[[#This Row],[Expenses]])*(Previsions[Final Budget])*1)} -> 80 | P33: {=SUMPRODUCT((Previsions[Type]="Expenses")*(Previsions[Cat]=Expenses[[#This Row],[Expenses]])*(Previsions[Final Budget])*1)} -> 80 | Q33: =SUM(E33:P33) -> 400 | S33: 80 | T33: 80 | U33: 80 | V33: 80 | W33: 80 | X33: 80 | Y33: 80 | Z33: 80 | AA33: 80 | AB33: 80 | AC33: 80 | AD33: 80 | AE33: =SUM(S33:AD33) -> 960
C34: Car | L34: {=SUMPRODUCT((Previsions[Type]="Expenses")*(Previsions[Cat]=Expenses[[#This Row],[Expenses]])*(Previsions[Final Budget])*1)} -> 50 | M34: {=SUMPRODUCT((Previsions[Type]="Expenses")*(Previsions[Cat]=Expenses[[#This Row],[Expenses]])*(Previsions[Final Budget])*1)} -> 50 | N34: {=SUMPRODUCT((Previsions[Type]="Expenses")*(Previsions[Cat]=Expenses[[#This Row],[Expenses]])*(Previsions[Final Budget])*1)} -> 50 | O34: {=SUMPRODUCT((Previsions[Type]="Expenses")*(Previsions[Cat]=Expenses[[#This Row],[Expenses]])*(Previsions[Final Budget])*1)} -> 50 | P34: {=SUMPRODUCT((Previsions[Type]="Expenses")*(Previsions[Cat]=Expenses[[#This Row],[Expenses]])*(Previsions[Final Budget])*1)} -> 50 | Q34: =SUM(E34:P34) -> 250 | AE34: =SUM(S34:AD34) -> 0
C35: Health Insurance | L35: {=SUMPRODUCT((Previsions[Type]="Expenses")*(Previsions[Cat]=Expenses[[#This Row],[Expenses]])*(Previsions[Final Budget])*1)} -> 501.35 | M35: {=SUMPRODUCT((Previsions[Type]="Expenses")*(Previsions[Cat]=Expenses[[#This Row],[Expenses]])*(Previsions[Final Budget])*1)} -> 501.35 | N35: {=SUMPRODUCT((Previsions[Type]="Expenses")*(Previsions[Cat]=Expenses[[#This Row],[Expenses]])*(Previsions[Final Budget])*1)} -> 501.35 | O35: {=SUMPRODUCT((Previsions[Type]="Expenses")*(Previsions[Cat]=Expenses[[#This Row],[Expenses]])*(Previsions[Final Budget])*1)} -> 501.35 | P35: {=SUMPRODUCT((Previsions[Type]="Expenses")*(Previsions[Cat]=Expenses[[#This Row],[Expenses]])*(Previsions[Final Budget])*1)} -> 501.35 | Q35: =SUM(E35:P35) -> 2506.75 | S35: 520 | T35: 520 | U35: 520 | V35: 520 | W35: 520 | X35: 520 | Y35: 520 | Z35: 520 | AA35: 520 | AB35: 520 | AC35: 520 | AD35: 520 | AE35: =SUM(S35:AD35) -> 6240 | AS35: =SUM(AG35:AR35) -> 0 | BG35: =SUM(AU35:BF35) -> 0 | BU35: =SUM(BI35:BT35) -> 0 | CI35: =SUM(BW35:CH35) -> 0 | CW35: =SUM(CK35:CV35) -> 0 | DK35: =SUM(CY35:DJ35) -> 0 | DY35: =SUM(DM35:DX35) -> 0 | EM35: =SUM(EA35:EL35) -> 0 | FA35: =SUM(EO35:EZ35) -> 0 | FO35: =SUM(FC35:FN35) -> 0 | GC35: =SUM(FQ35:GB35) -> 0 | GQ35: =SUM(GE35:GP35) -> 0 | HE35: =SUM(GS35:HD35) -> 0 | HS35: =SUM(HG35:HR35) -> 0 | IG35: =SUM(HU35:IF35) -> 0
C36: Health Other | L36: {=SUMPRODUCT((Previsions[Type]="Expenses")*(Previsions[Cat]=Expenses[[#This Row],[Expenses]])*(Previsions[Final Budget])*1)} -> 100 | M36: {=SUMPRODUCT((Previsions[Type]="Expenses")*(Previsions[Cat]=Expenses[[#This Row],[Expenses]])*(Previsions[Final Budget])*1)} -> 100 | N36: {=SUMPRODUCT((Previsions[Type]="Expenses")*(Previsions[Cat]=Expenses[[#This Row],[Expenses]])*(Previsions[Final Budget])*1)} -> 100 | O36: {=SUMPRODUCT((Previsions[Type]="Expenses")*(Previsions[Cat]=Expenses[[#This Row],[Expenses]])*(Previsions[Final Budget])*1)} -> 100 | P36: {=SUMPRODUCT((Previsions[Type]="Expenses")*(Previsions[Cat]=Expenses[[#This Row],[Expenses]])*(Previsions[Final Budget])*1)} -> 100 | Q36: =SUM(E36:P36) -> 500 | S36: 41.66 | T36: 41.66 | U36: 41.66 | V36: 41.66 | W36: 41.66 | X36: 41.66 | Y36: 41.66 | Z36: 41.66 | AA36: 41.66 | AB36: 41.66 | AC36: 41.66 | AD36: 41.66 | AE36: =SUM(S36:AD36) -> 499.92
C37: Clothing | L37: 100 | M37: 100 | N37: 100 | O37: 100 | P37: 100 | Q37: =SUM(E37:P37) -> 500 | S37: 41.66 | T37: 41.66 | U37: 41.66 | V37: 41.66 | W37: 41.66 | X37: 41.66 | Y37: 41.66 | Z37: 41.66 | AA37: 41.66 | AB37: 41.66 | AC37: 41.66 | AD37: 41.66 | AE37: 500 | AS37: =SUM(AG37:AR37) -> 0 | BG37: =SUM(AU37:BF37) -> 0 | BU37: =SUM(BI37:BT37) -> 0
C38: Media | L38: {=SUMPRODUCT((Previsions[Type]="Expenses")*(Previsions[Cat]=Expenses[[#This Row],[Expenses]])*(Previsions[Final Budget])*1)} -> 0 | M38: {=SUMPRODUCT((Previsions[Type]="Expenses")*(Previsions[Cat]=Expenses[[#This Row],[Expenses]])*(Previsions[Final Budget])*1)} -> 0 | N38: {=SUMPRODUCT((Previsions[Type]="Expenses")*(Previsions[Cat]=Expenses[[#This Row],[Expenses]])*(Previsions[Final Budget])*1)} -> 0 | O38: {=SUMPRODUCT((Previsions[Type]="Expenses")*(Previsions[Cat]=Expenses[[#This Row],[Expenses]])*(Previsions[Final Budget])*1)} -> 0 | P38: {=SUMPRODUCT((Previsions[Type]="Expenses")*(Previsions[Cat]=Expenses[[#This Row],[Expenses]])*(Previsions[Final Budget])*1)} -> 0 | Q38: =SUM(E38:P38) -> 0 | AE38: =SUM(S38:AD38) -> 0 | AS38: =SUM(AG38:AR38) -> 0 | BG38: =SUM(AU38:BF38) -> 0 | BU38: =SUM(BI38:BT38) -> 0
C39: Extras | L39: 200 | M39: 200 | N39: 200 | O39: 200 | P39: 200 | Q39: =SUM(E39:P39) -> 1000 | S39: 150 | T39: 150 | U39: 150 | V39: 150 | W39: 150 | X39: 150 | Y39: 150 | Z39: 150 | AA39: 150 | AB39: 150 | AC39: 150 | AD39: 150 | AE39: =SUM(S39:AD39) -> 1800
C40: Digital Goods | L40: {=SUMPRODUCT((Previsions[Type]="Expenses")*(Previsions[Cat]=Expenses[[#This Row],[Expenses]])*(Previsions[Final Budget])*1)} -> 200 | M40: {=SUMPRODUCT((Previsions[Type]="Expenses")*(Previsions[Cat]=Expenses[[#This Row],[Expenses]])*(Previsions[Final Budget])*1)} -> 200 | N40: {=SUMPRODUCT((Previsions[Type]="Expenses")*(Previsions[Cat]=Expenses[[#This Row],[Expenses]])*(Previsions[Final Budget])*1)} -> 200 | O40: {=SUMPRODUCT((Previsions[Type]="Expenses")*(Previsions[Cat]=Expenses[[#This Row],[Expenses]])*(Previsions[Final Budget])*1)} -> 200 | P40: {=SUMPRODUCT((Previsions[Type]="Expenses")*(Previsions[Cat]=Expenses[[#This Row],[Expenses]])*(Previsions[Final Budget])*1)} -> 200 | Q40: =SUM(E40:P40) -> 1000 | S40: =AE40/12 -> 83.333333 | T40: 83.333333 | U40: 83.333333 | V40: 83.333333 | W40: 83.333333 | X40: 83.333333 | Y40: 83.333333 | Z40: 83.333333 | AA40: 83.333333 | AB40: 83.333333 | AC40: 83.333333 | AD40: 83.333333 | AE40: 1000
C41: Wellbeing | L41: {=SUMPRODUCT((Previsions[Type]="Expenses")*(Previsions[Cat]=Expenses[[#This Row],[Expenses]])*(Previsions[Final Budget])*1)} -> 200 | M41: {=SUMPRODUCT((Previsions[Type]="Expenses")*(Previsions[Cat]=Expenses[[#This Row],[Expenses]])*(Previsions[Final Budget])*1)} -> 200 | N41: {=SUMPRODUCT((Previsions[Type]="Expenses")*(Previsions[Cat]=Expenses[[#This Row],[Expenses]])*(Previsions[Final Budget])*1)} -> 200 | O41: {=SUMPRODUCT((Previsions[Type]="Expenses")*(Previsions[Cat]=Expenses[[#This Row],[Expenses]])*(Previsions[Final Budget])*1)} -> 200 | P41: {=SUMPRODUCT((Previsions[Type]="Expenses")*(Previsions[Cat]=Expenses[[#This Row],[Expenses]])*(Previsions[Final Budget])*1)} -> 200 | Q41: =SUM(E41:P41) -> 1000 | S41: =AE41/12 -> 83.333333 | T41: 83.333333 | U41: 83.333333 | V41: 83.333333 | W41: 83.333333 | X41: 83.333333 | Y41: 83.333333 | Z41: 83.333333 | AA41: 83.333333 | AB41: 83.333333 | AC41: 83.333333 | AD41: 83.333333 | AE41: 1000
C42: Sport | L42: {=SUMPRODUCT((Previsions[Type]="Expenses")*(Previsions[Cat]=Expenses[[#This Row],[Expenses]])*(Previsions[Final Budget])*1)} -> 100 | M42: {=SUMPRODUCT((Previsions[Type]="Expenses")*(Previsions[Cat]=Expenses[[#This Row],[Expenses]])*(Previsions[Final Budget])*1)} -> 100 | N42: {=SUMPRODUCT((Previsions[Type]="Expenses")*(Previsions[Cat]=Expenses[[#This Row],[Expenses]])*(Previsions[Final Budget])*1)} -> 100 | O42: {=SUMPRODUCT((Previsions[Type]="Expenses")*(Previsions[Cat]=Expenses[[#This Row],[Expenses]])*(Previsions[Final Budget])*1)} -> 100 | P42: {=SUMPRODUCT((Previsions[Type]="Expenses")*(Previsions[Cat]=Expenses[[#This Row],[Expenses]])*(Previsions[Final Budget])*1)} -> 100 | Q42: =SUM(E42:P42) -> 500 | S42: =AE42/12 -> 83.333333 | T42: 83.333333 | U42: 83.333333 | V42: 83.333333 | W42: 83.333333 | X42: 83.333333 | Y42: 83.333333 | Z42: 83.333333 | AA42: 83.333333 | AB42: 83.333333 | AC42: 83.333333 | AD42: 83.333333 | AE42: 1000
C43: Travel | L43: {=SUMPRODUCT((Previsions[Type]="Expenses")*(Previsions[Cat]=Expenses[[#This Row],[Expenses]])*(Previsions[Final Budget])*1)} -> 400 | M43: {=SUMPRODUCT((Previsions[Type]="Expenses")*(Previsions[Cat]=Expenses[[#This Row],[Expenses]])*(Previsions[Final Budget])*1)} -> 400 | N43: {=SUMPRODUCT((Previsions[Type]="Expenses")*(Previsions[Cat]=Expenses[[#This Row],[Expenses]])*(Previsions[Final Budget])*1)} -> 400 | O43: {=SUMPRODUCT((Previsions[Type]="Expenses")*(Previsions[Cat]=Expenses[[#This Row],[Expenses]])*(Previsions[Final Budget])*1)} -> 400 | P43: {=SUMPRODUCT((Previsions[Type]="Expenses")*(Previsions[Cat]=Expenses[[#This Row],[Expenses]])*(Previsions[Final Budget])*1)} -> 400 | Q43: 2000 | S43: 420 | T43: 420 | U43: 420 | V43: 420 | W43: 420 | X43: 420 | Y43: 420 | Z43: 420 | AA43: 420 | AB43: 420 | AC43: 420 | AD43: 420 | AE43: =SUM(S43:AD43) -> 5040
C44: Withdraw | L44: {=SUMPRODUCT((Previsions[Type]="Expenses")*(Previsions[Cat]=Expenses[[#This Row],[Expenses]])*(Previsions[Final Budget])*1)} -> 20 | M44: {=SUMPRODUCT((Previsions[Type]="Expenses")*(Previsions[Cat]=Expenses[[#This Row],[Expenses]])*(Previsions[Final Budget])*1)} -> 20 | N44: {=SUMPRODUCT((Previsions[Type]="Expenses")*(Previsions[Cat]=Expenses[[#This Row],[Expenses]])*(Previsions[Final Budget])*1)} -> 20 | O44: {=SUMPRODUCT((Previsions[Type]="Expenses")*(Previsions[Cat]=Expenses[[#This Row],[Expenses]])*(Previsions[Final Budget])*1)} -> 20 | P44: {=SUMPRODUCT((Previsions[Type]="Expenses")*(Previsions[Cat]=Expenses[[#This Row],[Expenses]])*(Previsions[Final Budget])*1)} -> 20 | Q44: =SUM(E44:P44) -> 100 | S44: =100/12 -> 8.3333333 | T44: =100/12 -> 8.3333333 | U44: =100/12 -> 8.3333333 | V44: =100/12 -> 8.3333333 | W44: =100/12 -> 8.3333333 | X44: =100/12 -> 8.3333333 | Y44: =100/12 -> 8.3333333 | Z44: =100/12 -> 8.3333333 | ... AD44: =100/12 -> 8.3333333 | AE44: 100
C45: CC fees | L45: {=SUMPRODUCT((Previsions[Type]="Expenses")*(Previsions[Cat]=Expenses[[#This Row],[Expenses]])*(Previsions[Final Budget])*1)} -> 15 | M45: {=SUMPRODUCT((Previsions[Type]="Expenses")*(Previsions[Cat]=Expenses[[#This Row],[Expenses]])*(Previsions[Final Budget])*1)} -> 15 | N45: {=SUMPRODUCT((Previsions[Type]="Expenses")*(Previsions[Cat]=Expenses[[#This Row],[Expenses]])*(Previsions[Final Budget])*1)} -> 15 | O45: {=SUMPRODUCT((Previsions[Type]="Expenses")*(Previsions[Cat]=Expenses[[#This Row],[Expenses]])*(Previsions[Final Budget])*1)} -> 15 | P45: {=SUMPRODUCT((Previsions[Type]="Expenses")*(Previsions[Cat]=Expenses[[#This Row],[Expenses]])*(Previsions[Final Budget])*1)} -> 15 | Q45: =SUM(E45:P45) -> 75 | S45: 10 | T45: 10 | U45: 10 | V45: 10 | W45: 10 | X45: 10 | Y45: 10 | Z45: 10 | AA45: 10 | AB45: 10 | AC45: 10 | AD45: 10 | AE45: =SUM(S45:AD45) -> 120
C46: Tax | L46: 140 | M46: 140 | N46: 140 | O46: 140 | P46: 140 | Q46: =SUM(E46:P46) -> 700 | AE46: =SUM(S46:AD46) -> 0
C47: Debt | L47: {=SUMPRODUCT((Previsions[Type]="Expenses")*(Previsions[Cat]=Expenses[[#This Row],[Expenses]])*(Previsions[Final Budget])*1)} -> 2000 | M47: 555 | N47: 1445 | Q47: =SUM(E47:P47) -> 4000 | S47: =AE47/12 -> 37.25 | T47: 37 | U47: 37 | V47: 37 | W47: 37 | X47: 37 | Y47: 37 | Z47: 37 | AA47: 37 | AB47: 37 | AC47: 37 | AD47: 37 | AE47: 447 | AS47: =SUM(AG47:AR47) -> 0 | BG47: =SUM(AU47:BF47) -> 0 | BU47: =SUM(BI47:BT47) -> 0 | CI47: =SUM(BW47:CH47) -> 0 | CW47: =SUM(CK47:CV47) -> 0 | DK47: =SUM(CY47:DJ47) -> 0 | DY47: =SUM(DM47:DX47) -> 0 | EM47: =SUM(EA47:EL47) -> 0 | FA47: =SUM(EO47:EZ47) -> 0 | FO47: =SUM(FC47:FN47) -> 0 | GC47: =SUM(FQ47:GB47) -> 0 | GQ47: =SUM(GE47:GP47) -> 0 | HE47: =SUM(GS47:HD47) -> 0 | HS47: =SUM(HG47:HR47) -> 0 | IG47: =SUM(HU47:IF47) -> 0
C48: Enter Expenses Category… | Q48: =SUM(E48:P48) -> 0 | AE48: =SUM(S48:AD48) -> 0 | AS48: =SUM(AG48:AR48) -> 0 | BG48: =SUM(AU48:BF48) -> 0 | BU48: =SUM(BI48:BT48) -> 0 | CI48: =SUM(BW48:CH48) -> 0 | CW48: =SUM(CK48:CV48) -> 0 | DK48: =SUM(CY48:DJ48) -> 0 | DY48: =SUM(DM48:DX48) -> 0 | EM48: =SUM(EA48:EL48) -> 0 | FA48: =SUM(EO48:EZ48) -> 0 | FO48: =SUM(FC48:FN48) -> 0 | GC48: =SUM(FQ48:GB48) -> 0 | GQ48: =SUM(GE48:GP48) -> 0 | HE48: =SUM(GS48:HD48) -> 0 | HS48: =SUM(HG48:HR48) -> 0 | IG48: =SUM(HU48:IF48) -> 0
C49: Enter Expenses Category… | Q49: =SUM(E49:P49) -> 0 | AE49: =SUM(S49:AD49) -> 0 | AS49: =SUM(AG49:AR49) -> 0 | BG49: =SUM(AU49:BF49) -> 0 | BU49: =SUM(BI49:BT49) -> 0 | CI49: =SUM(BW49:CH49) -> 0 | CW49: =SUM(CK49:CV49) -> 0 | DK49: =SUM(CY49:DJ49) -> 0 | DY49: =SUM(DM49:DX49) -> 0 | EM49: =SUM(EA49:EL49) -> 0 | FA49: =SUM(EO49:EZ49) -> 0 | FO49: =SUM(FC49:FN49) -> 0 | GC49: =SUM(FQ49:GB49) -> 0 | GQ49: =SUM(GE49:GP49) -> 0 | HE49: =SUM(GS49:HD49) -> 0 | HS49: =SUM(HG49:HR49) -> 0 | IG49: =SUM(HU49:IF49) -> 0
C50: Enter Expenses Category… | Q50: =SUM(E50:P50) -> 0 | AE50: =SUM(S50:AD50) -> 0 | AS50: =SUM(AG50:AR50) -> 0 | BG50: =SUM(AU50:BF50) -> 0 | BU50: =SUM(BI50:BT50) -> 0 | CI50: =SUM(BW50:CH50) -> 0 | CW50: =SUM(CK50:CV50) -> 0 | DK50: =SUM(CY50:DJ50) -> 0 | DY50: =SUM(DM50:DX50) -> 0 | EM50: =SUM(EA50:EL50) -> 0 | FA50: =SUM(EO50:EZ50) -> 0 | FO50: =SUM(FC50:FN50) -> 0 | GC50: =SUM(FQ50:GB50) -> 0 | GQ50: =SUM(GE50:GP50) -> 0 | HE50: =SUM(GS50:HD50) -> 0 | HS50: =SUM(HG50:HR50) -> 0 | IG50: =SUM(HU50:IF50) -> 0
C51: Enter Expenses Category… | Q51: =SUM(E51:P51) -> 0 | AE51: =SUM(S51:AD51) -> 0 | AS51: =SUM(AG51:AR51) -> 0 | BG51: =SUM(AU51:BF51) -> 0 | BU51: =SUM(BI51:BT51) -> 0 | CI51: =SUM(BW51:CH51) -> 0 | CW51: =SUM(CK51:CV51) -> 0 | DK51: =SUM(CY51:DJ51) -> 0 | DY51: =SUM(DM51:DX51) -> 0 | EM51: =SUM(EA51:EL51) -> 0 | FA51: =SUM(EO51:EZ51) -> 0 | FO51: =SUM(FC51:FN51) -> 0 | GC51: =SUM(FQ51:GB51) -> 0 | GQ51: =SUM(GE51:GP51) -> 0 | HE51: =SUM(GS51:HD51) -> 0 | HS51: =SUM(HG51:HR51) -> 0 | IG51: =SUM(HU51:IF51) -> 0
C52: Total | E52: {=SUM(INDIRECT(ADDRESS(expenses_min_row, COLUMN()) & ":" & ADDRESS(expenses_max_row, COLUMN())))} -> 0 | F52: {=SUM(INDIRECT(ADDRESS(expenses_min_row, COLUMN()) & ":" & ADDRESS(expenses_max_row, COLUMN())))} -> 0 | G52: {=SUM(INDIRECT(ADDRESS(expenses_min_row, COLUMN()) & ":" & ADDRESS(expenses_max_row, COLUMN())))} -> 0 | H52: {=SUM(INDIRECT(ADDRESS(expenses_min_row, COLUMN()) & ":" & ADDRESS(expenses_max_row, COLUMN())))} -> 0 | I52: {=SUM(INDIRECT(ADDRESS(expenses_min_row, COLUMN()) & ":" & ADDRESS(expenses_max_row, COLUMN())))} -> 0 | J52: {=SUM(INDIRECT(ADDRESS(expenses_min_row, COLUMN()) & ":" & ADDRESS(expenses_max_row, COLUMN())))} -> 0 | K52: {=SUM(INDIRECT(ADDRESS(expenses_min_row, COLUMN()) & ":" & ADDRESS(expenses_max_row, COLUMN())))} -> 0 | L52: {=SUM(INDIRECT(ADDRESS(expenses_min_row, COLUMN()) & ":" & ADDRESS(expenses_max_row, COLUMN())))} -> 7313.35 | ... Q52: {=SUM(INDIRECT(ADDRESS(expenses_min_row, COLUMN()) & ":" & ADDRESS(expenses_max_row, COLUMN())))} -> 32164.35 | S52: {=SUM(INDIRECT(ADDRESS(expenses_min_row, COLUMN()) & ":" & ADDRESS(expenses_max_row, COLUMN())))} -> 4318.9033 | T52: {=SUM(INDIRECT(ADDRESS(expenses_min_row, COLUMN()) & ":" & ADDRESS(expenses_max_row, COLUMN())))} -> 4318.6533 | U52: {=SUM(INDIRECT(ADDRESS(expenses_min_row, COLUMN()) & ":" & ADDRESS(expenses_max_row, COLUMN())))} -> 4318.6533 | V52: {=SUM(INDIRECT(ADDRESS(expenses_min_row, COLUMN()) & ":" & ADDRESS(expenses_max_row, COLUMN())))} -> 4318.6533 | W52: {=SUM(INDIRECT(ADDRESS(expenses_min_row, COLUMN()) & ":" & ADDRESS(expenses_max_row, COLUMN())))} -> 4318.6533 | X52: {=SUM(INDIRECT(ADDRESS(expenses_min_row, COLUMN()) & ":" & ADDRESS(expenses_max_row, COLUMN())))} -> 4318.6533 | Y52: {=SUM(INDIRECT(ADDRESS(expenses_min_row, COLUMN()) & ":" & ADDRESS(expenses_max_row, COLUMN())))} -> 4318.6533 | Z52: {=SUM(INDIRECT(ADDRESS(expenses_min_row, COLUMN()) & ":" & ADDRESS(expenses_max_row, COLUMN())))} -> 4318.6533 | ... AE52: {=SUM(INDIRECT(ADDRESS(expenses_min_row, COLUMN()) & ":" & ADDRESS(expenses_max_row, COLUMN())))} -> 51826.92 | AG52: {=SUM(INDIRECT(ADDRESS(expenses_min_row, COLUMN()) & ":" & ADDRESS(expenses_max_row, COLUMN())))} -> 0 | AH52: {=SUM(INDIRECT(ADDRESS(expenses_min_row, COLUMN()) & ":" & ADDRESS(expenses_max_row, COLUMN())))} -> 0 | AI52: {=SUM(INDIRECT(ADDRESS(expenses_min_row, COLUMN()) & ":" & ADDRESS(expenses_max_row, COLUMN())))} -> 0 | AJ52: {=SUM(INDIRECT(ADDRESS(expenses_min_row, COLUMN()) & ":" & ADDRESS(expenses_max_row, COLUMN())))} -> 0 | AK52: {=SUM(INDIRECT(ADDRESS(expenses_min_row, COLUMN()) & ":" & ADDRESS(expenses_max_row, COLUMN())))} -> 0 | AL52: {=SUM(INDIRECT(ADDRESS(expenses_min_row, COLUMN()) & ":" & ADDRESS(expenses_max_row, COLUMN())))} -> 0 | AM52: {=SUM(INDIRECT(ADDRESS(expenses_min_row, COLUMN()) & ":" & ADDRESS(expenses_max_row, COLUMN())))} -> 0 | AN52: {=SUM(INDIRECT(ADDRESS(expenses_min_row, COLUMN()) & ":" & ADDRESS(expenses_max_row, COLUMN())))} -> 0 | ... AS52: {=SUM(INDIRECT(ADDRESS(expenses_min_row, COLUMN()) & ":" & ADDRESS(expenses_max_row, COLUMN())))} -> 0 | AU52: {=SUM(INDIRECT(ADDRESS(expenses_min_row, COLUMN()) & ":" & ADDRESS(expenses_max_row, COLUMN())))} -> 0 | AV52: {=SUM(INDIRECT(ADDRESS(expenses_min_row, COLUMN()) & ":" & ADDRESS(expenses_max_row, COLUMN())))} -> 0 | AW52: {=SUM(INDIRECT(ADDRESS(expenses_min_row, COLUMN()) & ":" & ADDRESS(expenses_max_row, COLUMN())))} -> 0 | AX52: {=SUM(INDIRECT(ADDRESS(expenses_min_row, COLUMN()) & ":" & ADDRESS(expenses_max_row, COLUMN())))} -> 0 | AY52: {=SUM(INDIRECT(ADDRESS(expenses_min_row, COLUMN()) & ":" & ADDRESS(expenses_max_row, COLUMN())))} -> 0 | AZ52: {=SUM(INDIRECT(ADDRESS(expenses_min_row, COLUMN()) & ":" & ADDRESS(expenses_max_row, COLUMN())))} -> 0 | BA52: {=SUM(INDIRECT(ADDRESS(expenses_min_row, COLUMN()) & ":" & ADDRESS(expenses_max_row, COLUMN())))} -> 0 | BB52: {=SUM(INDIRECT(ADDRESS(expenses_min_row, COLUMN()) & ":" & ADDRESS(expenses_max_row, COLUMN())))} -> 0 | ... BG52: {=SUM(INDIRECT(ADDRESS(expenses_min_row, COLUMN()) & ":" & ADDRESS(expenses_max_row, COLUMN())))} -> 0 | BI52: {=SUM(INDIRECT(ADDRESS(expenses_min_row, COLUMN()) & ":" & ADDRESS(expenses_max_row, COLUMN())))} -> 0 | BJ52: {=SUM(INDIRECT(ADDRESS(expenses_min_row, COLUMN()) & ":" & ADDRESS(expenses_max_row, COLUMN())))} -> 0 | BK52: {=SUM(INDIRECT(ADDRESS(expenses_min_row, COLUMN()) & ":" & ADDRESS(expenses_max_row, COLUMN())))} -> 0 | BL52: {=SUM(INDIRECT(ADDRESS(expenses_min_row, COLUMN()) & ":" & ADDRESS(expenses_max_row, COLUMN())))} -> 0 | BM52: {=SUM(INDIRECT(ADDRESS(expenses_min_row, COLUMN()) & ":" & ADDRESS(expenses_max_row, COLUMN())))} -> 0 | BN52: {=SUM(INDIRECT(ADDRESS(expenses_min_row, COLUMN()) & ":" & ADDRESS(expenses_max_row, COLUMN())))} -> 0 | BO52: {=SUM(INDIRECT(ADDRESS(expenses_min_row, COLUMN()) & ":" & ADDRESS(expenses_max_row, COLUMN())))} -> 0 | BP52: {=SUM(INDIRECT(ADDRESS(expenses_min_row, COLUMN()) & ":" & ADDRESS(expenses_max_row, COLUMN())))} -> 0 | ... BU52: {=SUM(INDIRECT(ADDRESS(expenses_min_row, COLUMN()) & ":" & ADDRESS(expenses_max_row, COLUMN())))} -> 0 | BW52: {=SUM(INDIRECT(ADDRESS(expenses_min_row, COLUMN()) & ":" & ADDRESS(expenses_max_row, COLUMN())))} -> 0 | BX52: {=SUM(INDIRECT(ADDRESS(expenses_min_row, COLUMN()) & ":" & ADDRESS(expenses_max_row, COLUMN())))} -> 0 | BY52: {=SUM(INDIRECT(ADDRESS(expenses_min_row, COLUMN()) & ":" & ADDRESS(expenses_max_row, COLUMN())))} -> 0 | BZ52: {=SUM(INDIRECT(ADDRESS(expenses_min_row, COLUMN()) & ":" & ADDRESS(expenses_max_row, COLUMN())))} -> 0 | CA52: {=SUM(INDIRECT(ADDRESS(expenses_min_row, COLUMN()) & ":" & ADDRESS(expenses_max_row, COLUMN())))} -> 0 | CB52: {=SUM(INDIRECT(ADDRESS(expenses_min_row, COLUMN()) & ":" & ADDRESS(expenses_max_row, COLUMN())))} -> 0 | CC52: {=SUM(INDIRECT(ADDRESS(expenses_min_row, COLUMN()) & ":" & ADDRESS(expenses_max_row, COLUMN())))} -> 0 | CD52: {=SUM(INDIRECT(ADDRESS(expenses_min_row, COLUMN()) & ":" & ADDRESS(expenses_max_row, COLUMN())))} -> 0 | ... CI52: {=SUM(INDIRECT(ADDRESS(expenses_min_row, COLUMN()) & ":" & ADDRESS(expenses_max_row, COLUMN())))} -> 0 | CK52: {=SUM(INDIRECT(ADDRESS(expenses_min_row, COLUMN()) & ":" & ADDRESS(expenses_max_row, COLUMN())))} -> 0 | CL52: {=SUM(INDIRECT(ADDRESS(expenses_min_row, COLUMN()) & ":" & ADDRESS(expenses_max_row, COLUMN())))} -> 0 | CM52: {=SUM(INDIRECT(ADDRESS(expenses_min_row, COLUMN()) & ":" & ADDRESS(expenses_max_row, COLUMN())))} -> 0 | CN52: {=SUM(INDIRECT(ADDRESS(expenses_min_row, COLUMN()) & ":" & ADDRESS(expenses_max_row, COLUMN())))} -> 0 | CO52: {=SUM(INDIRECT(ADDRESS(expenses_min_row, COLUMN()) & ":" & ADDRESS(expenses_max_row, COLUMN())))} -> 0 | CP52: {=SUM(INDIRECT(ADDRESS(expenses_min_row, COLUMN()) & ":" & ADDRESS(expenses_max_row, COLUMN())))} -> 0 | CQ52: {=SUM(INDIRECT(ADDRESS(expenses_min_row, COLUMN()) & ":" & ADDRESS(expenses_max_row, COLUMN())))} -> 0 | CR52: {=SUM(INDIRECT(ADDRESS(expenses_min_row, COLUMN()) & ":" & ADDRESS(expenses_max_row, COLUMN())))} -> 0 | ... CW52: {=SUM(INDIRECT(ADDRESS(expenses_min_row, COLUMN()) & ":" & ADDRESS(expenses_max_row, COLUMN())))} -> 0 | CY52: {=SUM(INDIRECT(ADDRESS(expenses_min_row, COLUMN()) & ":" & ADDRESS(expenses_max_row, COLUMN())))} -> 0 | CZ52: {=SUM(INDIRECT(ADDRESS(expenses_min_row, COLUMN()) & ":" & ADDRESS(expenses_max_row, COLUMN())))} -> 0 | DA52: {=SUM(INDIRECT(ADDRESS(expenses_min_row, COLUMN()) & ":" & ADDRESS(expenses_max_row, COLUMN())))} -> 0 | DB52: {=SUM(INDIRECT(ADDRESS(expenses_min_row, COLUMN()) & ":" & ADDRESS(expenses_max_row, COLUMN())))} -> 0 | DC52: {=SUM(INDIRECT(ADDRESS(expenses_min_row, COLUMN()) & ":" & ADDRESS(expenses_max_row, COLUMN())))} -> 0 | DD52: {=SUM(INDIRECT(ADDRESS(expenses_min_row, COLUMN()) & ":" & ADDRESS(expenses_max_row, COLUMN())))} -> 0 | DE52: {=SUM(INDIRECT(ADDRESS(expenses_min_row, COLUMN()) & ":" & ADDRESS(expenses_max_row, COLUMN())))} -> 0 | DF52: {=SUM(INDIRECT(ADDRESS(expenses_min_row, COLUMN()) & ":" & ADDRESS(expenses_max_row, COLUMN())))} -> 0 | ... DK52: {=SUM(INDIRECT(ADDRESS(expenses_min_row, COLUMN()) & ":" & ADDRESS(expenses_max_row, COLUMN())))} -> 0 | DM52: {=SUM(INDIRECT(ADDRESS(expenses_min_row, COLUMN()) & ":" & ADDRESS(expenses_max_row, COLUMN())))} -> 0 | DN52: {=SUM(INDIRECT(ADDRESS(expenses_min_row, COLUMN()) & ":" & ADDRESS(expenses_max_row, COLUMN())))} -> 0 | DO52: {=SUM(INDIRECT(ADDRESS(expenses_min_row, COLUMN()) & ":" & ADDRESS(expenses_max_row, COLUMN())))} -> 0 | DP52: {=SUM(INDIRECT(ADDRESS(expenses_min_row, COLUMN()) & ":" & ADDRESS(expenses_max_row, COLUMN())))} -> 0 | DQ52: {=SUM(INDIRECT(ADDRESS(expenses_min_row, COLUMN()) & ":" & ADDRESS(expenses_max_row, COLUMN())))} -> 0 | DR52: {=SUM(INDIRECT(ADDRESS(expenses_min_row, COLUMN()) & ":" & ADDRESS(expenses_max_row, COLUMN())))} -> 0 | DS52: {=SUM(INDIRECT(ADDRESS(expenses_min_row, COLUMN()) & ":" & ADDRESS(expenses_max_row, COLUMN())))} -> 0 | DT52: {=SUM(INDIRECT(ADDRESS(expenses_min_row, COLUMN()) & ":" & ADDRESS(expenses_max_row, COLUMN())))} -> 0 | ... DY52: {=SUM(INDIRECT(ADDRESS(expenses_min_row, COLUMN()) & ":" & ADDRESS(expenses_max_row, COLUMN())))} -> 0 | EA52: {=SUM(INDIRECT(ADDRESS(expenses_min_row, COLUMN()) & ":" & ADDRESS(expenses_max_row, COLUMN())))} -> 0 | EB52: {=SUM(INDIRECT(ADDRESS(expenses_min_row, COLUMN()) & ":" & ADDRESS(expenses_max_row, COLUMN())))} -> 0 | EC52: {=SUM(INDIRECT(ADDRESS(expenses_min_row, COLUMN()) & ":" & ADDRESS(expenses_max_row, COLUMN())))} -> 0 | ED52: {=SUM(INDIRECT(ADDRESS(expenses_min_row, COLUMN()) & ":" & ADDRESS(expenses_max_row, COLUMN())))} -> 0 | EE52: {=SUM(INDIRECT(ADDRESS(expenses_min_row, COLUMN()) & ":" & ADDRESS(expenses_max_row, COLUMN())))} -> 0 | EF52: {=SUM(INDIRECT(ADDRESS(expenses_min_row, COLUMN()) & ":" & ADDRESS(expenses_max_row, COLUMN())))} -> 0 | EG52: {=SUM(INDIRECT(ADDRESS(expenses_min_row, COLUMN()) & ":" & ADDRESS(expenses_max_row, COLUMN())))} -> 0 | EH52: {=SUM(INDIRECT(ADDRESS(expenses_min_row, COLUMN()) & ":" & ADDRESS(expenses_max_row, COLUMN())))} -> 0 | ... EM52: {=SUM(INDIRECT(ADDRESS(expenses_min_row, COLUMN()) & ":" & ADDRESS(expenses_max_row, COLUMN())))} -> 0 | EO52: {=SUM(INDIRECT(ADDRESS(expenses_min_row, COLUMN()) & ":" & ADDRESS(expenses_max_row, COLUMN())))} -> 0 | EP52: {=SUM(INDIRECT(ADDRESS(expenses_min_row, COLUMN()) & ":" & ADDRESS(expenses_max_row, COLUMN())))} -> 0 | EQ52: {=SUM(INDIRECT(ADDRESS(expenses_min_row, COLUMN()) & ":" & ADDRESS(expenses_max_row, COLUMN())))} -> 0 | ER52: {=SUM(INDIRECT(ADDRESS(expenses_min_row, COLUMN()) & ":" & ADDRESS(expenses_max_row, COLUMN())))} -> 0 | ES52: {=SUM(INDIRECT(ADDRESS(expenses_min_row, COLUMN()) & ":" & ADDRESS(expenses_max_row, COLUMN())))} -> 0 | ET52: {=SUM(INDIRECT(ADDRESS(expenses_min_row, COLUMN()) & ":" & ADDRESS(expenses_max_row, COLUMN())))} -> 0 | EU52: {=SUM(INDIRECT(ADDRESS(expenses_min_row, COLUMN()) & ":" & ADDRESS(expenses_max_row, COLUMN())))} -> 0 | EV52: {=SUM(INDIRECT(ADDRESS(expenses_min_row, COLUMN()) & ":" & ADDRESS(expenses_max_row, COLUMN())))} -> 0 | ... FA52: {=SUM(INDIRECT(ADDRESS(expenses_min_row, COLUMN()) & ":" & ADDRESS(expenses_max_row, COLUMN())))} -> 0 | FC52: {=SUM(INDIRECT(ADDRESS(expenses_min_row, COLUMN()) & ":" & ADDRESS(expenses_max_row, COLUMN())))} -> 0 | FD52: {=SUM(INDIRECT(ADDRESS(expenses_min_row, COLUMN()) & ":" & ADDRESS(expenses_max_row, COLUMN())))} -> 0 | FE52: {=SUM(INDIRECT(ADDRESS(expenses_min_row, COLUMN()) & ":" & ADDRESS(expenses_max_row, COLUMN())))} -> 0 | FF52: {=SUM(INDIRECT(ADDRESS(expenses_min_row, COLUMN()) & ":" & ADDRESS(expenses_max_row, COLUMN())))} -> 0 | FG52: {=SUM(INDIRECT(ADDRESS(expenses_min_row, COLUMN()) & ":" & ADDRESS(expenses_max_row, COLUMN())))} -> 0 | FH52: {=SUM(INDIRECT(ADDRESS(expenses_min_row, COLUMN()) & ":" & ADDRESS(expenses_max_row, COLUMN())))} -> 0 | FI52: {=SUM(INDIRECT(ADDRESS(expenses_min_row, COLUMN()) & ":" & ADDRESS(expenses_max_row, COLUMN())))} -> 0 | FJ52: {=SUM(INDIRECT(ADDRESS(expenses_min_row, COLUMN()) & ":" & ADDRESS(expenses_max_row, COLUMN())))} -> 0 | ... FO52: {=SUM(INDIRECT(ADDRESS(expenses_min_row, COLUMN()) & ":" & ADDRESS(expenses_max_row, COLUMN())))} -> 0 | FQ52: {=SUM(INDIRECT(ADDRESS(expenses_min_row, COLUMN()) & ":" & ADDRESS(expenses_max_row, COLUMN())))} -> 0 | FR52: {=SUM(INDIRECT(ADDRESS(expenses_min_row, COLUMN()) & ":" & ADDRESS(expenses_max_row, COLUMN())))} -> 0 | FS52: {=SUM(INDIRECT(ADDRESS(expenses_min_row, COLUMN()) & ":" & ADDRESS(expenses_max_row, COLUMN())))} -> 0 | FT52: {=SUM(INDIRECT(ADDRESS(expenses_min_row, COLUMN()) & ":" & ADDRESS(expenses_max_row, COLUMN())))} -> 0 | FU52: {=SUM(INDIRECT(ADDRESS(expenses_min_row, COLUMN()) & ":" & ADDRESS(expenses_max_row, COLUMN())))} -> 0 | FV52: {=SUM(INDIRECT(ADDRESS(expenses_min_row, COLUMN()) & ":" & ADDRESS(expenses_max_row, COLUMN())))} -> 0 | FW52: {=SUM(INDIRECT(ADDRESS(expenses_min_row, COLUMN()) & ":" & ADDRESS(expenses_max_row, COLUMN())))} -> 0 | FX52: {=SUM(INDIRECT(ADDRESS(expenses_min_row, COLUMN()) & ":" & ADDRESS(expenses_max_row, COLUMN())))} -> 0 | ... GC52: {=SUM(INDIRECT(ADDRESS(expenses_min_row, COLUMN()) & ":" & ADDRESS(expenses_max_row, COLUMN())))} -> 0 | GE52: {=SUM(INDIRECT(ADDRESS(expenses_min_row, COLUMN()) & ":" & ADDRESS(expenses_max_row, COLUMN())))} -> 0 | GF52: {=SUM(INDIRECT(ADDRESS(expenses_min_row, COLUMN()) & ":" & ADDRESS(expenses_max_row, COLUMN())))} -> 0 | GG52: {=SUM(INDIRECT(ADDRESS(expenses_min_row, COLUMN()) & ":" & ADDRESS(expenses_max_row, COLUMN())))} -> 0 | GH52: {=SUM(INDIRECT(ADDRESS(expenses_min_row, COLUMN()) & ":" & ADDRESS(expenses_max_row, COLUMN())))} -> 0 | GI52: {=SUM(INDIRECT(ADDRESS(expenses_min_row, COLUMN()) & ":" & ADDRESS(expenses_max_row, COLUMN())))} -> 0 | GJ52: {=SUM(INDIRECT(ADDRESS(expenses_min_row, COLUMN()) & ":" & ADDRESS(expenses_max_row, COLUMN())))} -> 0 | GK52: {=SUM(INDIRECT(ADDRESS(expenses_min_row, COLUMN()) & ":" & ADDRESS(expenses_max_row, COLUMN())))} -> 0 | GL52: {=SUM(INDIRECT(ADDRESS(expenses_min_row, COLUMN()) & ":" & ADDRESS(expenses_max_row, COLUMN())))} -> 0 | ... GQ52: {=SUM(INDIRECT(ADDRESS(expenses_min_row, COLUMN()) & ":" & ADDRESS(expenses_max_row, COLUMN())))} -> 0 | GS52: {=SUM(INDIRECT(ADDRESS(expenses_min_row, COLUMN()) & ":" & ADDRESS(expenses_max_row, COLUMN())))} -> 0 | GT52: {=SUM(INDIRECT(ADDRESS(expenses_min_row, COLUMN()) & ":" & ADDRESS(expenses_max_row, COLUMN())))} -> 0 | GU52: {=SUM(INDIRECT(ADDRESS(expenses_min_row, COLUMN()) & ":" & ADDRESS(expenses_max_row, COLUMN())))} -> 0 | GV52: {=SUM(INDIRECT(ADDRESS(expenses_min_row, COLUMN()) & ":" & ADDRESS(expenses_max_row, COLUMN())))} -> 0 | GW52: {=SUM(INDIRECT(ADDRESS(expenses_min_row, COLUMN()) & ":" & ADDRESS(expenses_max_row, COLUMN())))} -> 0 | GX52: {=SUM(INDIRECT(ADDRESS(expenses_min_row, COLUMN()) & ":" & ADDRESS(expenses_max_row, COLUMN())))} -> 0 | GY52: {=SUM(INDIRECT(ADDRESS(expenses_min_row, COLUMN()) & ":" & ADDRESS(expenses_max_row, COLUMN())))} -> 0 | GZ52: {=SUM(INDIRECT(ADDRESS(expenses_min_row, COLUMN()) & ":" & ADDRESS(expenses_max_row, COLUMN())))} -> 0 | ... HE52: {=SUM(INDIRECT(ADDRESS(expenses_min_row, COLUMN()) & ":" & ADDRESS(expenses_max_row, COLUMN())))} -> 0 | HG52: {=SUM(INDIRECT(ADDRESS(expenses_min_row, COLUMN()) & ":" & ADDRESS(expenses_max_row, COLUMN())))} -> 0 | HH52: {=SUM(INDIRECT(ADDRESS(expenses_min_row, COLUMN()) & ":" & ADDRESS(expenses_max_row, COLUMN())))} -> 0 | HI52: {=SUM(INDIRECT(ADDRESS(expenses_min_row, COLUMN()) & ":" & ADDRESS(expenses_max_row, COLUMN())))} -> 0 | HJ52: {=SUM(INDIRECT(ADDRESS(expenses_min_row, COLUMN()) & ":" & ADDRESS(expenses_max_row, COLUMN())))} -> 0 | HK52: {=SUM(INDIRECT(ADDRESS(expenses_min_row, COLUMN()) & ":" & ADDRESS(expenses_max_row, COLUMN())))} -> 0 | HL52: {=SUM(INDIRECT(ADDRESS(expenses_min_row, COLUMN()) & ":" & ADDRESS(expenses_max_row, COLUMN())))} -> 0 | HM52: {=SUM(INDIRECT(ADDRESS(expenses_min_row, COLUMN()) & ":" & ADDRESS(expenses_max_row, COLUMN())))} -> 0 | HN52: {=SUM(INDIRECT(ADDRESS(expenses_min_row, COLUMN()) & ":" & ADDRESS(expenses_max_row, COLUMN())))} -> 0 | ... HS52: {=SUM(INDIRECT(ADDRESS(expenses_min_row, COLUMN()) & ":" & ADDRESS(expenses_max_row, COLUMN())))} -> 0 | HU52: {=SUM(INDIRECT(ADDRESS(expenses_min_row, COLUMN()) & ":" & ADDRESS(expenses_max_row, COLUMN())))} -> 0 | HV52: {=SUM(INDIRECT(ADDRESS(expenses_min_row, COLUMN()) & ":" & ADDRESS(expenses_max_row, COLUMN())))} -> 0 | HW52: {=SUM(INDIRECT(ADDRESS(expenses_min_row, COLUMN()) & ":" & ADDRESS(expenses_max_row, COLUMN())))} -> 0 | HX52: {=SUM(INDIRECT(ADDRESS(expenses_min_row, COLUMN()) & ":" & ADDRESS(expenses_max_row, COLUMN())))} -> 0 | HY52: {=SUM(INDIRECT(ADDRESS(expenses_min_row, COLUMN()) & ":" & ADDRESS(expenses_max_row, COLUMN())))} -> 0 | HZ52: {=SUM(INDIRECT(ADDRESS(expenses_min_row, COLUMN()) & ":" & ADDRESS(expenses_max_row, COLUMN())))} -> 0 | IA52: {=SUM(INDIRECT(ADDRESS(expenses_min_row, COLUMN()) & ":" & ADDRESS(expenses_max_row, COLUMN())))} -> 0 | IB52: {=SUM(INDIRECT(ADDRESS(expenses_min_row, COLUMN()) & ":" & ADDRESS(expenses_max_row, COLUMN())))} -> 0 | ... IG52: {=SUM(INDIRECT(ADDRESS(expenses_min_row, COLUMN()) & ":" & ADDRESS(expenses_max_row, COLUMN())))} -> 0
C54: Savings | E54: =DATE(E$6,1,1) -> 45658 | F54: =DATE(E$6,2,1) -> 45689 | G54: =DATE(E$6,3,1) -> 45717 | H54: =DATE(E$6,4,1) -> 45748 | I54: =DATE(E$6,5,1) -> 45778 | J54: =DATE(E$6,6,1) -> 45809 | K54: =DATE(E$6,7,1) -> 45839 | L54: =DATE(E$6,8,1) -> 45870 | M54: =DATE(E$6,9,1) -> 45901 | N54: =DATE(E$6,10,1) -> 45931 | O54: =DATE(E$6,11,1) -> 45962 | P54: =DATE(E$6,12,1) -> 45992 | Q54: =E$6 -> 2025 | S54: =DATE(S$6,1,1) -> 46023 | T54: =DATE(S$6,2,1) -> 46054 | U54: =DATE(S$6,3,1) -> 46082 | V54: =DATE(S$6,4,1) -> 46113 | W54: =DATE(S$6,5,1) -> 46143 | X54: =DATE(S$6,6,1) -> 46174 | Y54: =DATE(S$6,7,1) -> 46204 | Z54: =DATE(S$6,8,1) -> 46235 | AA54: =DATE(S$6,9,1) -> 46266 | AB54: =DATE(S$6,10,1) -> 46296 | AC54: =DATE(S$6,11,1) -> 46327 | AD54: =DATE(S$6,12,1) -> 46357 | AE54: =S$6 -> 2026 | AG54: =DATE(AG$6,1,1) -> 46388 | AH54: =DATE(AG$6,2,1) -> 46419 | AI54: =DATE(AG$6,3,1) -> 46447 | AJ54: =DATE(AG$6,4,1) -> 46478 | AK54: =DATE(AG$6,5,1) -> 46508 | AL54: =DATE(AG$6,6,1) -> 46539 | AM54: =DATE(AG$6,7,1) -> 46569 | AN54: =DATE(AG$6,8,1) -> 46600 | AO54: =DATE(AG$6,9,1) -> 46631 | AP54: =DATE(AG$6,10,1) -> 46661 | AQ54: =DATE(AG$6,11,1) -> 46692 | AR54: =DATE(AG$6,12,1) -> 46722 | AS54: =AG$6 -> 2027 | AU54: =DATE(AU$6,1,1) -> 46753 | AV54: =DATE(AU$6,2,1) -> 46784 | AW54: =DATE(AU$6,3,1) -> 46813 | AX54: =DATE(AU$6,4,1) -> 46844 | AY54: =DATE(AU$6,5,1) -> 46874 | AZ54: =DATE(AU$6,6,1) -> 46905 | BA54: =DATE(AU$6,7,1) -> 46935 | BB54: =DATE(AU$6,8,1) -> 46966 | BC54: =DATE(AU$6,9,1) -> 46997 | BD54: =DATE(AU$6,10,1) -> 47027 | BE54: =DATE(AU$6,11,1) -> 47058 | BF54: =DATE(AU$6,12,1) -> 47088 | BG54: =AU$6 -> 2028 | BI54: =DATE(BI$6,1,1) -> 47119 | BJ54: =DATE(BI$6,2,1) -> 47150 | BK54: =DATE(BI$6,3,1) -> 47178 | BL54: =DATE(BI$6,4,1) -> 47209 | BM54: =DATE(BI$6,5,1) -> 47239 | BN54: =DATE(BI$6,6,1) -> 47270 | BO54: =DATE(BI$6,7,1) -> 47300 | BP54: =DATE(BI$6,8,1) -> 47331 | BQ54: =DATE(BI$6,9,1) -> 47362 | BR54: =DATE(BI$6,10,1) -> 47392 | BS54: =DATE(BI$6,11,1) -> 47423 | BT54: =DATE(BI$6,12,1) -> 47453 | BU54: =BI$6 -> 2029 | BW54: =DATE(BW$6,1,1) -> 47484 | BX54: =DATE(BW$6,2,1) -> 47515 | BY54: =DATE(BW$6,3,1) -> 47543 | BZ54: =DATE(BW$6,4,1) -> 47574 | CA54: =DATE(BW$6,5,1) -> 47604 | CB54: =DATE(BW$6,6,1) -> 47635 | CC54: =DATE(BW$6,7,1) -> 47665 | CD54: =DATE(BW$6,8,1) -> 47696 | CE54: =DATE(BW$6,9,1) -> 47727 | CF54: =DATE(BW$6,10,1) -> 47757 | CG54: =DATE(BW$6,11,1) -> 47788 | CH54: =DATE(BW$6,12,1) -> 47818 | CI54: =BW$6 -> 2030 | CK54: =DATE(CK$6,1,1) -> 47849 | CL54: =DATE(CK$6,2,1) -> 47880 | CM54: =DATE(CK$6,3,1) -> 47908 | CN54: =DATE(CK$6,4,1) -> 47939 | CO54: =DATE(CK$6,5,1) -> 47969 | CP54: =DATE(CK$6,6,1) -> 48000 | CQ54: =DATE(CK$6,7,1) -> 48030 | CR54: =DATE(CK$6,8,1) -> 48061 | CS54: =DATE(CK$6,9,1) -> 48092 | CT54: =DATE(CK$6,10,1) -> 48122 | CU54: =DATE(CK$6,11,1) -> 48153 | CV54: =DATE(CK$6,12,1) -> 48183 | CW54: =CK$6 -> 2031 | CY54: =DATE(CY$6,1,1) -> 48214 | CZ54: =DATE(CY$6,2,1) -> 48245 | DA54: =DATE(CY$6,3,1) -> 48274 | DB54: =DATE(CY$6,4,1) -> 48305 | DC54: =DATE(CY$6,5,1) -> 48335 | DD54: =DATE(CY$6,6,1) -> 48366 | DE54: =DATE(CY$6,7,1) -> 48396 | DF54: =DATE(CY$6,8,1) -> 48427 | DG54: =DATE(CY$6,9,1) -> 48458 | DH54: =DATE(CY$6,10,1) -> 48488 | DI54: =DATE(CY$6,11,1) -> 48519 | DJ54: =DATE(CY$6,12,1) -> 48549 | DK54: =CY$6 -> 2032 | DM54: =DATE(DM$6,1,1) -> 48580 | DN54: =DATE(DM$6,2,1) -> 48611 | DO54: =DATE(DM$6,3,1) -> 48639 | DP54: =DATE(DM$6,4,1) -> 48670 | DQ54: =DATE(DM$6,5,1) -> 48700 | DR54: =DATE(DM$6,6,1) -> 48731 | DS54: =DATE(DM$6,7,1) -> 48761 | DT54: =DATE(DM$6,8,1) -> 48792 | DU54: =DATE(DM$6,9,1) -> 48823 | DV54: =DATE(DM$6,10,1) -> 48853 | DW54: =DATE(DM$6,11,1) -> 48884 | DX54: =DATE(DM$6,12,1) -> 48914 | DY54: =DM$6 -> 2033 | EA54: =DATE(EA$6,1,1) -> 48945 | EB54: =DATE(EA$6,2,1) -> 48976 | EC54: =DATE(EA$6,3,1) -> 49004 | ED54: =DATE(EA$6,4,1) -> 49035 | EE54: =DATE(EA$6,5,1) -> 49065 | EF54: =DATE(EA$6,6,1) -> 49096 | EG54: =DATE(EA$6,7,1) -> 49126 | EH54: =DATE(EA$6,8,1) -> 49157 | EI54: =DATE(EA$6,9,1) -> 49188 | EJ54: =DATE(EA$6,10,1) -> 49218 | EK54: =DATE(EA$6,11,1) -> 49249 | EL54: =DATE(EA$6,12,1) -> 49279 | EM54: =EA$6 -> 2034 | EO54: =DATE(EO$6,1,1) -> 49310 | EP54: =DATE(EO$6,2,1) -> 49341 | EQ54: =DATE(EO$6,3,1) -> 49369 | ER54: =DATE(EO$6,4,1) -> 49400 | ES54: =DATE(EO$6,5,1) -> 49430 | ET54: =DATE(EO$6,6,1) -> 49461 | EU54: =DATE(EO$6,7,1) -> 49491 | EV54: =DATE(EO$6,8,1) -> 49522 | EW54: =DATE(EO$6,9,1) -> 49553 | EX54: =DATE(EO$6,10,1) -> 49583 | EY54: =DATE(EO$6,11,1) -> 49614 | EZ54: =DATE(EO$6,12,1) -> 49644 | FA54: =EO$6 -> 2035 | FC54: =DATE(FC$6,1,1) -> 49675 | FD54: =DATE(FC$6,2,1) -> 49706 | FE54: =DATE(FC$6,3,1) -> 49735 | FF54: =DATE(FC$6,4,1) -> 49766 | FG54: =DATE(FC$6,5,1) -> 49796 | FH54: =DATE(FC$6,6,1) -> 49827 | FI54: =DATE(FC$6,7,1) -> 49857 | FJ54: =DATE(FC$6,8,1) -> 49888 | FK54: =DATE(FC$6,9,1) -> 49919 | FL54: =DATE(FC$6,10,1) -> 49949 | FM54: =DATE(FC$6,11,1) -> 49980 | FN54: =DATE(FC$6,12,1) -> 50010 | FO54: =FC$6 -> 2036 | FQ54: =DATE(FQ$6,1,1) -> 50041 | FR54: =DATE(FQ$6,2,1) -> 50072 | FS54: =DATE(FQ$6,3,1) -> 50100 | FT54: =DATE(FQ$6,4,1) -> 50131 | FU54: =DATE(FQ$6,5,1) -> 50161 | FV54: =DATE(FQ$6,6,1) -> 50192 | FW54: =DATE(FQ$6,7,1) -> 50222 | FX54: =DATE(FQ$6,8,1) -> 50253 | FY54: =DATE(FQ$6,9,1) -> 50284 | FZ54: =DATE(FQ$6,10,1) -> 50314 | GA54: =DATE(FQ$6,11,1) -> 50345 | GB54: =DATE(FQ$6,12,1) -> 50375 | GC54: =FQ$6 -> 2037 | GE54: =DATE(GE$6,1,1) -> 50406 | GF54: =DATE(GE$6,2,1) -> 50437 | GG54: =DATE(GE$6,3,1) -> 50465 | GH54: =DATE(GE$6,4,1) -> 50496 | GI54: =DATE(GE$6,5,1) -> 50526 | GJ54: =DATE(GE$6,6,1) -> 50557 | GK54: =DATE(GE$6,7,1) -> 50587 | GL54: =DATE(GE$6,8,1) -> 50618 | GM54: =DATE(GE$6,9,1) -> 50649 | GN54: =DATE(GE$6,10,1) -> 50679 | GO54: =DATE(GE$6,11,1) -> 50710 | GP54: =DATE(GE$6,12,1) -> 50740 | GQ54: =GE$6 -> 2038 | GS54: =DATE(GS$6,1,1) -> 50771 | GT54: =DATE(GS$6,2,1) -> 50802 | GU54: =DATE(GS$6,3,1) -> 50830 | GV54: =DATE(GS$6,4,1) -> 50861 | GW54: =DATE(GS$6,5,1) -> 50891 | GX54: =DATE(GS$6,6,1) -> 50922 | GY54: =DATE(GS$6,7,1) -> 50952 | GZ54: =DATE(GS$6,8,1) -> 50983 | HA54: =DATE(GS$6,9,1) -> 51014 | HB54: =DATE(GS$6,10,1) -> 51044 | HC54: =DATE(GS$6,11,1) -> 51075 | HD54: =DATE(GS$6,12,1) -> 51105 | HE54: =GS$6 -> 2039 | HG54: =DATE(HG$6,1,1) -> 51136 | HH54: =DATE(HG$6,2,1) -> 51167 | HI54: =DATE(HG$6,3,1) -> 51196 | HJ54: =DATE(HG$6,4,1) -> 51227 | HK54: =DATE(HG$6,5,1) -> 51257 | HL54: =DATE(HG$6,6,1) -> 51288 | HM54: =DATE(HG$6,7,1) -> 51318 | HN54: =DATE(HG$6,8,1) -> 51349 | HO54: =DATE(HG$6,9,1) -> 51380 | HP54: =DATE(HG$6,10,1) -> 51410 | HQ54: =DATE(HG$6,11,1) -> 51441 | HR54: =DATE(HG$6,12,1) -> 51471 | HS54: =HG$6 -> 2040 | HU54: =DATE(HU$6,1,1) -> 51502 | HV54: =DATE(HU$6,2,1) -> 51533 | HW54: =DATE(HU$6,3,1) -> 51561 | HX54: =DATE(HU$6,4,1) -> 51592 | HY54: =DATE(HU$6,5,1) -> 51622 | HZ54: =DATE(HU$6,6,1) -> 51653 | IA54: =DATE(HU$6,7,1) -> 51683 | IB54: =DATE(HU$6,8,1) -> 51714 | IC54: =DATE(HU$6,9,1) -> 51745 | ID54: =DATE(HU$6,10,1) -> 51775 | IE54: =DATE(HU$6,11,1) -> 51806 | IF54: =DATE(HU$6,12,1) -> 51836 | IG54: =HU$6 -> 2041
C55: Rent Guarantee | Q55: =SUM(E55:P55) -> 0 | AE55: =SUM(S55:AD55) -> 0 | AS55: =SUM(AG55:AR55) -> 0 | BG55: =SUM(AU55:BF55) -> 0 | BU55: =SUM(BI55:BT55) -> 0 | CI55: =SUM(BW55:CH55) -> 0 | CW55: =SUM(CK55:CV55) -> 0 | DK55: =SUM(CY55:DJ55) -> 0 | DY55: =SUM(DM55:DX55) -> 0 | EM55: =SUM(EA55:EL55) -> 0 | FA55: =SUM(EO55:EZ55) -> 0 | FO55: =SUM(FC55:FN55) -> 0 | GC55: =SUM(FQ55:GB55) -> 0 | GQ55: =SUM(GE55:GP55) -> 0 | HE55: =SUM(GS55:HD55) -> 0 | HS55: =SUM(HG55:HR55) -> 0 | IG55: =SUM(HU55:IF55) -> 0
C56: Emergency Fund
C57: Retirement Account | Q57: =SUM(E57:P57) -> 0 | AE57: =SUM(S57:AD57) -> 0 | AS57: =SUM(AG57:AR57) -> 0 | BG57: =SUM(AU57:BF57) -> 0 | BU57: =SUM(BI57:BT57) -> 0 | CI57: =SUM(BW57:CH57) -> 0 | CW57: =SUM(CK57:CV57) -> 0 | DK57: =SUM(CY57:DJ57) -> 0 | DY57: =SUM(DM57:DX57) -> 0 | EM57: =SUM(EA57:EL57) -> 0 | FA57: =SUM(EO57:EZ57) -> 0 | FO57: =SUM(FC57:FN57) -> 0 | GC57: =SUM(FQ57:GB57) -> 0 | GQ57: =SUM(GE57:GP57) -> 0 | HE57: =SUM(GS57:HD57) -> 0 | HS57: =SUM(HG57:HR57) -> 0 | IG57: =SUM(HU57:IF57) -> 0
C58: Stock Portofolio | Q58: =SUM(E58:P58) -> 0 | AE58: =SUM(S58:AD58) -> 0 | AS58: =SUM(AG58:AR58) -> 0 | BG58: =SUM(AU58:BF58) -> 0 | BU58: =SUM(BI58:BT58) -> 0 | CI58: =SUM(BW58:CH58) -> 0 | CW58: =SUM(CK58:CV58) -> 0 | DK58: =SUM(CY58:DJ58) -> 0 | DY58: =SUM(DM58:DX58) -> 0 | EM58: =SUM(EA58:EL58) -> 0 | FA58: =SUM(EO58:EZ58) -> 0 | FO58: =SUM(FC58:FN58) -> 0 | GC58: =SUM(FQ58:GB58) -> 0 | GQ58: =SUM(GE58:GP58) -> 0 | HE58: =SUM(GS58:HD58) -> 0 | HS58: =SUM(HG58:HR58) -> 0 | IG58: =SUM(HU58:IF58) -> 0
C59: Sinking Fund Dow Payment | Q59: =SUM(E59:P59) -> 0 | AE59: =SUM(S59:AD59) -> 0 | AS59: =SUM(AG59:AR59) -> 0 | BG59: =SUM(AU59:BF59) -> 0 | BU59: =SUM(BI59:BT59) -> 0 | CI59: =SUM(BW59:CH59) -> 0 | CW59: =SUM(CK59:CV59) -> 0 | DK59: =SUM(CY59:DJ59) -> 0 | DY59: =SUM(DM59:DX59) -> 0 | EM59: =SUM(EA59:EL59) -> 0 | FA59: =SUM(EO59:EZ59) -> 0 | FO59: =SUM(FC59:FN59) -> 0 | GC59: =SUM(FQ59:GB59) -> 0 | GQ59: =SUM(GE59:GP59) -> 0 | HE59: =SUM(GS59:HD59) -> 0 | HS59: =SUM(HG59:HR59) -> 0 | IG59: =SUM(HU59:IF59) -> 0
C60: Sinking Fund Rest | Q60: =SUM(E60:P60) -> 0 | AE60: =SUM(S60:AD60) -> 0 | AS60: =SUM(AG60:AR60) -> 0 | BG60: =SUM(AU60:BF60) -> 0 | BU60: =SUM(BI60:BT60) -> 0 | CI60: =SUM(BW60:CH60) -> 0 | CW60: =SUM(CK60:CV60) -> 0 | DK60: =SUM(CY60:DJ60) -> 0 | DY60: =SUM(DM60:DX60) -> 0 | EM60: =SUM(EA60:EL60) -> 0 | FA60: =SUM(EO60:EZ60) -> 0 | FO60: =SUM(FC60:FN60) -> 0 | GC60: =SUM(FQ60:GB60) -> 0 | GQ60: =SUM(GE60:GP60) -> 0 | HE60: =SUM(GS60:HD60) -> 0 | HS60: =SUM(HG60:HR60) -> 0 | IG60: =SUM(HU60:IF60) -> 0
C61: Enter Savings Category… | Q61: =SUM(E61:P61) -> 0 | AE61: =SUM(S61:AD61) -> 0 | AS61: =SUM(AG61:AR61) -> 0 | BG61: =SUM(AU61:BF61) -> 0 | BU61: =SUM(BI61:BT61) -> 0 | CI61: =SUM(BW61:CH61) -> 0 | CW61: =SUM(CK61:CV61) -> 0 | DK61: =SUM(CY61:DJ61) -> 0 | DY61: =SUM(DM61:DX61) -> 0 | EM61: =SUM(EA61:EL61) -> 0 | FA61: =SUM(EO61:EZ61) -> 0 | FO61: =SUM(FC61:FN61) -> 0 | GC61: =SUM(FQ61:GB61) -> 0 | GQ61: =SUM(GE61:GP61) -> 0 | HE61: =SUM(GS61:HD61) -> 0 | HS61: =SUM(HG61:HR61) -> 0 | IG61: =SUM(HU61:IF61) -> 0
C62: Enter Savings Category… | Q62: =SUM(E62:P62) -> 0 | AE62: =SUM(S62:AD62) -> 0 | AS62: =SUM(AG62:AR62) -> 0 | BG62: =SUM(AU62:BF62) -> 0 | BU62: =SUM(BI62:BT62) -> 0 | CI62: =SUM(BW62:CH62) -> 0 | CW62: =SUM(CK62:CV62) -> 0 | DK62: =SUM(CY62:DJ62) -> 0 | DY62: =SUM(DM62:DX62) -> 0 | EM62: =SUM(EA62:EL62) -> 0 | FA62: =SUM(EO62:EZ62) -> 0 | FO62: =SUM(FC62:FN62) -> 0 | GC62: =SUM(FQ62:GB62) -> 0 | GQ62: =SUM(GE62:GP62) -> 0 | HE62: =SUM(GS62:HD62) -> 0 | HS62: =SUM(HG62:HR62) -> 0 | IG62: =SUM(HU62:IF62) -> 0
C63: Enter Savings Category… | Q63: =SUM(E63:P63) -> 0 | AE63: =SUM(S63:AD63) -> 0 | AS63: =SUM(AG63:AR63) -> 0 | BG63: =SUM(AU63:BF63) -> 0 | BU63: =SUM(BI63:BT63) -> 0 | CI63: =SUM(BW63:CH63) -> 0 | CW63: =SUM(CK63:CV63) -> 0 | DK63: =SUM(CY63:DJ63) -> 0 | DY63: =SUM(DM63:DX63) -> 0 | EM63: =SUM(EA63:EL63) -> 0 | FA63: =SUM(EO63:EZ63) -> 0 | FO63: =SUM(FC63:FN63) -> 0 | GC63: =SUM(FQ63:GB63) -> 0 | GQ63: =SUM(GE63:GP63) -> 0 | HE63: =SUM(GS63:HD63) -> 0 | HS63: =SUM(HG63:HR63) -> 0 | IG63: =SUM(HU63:IF63) -> 0
C64: Enter Savings Category… | Q64: =SUM(E64:P64) -> 0 | AE64: =SUM(S64:AD64) -> 0 | AS64: =SUM(AG64:AR64) -> 0 | BG64: =SUM(AU64:BF64) -> 0 | BU64: =SUM(BI64:BT64) -> 0 | CI64: =SUM(BW64:CH64) -> 0 | CW64: =SUM(CK64:CV64) -> 0 | DK64: =SUM(CY64:DJ64) -> 0 | DY64: =SUM(DM64:DX64) -> 0 | EM64: =SUM(EA64:EL64) -> 0 | FA64: =SUM(EO64:EZ64) -> 0 | FO64: =SUM(FC64:FN64) -> 0 | GC64: =SUM(FQ64:GB64) -> 0 | GQ64: =SUM(GE64:GP64) -> 0 | HE64: =SUM(GS64:HD64) -> 0 | HS64: =SUM(HG64:HR64) -> 0 | IG64: =SUM(HU64:IF64) -> 0
C65: Enter Savings Category… | Q65: =SUM(E65:P65) -> 0 | AE65: =SUM(S65:AD65) -> 0 | AS65: =SUM(AG65:AR65) -> 0 | BG65: =SUM(AU65:BF65) -> 0 | BU65: =SUM(BI65:BT65) -> 0 | CI65: =SUM(BW65:CH65) -> 0 | CW65: =SUM(CK65:CV65) -> 0 | DK65: =SUM(CY65:DJ65) -> 0 | DY65: =SUM(DM65:DX65) -> 0 | EM65: =SUM(EA65:EL65) -> 0 | FA65: =SUM(EO65:EZ65) -> 0 | FO65: =SUM(FC65:FN65) -> 0 | GC65: =SUM(FQ65:GB65) -> 0 | GQ65: =SUM(GE65:GP65) -> 0 | HE65: =SUM(GS65:HD65) -> 0 | HS65: =SUM(HG65:HR65) -> 0 | IG65: =SUM(HU65:IF65) -> 0
C66: Total | E66: {=SUM(INDIRECT(ADDRESS(savings_min_row, COLUMN()) & ":" & ADDRESS(savings_max_row, COLUMN())))} -> 0 | F66: {=SUM(INDIRECT(ADDRESS(savings_min_row, COLUMN()) & ":" & ADDRESS(savings_max_row, COLUMN())))} -> 0 | G66: {=SUM(INDIRECT(ADDRESS(savings_min_row, COLUMN()) & ":" & ADDRESS(savings_max_row, COLUMN())))} -> 0 | H66: {=SUM(INDIRECT(ADDRESS(savings_min_row, COLUMN()) & ":" & ADDRESS(savings_max_row, COLUMN())))} -> 0 | I66: {=SUM(INDIRECT(ADDRESS(savings_min_row, COLUMN()) & ":" & ADDRESS(savings_max_row, COLUMN())))} -> 0 | J66: {=SUM(INDIRECT(ADDRESS(savings_min_row, COLUMN()) & ":" & ADDRESS(savings_max_row, COLUMN())))} -> 0 | K66: {=SUM(INDIRECT(ADDRESS(savings_min_row, COLUMN()) & ":" & ADDRESS(savings_max_row, COLUMN())))} -> 0 | L66: {=SUM(INDIRECT(ADDRESS(savings_min_row, COLUMN()) & ":" & ADDRESS(savings_max_row, COLUMN())))} -> 0 | ... Q66: {=SUM(INDIRECT(ADDRESS(savings_min_row, COLUMN()) & ":" & ADDRESS(savings_max_row, COLUMN())))} -> 0 | S66: {=SUM(INDIRECT(ADDRESS(savings_min_row, COLUMN()) & ":" & ADDRESS(savings_max_row, COLUMN())))} -> 0 | T66: {=SUM(INDIRECT(ADDRESS(savings_min_row, COLUMN()) & ":" & ADDRESS(savings_max_row, COLUMN())))} -> 0 | U66: {=SUM(INDIRECT(ADDRESS(savings_min_row, COLUMN()) & ":" & ADDRESS(savings_max_row, COLUMN())))} -> 0 | V66: {=SUM(INDIRECT(ADDRESS(savings_min_row, COLUMN()) & ":" & ADDRESS(savings_max_row, COLUMN())))} -> 0 | W66: {=SUM(INDIRECT(ADDRESS(savings_min_row, COLUMN()) & ":" & ADDRESS(savings_max_row, COLUMN())))} -> 0 | X66: {=SUM(INDIRECT(ADDRESS(savings_min_row, COLUMN()) & ":" & ADDRESS(savings_max_row, COLUMN())))} -> 0 | Y66: {=SUM(INDIRECT(ADDRESS(savings_min_row, COLUMN()) & ":" & ADDRESS(savings_max_row, COLUMN())))} -> 0 | Z66: {=SUM(INDIRECT(ADDRESS(savings_min_row, COLUMN()) & ":" & ADDRESS(savings_max_row, COLUMN())))} -> 0 | ... AE66: {=SUM(INDIRECT(ADDRESS(savings_min_row, COLUMN()) & ":" & ADDRESS(savings_max_row, COLUMN())))} -> 0 | AG66: {=SUM(INDIRECT(ADDRESS(savings_min_row, COLUMN()) & ":" & ADDRESS(savings_max_row, COLUMN())))} -> 0 | AH66: {=SUM(INDIRECT(ADDRESS(savings_min_row, COLUMN()) & ":" & ADDRESS(savings_max_row, COLUMN())))} -> 0 | AI66: {=SUM(INDIRECT(ADDRESS(savings_min_row, COLUMN()) & ":" & ADDRESS(savings_max_row, COLUMN())))} -> 0 | AJ66: {=SUM(INDIRECT(ADDRESS(savings_min_row, COLUMN()) & ":" & ADDRESS(savings_max_row, COLUMN())))} -> 0 | AK66: {=SUM(INDIRECT(ADDRESS(savings_min_row, COLUMN()) & ":" & ADDRESS(savings_max_row, COLUMN())))} -> 0 | AL66: {=SUM(INDIRECT(ADDRESS(savings_min_row, COLUMN()) & ":" & ADDRESS(savings_max_row, COLUMN())))} -> 0 | AM66: {=SUM(INDIRECT(ADDRESS(savings_min_row, COLUMN()) & ":" & ADDRESS(savings_max_row, COLUMN())))} -> 0 | AN66: {=SUM(INDIRECT(ADDRESS(savings_min_row, COLUMN()) & ":" & ADDRESS(savings_max_row, COLUMN())))} -> 0 | ... AS66: {=SUM(INDIRECT(ADDRESS(savings_min_row, COLUMN()) & ":" & ADDRESS(savings_max_row, COLUMN())))} -> 0 | AU66: {=SUM(INDIRECT(ADDRESS(savings_min_row, COLUMN()) & ":" & ADDRESS(savings_max_row, COLUMN())))} -> 0 | AV66: {=SUM(INDIRECT(ADDRESS(savings_min_row, COLUMN()) & ":" & ADDRESS(savings_max_row, COLUMN())))} -> 0 | AW66: {=SUM(INDIRECT(ADDRESS(savings_min_row, COLUMN()) & ":" & ADDRESS(savings_max_row, COLUMN())))} -> 0 | AX66: {=SUM(INDIRECT(ADDRESS(savings_min_row, COLUMN()) & ":" & ADDRESS(savings_max_row, COLUMN())))} -> 0 | AY66: {=SUM(INDIRECT(ADDRESS(savings_min_row, COLUMN()) & ":" & ADDRESS(savings_max_row, COLUMN())))} -> 0 | AZ66: {=SUM(INDIRECT(ADDRESS(savings_min_row, COLUMN()) & ":" & ADDRESS(savings_max_row, COLUMN())))} -> 0 | BA66: {=SUM(INDIRECT(ADDRESS(savings_min_row, COLUMN()) & ":" & ADDRESS(savings_max_row, COLUMN())))} -> 0 | BB66: {=SUM(INDIRECT(ADDRESS(savings_min_row, COLUMN()) & ":" & ADDRESS(savings_max_row, COLUMN())))} -> 0 | ... BG66: {=SUM(INDIRECT(ADDRESS(savings_min_row, COLUMN()) & ":" & ADDRESS(savings_max_row, COLUMN())))} -> 0 | BI66: {=SUM(INDIRECT(ADDRESS(savings_min_row, COLUMN()) & ":" & ADDRESS(savings_max_row, COLUMN())))} -> 0 | BJ66: {=SUM(INDIRECT(ADDRESS(savings_min_row, COLUMN()) & ":" & ADDRESS(savings_max_row, COLUMN())))} -> 0 | BK66: {=SUM(INDIRECT(ADDRESS(savings_min_row, COLUMN()) & ":" & ADDRESS(savings_max_row, COLUMN())))} -> 0 | BL66: {=SUM(INDIRECT(ADDRESS(savings_min_row, COLUMN()) & ":" & ADDRESS(savings_max_row, COLUMN())))} -> 0 | BM66: {=SUM(INDIRECT(ADDRESS(savings_min_row, COLUMN()) & ":" & ADDRESS(savings_max_row, COLUMN())))} -> 0 | BN66: {=SUM(INDIRECT(ADDRESS(savings_min_row, COLUMN()) & ":" & ADDRESS(savings_max_row, COLUMN())))} -> 0 | BO66: {=SUM(INDIRECT(ADDRESS(savings_min_row, COLUMN()) & ":" & ADDRESS(savings_max_row, COLUMN())))} -> 0 | BP66: {=SUM(INDIRECT(ADDRESS(savings_min_row, COLUMN()) & ":" & ADDRESS(savings_max_row, COLUMN())))} -> 0 | ... BU66: {=SUM(INDIRECT(ADDRESS(savings_min_row, COLUMN()) & ":" & ADDRESS(savings_max_row, COLUMN())))} -> 0 | BW66: {=SUM(INDIRECT(ADDRESS(savings_min_row, COLUMN()) & ":" & ADDRESS(savings_max_row, COLUMN())))} -> 0 | BX66: {=SUM(INDIRECT(ADDRESS(savings_min_row, COLUMN()) & ":" & ADDRESS(savings_max_row, COLUMN())))} -> 0 | BY66: {=SUM(INDIRECT(ADDRESS(savings_min_row, COLUMN()) & ":" & ADDRESS(savings_max_row, COLUMN())))} -> 0 | BZ66: {=SUM(INDIRECT(ADDRESS(savings_min_row, COLUMN()) & ":" & ADDRESS(savings_max_row, COLUMN())))} -> 0 | CA66: {=SUM(INDIRECT(ADDRESS(savings_min_row, COLUMN()) & ":" & ADDRESS(savings_max_row, COLUMN())))} -> 0 | CB66: {=SUM(INDIRECT(ADDRESS(savings_min_row, COLUMN()) & ":" & ADDRESS(savings_max_row, COLUMN())))} -> 0 | CC66: {=SUM(INDIRECT(ADDRESS(savings_min_row, COLUMN()) & ":" & ADDRESS(savings_max_row, COLUMN())))} -> 0 | CD66: {=SUM(INDIRECT(ADDRESS(savings_min_row, COLUMN()) & ":" & ADDRESS(savings_max_row, COLUMN())))} -> 0 | ... CI66: {=SUM(INDIRECT(ADDRESS(savings_min_row, COLUMN()) & ":" & ADDRESS(savings_max_row, COLUMN())))} -> 0 | CK66: {=SUM(INDIRECT(ADDRESS(savings_min_row, COLUMN()) & ":" & ADDRESS(savings_max_row, COLUMN())))} -> 0 | CL66: {=SUM(INDIRECT(ADDRESS(savings_min_row, COLUMN()) & ":" & ADDRESS(savings_max_row, COLUMN())))} -> 0 | CM66: {=SUM(INDIRECT(ADDRESS(savings_min_row, COLUMN()) & ":" & ADDRESS(savings_max_row, COLUMN())))} -> 0 | CN66: {=SUM(INDIRECT(ADDRESS(savings_min_row, COLUMN()) & ":" & ADDRESS(savings_max_row, COLUMN())))} -> 0 | CO66: {=SUM(INDIRECT(ADDRESS(savings_min_row, COLUMN()) & ":" & ADDRESS(savings_max_row, COLUMN())))} -> 0 | CP66: {=SUM(INDIRECT(ADDRESS(savings_min_row, COLUMN()) & ":" & ADDRESS(savings_max_row, COLUMN())))} -> 0 | CQ66: {=SUM(INDIRECT(ADDRESS(savings_min_row, COLUMN()) & ":" & ADDRESS(savings_max_row, COLUMN())))} -> 0 | CR66: {=SUM(INDIRECT(ADDRESS(savings_min_row, COLUMN()) & ":" & ADDRESS(savings_max_row, COLUMN())))} -> 0 | ... CW66: {=SUM(INDIRECT(ADDRESS(savings_min_row, COLUMN()) & ":" & ADDRESS(savings_max_row, COLUMN())))} -> 0 | CY66: {=SUM(INDIRECT(ADDRESS(savings_min_row, COLUMN()) & ":" & ADDRESS(savings_max_row, COLUMN())))} -> 0 | CZ66: {=SUM(INDIRECT(ADDRESS(savings_min_row, COLUMN()) & ":" & ADDRESS(savings_max_row, COLUMN())))} -> 0 | DA66: {=SUM(INDIRECT(ADDRESS(savings_min_row, COLUMN()) & ":" & ADDRESS(savings_max_row, COLUMN())))} -> 0 | DB66: {=SUM(INDIRECT(ADDRESS(savings_min_row, COLUMN()) & ":" & ADDRESS(savings_max_row, COLUMN())))} -> 0 | DC66: {=SUM(INDIRECT(ADDRESS(savings_min_row, COLUMN()) & ":" & ADDRESS(savings_max_row, COLUMN())))} -> 0 | DD66: {=SUM(INDIRECT(ADDRESS(savings_min_row, COLUMN()) & ":" & ADDRESS(savings_max_row, COLUMN())))} -> 0 | DE66: {=SUM(INDIRECT(ADDRESS(savings_min_row, COLUMN()) & ":" & ADDRESS(savings_max_row, COLUMN())))} -> 0 | DF66: {=SUM(INDIRECT(ADDRESS(savings_min_row, COLUMN()) & ":" & ADDRESS(savings_max_row, COLUMN())))} -> 0 | ... DK66: {=SUM(INDIRECT(ADDRESS(savings_min_row, COLUMN()) & ":" & ADDRESS(savings_max_row, COLUMN())))} -> 0 | DM66: {=SUM(INDIRECT(ADDRESS(savings_min_row, COLUMN()) & ":" & ADDRESS(savings_max_row, COLUMN())))} -> 0 | DN66: {=SUM(INDIRECT(ADDRESS(savings_min_row, COLUMN()) & ":" & ADDRESS(savings_max_row, COLUMN())))} -> 0 | DO66: {=SUM(INDIRECT(ADDRESS(savings_min_row, COLUMN()) & ":" & ADDRESS(savings_max_row, COLUMN())))} -> 0 | DP66: {=SUM(INDIRECT(ADDRESS(savings_min_row, COLUMN()) & ":" & ADDRESS(savings_max_row, COLUMN())))} -> 0 | DQ66: {=SUM(INDIRECT(ADDRESS(savings_min_row, COLUMN()) & ":" & ADDRESS(savings_max_row, COLUMN())))} -> 0 | DR66: {=SUM(INDIRECT(ADDRESS(savings_min_row, COLUMN()) & ":" & ADDRESS(savings_max_row, COLUMN())))} -> 0 | DS66: {=SUM(INDIRECT(ADDRESS(savings_min_row, COLUMN()) & ":" & ADDRESS(savings_max_row, COLUMN())))} -> 0 | DT66: {=SUM(INDIRECT(ADDRESS(savings_min_row, COLUMN()) & ":" & ADDRESS(savings_max_row, COLUMN())))} -> 0 | ... DY66: {=SUM(INDIRECT(ADDRESS(savings_min_row, COLUMN()) & ":" & ADDRESS(savings_max_row, COLUMN())))} -> 0 | EA66: {=SUM(INDIRECT(ADDRESS(savings_min_row, COLUMN()) & ":" & ADDRESS(savings_max_row, COLUMN())))} -> 0 | EB66: {=SUM(INDIRECT(ADDRESS(savings_min_row, COLUMN()) & ":" & ADDRESS(savings_max_row, COLUMN())))} -> 0 | EC66: {=SUM(INDIRECT(ADDRESS(savings_min_row, COLUMN()) & ":" & ADDRESS(savings_max_row, COLUMN())))} -> 0 | ED66: {=SUM(INDIRECT(ADDRESS(savings_min_row, COLUMN()) & ":" & ADDRESS(savings_max_row, COLUMN())))} -> 0 | EE66: {=SUM(INDIRECT(ADDRESS(savings_min_row, COLUMN()) & ":" & ADDRESS(savings_max_row, COLUMN())))} -> 0 | EF66: {=SUM(INDIRECT(ADDRESS(savings_min_row, COLUMN()) & ":" & ADDRESS(savings_max_row, COLUMN())))} -> 0 | EG66: {=SUM(INDIRECT(ADDRESS(savings_min_row, COLUMN()) & ":" & ADDRESS(savings_max_row, COLUMN())))} -> 0 | EH66: {=SUM(INDIRECT(ADDRESS(savings_min_row, COLUMN()) & ":" & ADDRESS(savings_max_row, COLUMN())))} -> 0 | ... EM66: {=SUM(INDIRECT(ADDRESS(savings_min_row, COLUMN()) & ":" & ADDRESS(savings_max_row, COLUMN())))} -> 0 | EO66: {=SUM(INDIRECT(ADDRESS(savings_min_row, COLUMN()) & ":" & ADDRESS(savings_max_row, COLUMN())))} -> 0 | EP66: {=SUM(INDIRECT(ADDRESS(savings_min_row, COLUMN()) & ":" & ADDRESS(savings_max_row, COLUMN())))} -> 0 | EQ66: {=SUM(INDIRECT(ADDRESS(savings_min_row, COLUMN()) & ":" & ADDRESS(savings_max_row, COLUMN())))} -> 0 | ER66: {=SUM(INDIRECT(ADDRESS(savings_min_row, COLUMN()) & ":" & ADDRESS(savings_max_row, COLUMN())))} -> 0 | ES66: {=SUM(INDIRECT(ADDRESS(savings_min_row, COLUMN()) & ":" & ADDRESS(savings_max_row, COLUMN())))} -> 0 | ET66: {=SUM(INDIRECT(ADDRESS(savings_min_row, COLUMN()) & ":" & ADDRESS(savings_max_row, COLUMN())))} -> 0 | EU66: {=SUM(INDIRECT(ADDRESS(savings_min_row, COLUMN()) & ":" & ADDRESS(savings_max_row, COLUMN())))} -> 0 | EV66: {=SUM(INDIRECT(ADDRESS(savings_min_row, COLUMN()) & ":" & ADDRESS(savings_max_row, COLUMN())))} -> 0 | ... FA66: {=SUM(INDIRECT(ADDRESS(savings_min_row, COLUMN()) & ":" & ADDRESS(savings_max_row, COLUMN())))} -> 0 | FC66: {=SUM(INDIRECT(ADDRESS(savings_min_row, COLUMN()) & ":" & ADDRESS(savings_max_row, COLUMN())))} -> 0 | FD66: {=SUM(INDIRECT(ADDRESS(savings_min_row, COLUMN()) & ":" & ADDRESS(savings_max_row, COLUMN())))} -> 0 | FE66: {=SUM(INDIRECT(ADDRESS(savings_min_row, COLUMN()) & ":" & ADDRESS(savings_max_row, COLUMN())))} -> 0 | FF66: {=SUM(INDIRECT(ADDRESS(savings_min_row, COLUMN()) & ":" & ADDRESS(savings_max_row, COLUMN())))} -> 0 | FG66: {=SUM(INDIRECT(ADDRESS(savings_min_row, COLUMN()) & ":" & ADDRESS(savings_max_row, COLUMN())))} -> 0 | FH66: {=SUM(INDIRECT(ADDRESS(savings_min_row, COLUMN()) & ":" & ADDRESS(savings_max_row, COLUMN())))} -> 0 | FI66: {=SUM(INDIRECT(ADDRESS(savings_min_row, COLUMN()) & ":" & ADDRESS(savings_max_row, COLUMN())))} -> 0 | FJ66: {=SUM(INDIRECT(ADDRESS(savings_min_row, COLUMN()) & ":" & ADDRESS(savings_max_row, COLUMN())))} -> 0 | ... FO66: {=SUM(INDIRECT(ADDRESS(savings_min_row, COLUMN()) & ":" & ADDRESS(savings_max_row, COLUMN())))} -> 0 | FQ66: {=SUM(INDIRECT(ADDRESS(savings_min_row, COLUMN()) & ":" & ADDRESS(savings_max_row, COLUMN())))} -> 0 | FR66: {=SUM(INDIRECT(ADDRESS(savings_min_row, COLUMN()) & ":" & ADDRESS(savings_max_row, COLUMN())))} -> 0 | FS66: {=SUM(INDIRECT(ADDRESS(savings_min_row, COLUMN()) & ":" & ADDRESS(savings_max_row, COLUMN())))} -> 0 | FT66: {=SUM(INDIRECT(ADDRESS(savings_min_row, COLUMN()) & ":" & ADDRESS(savings_max_row, COLUMN())))} -> 0 | FU66: {=SUM(INDIRECT(ADDRESS(savings_min_row, COLUMN()) & ":" & ADDRESS(savings_max_row, COLUMN())))} -> 0 | FV66: {=SUM(INDIRECT(ADDRESS(savings_min_row, COLUMN()) & ":" & ADDRESS(savings_max_row, COLUMN())))} -> 0 | FW66: {=SUM(INDIRECT(ADDRESS(savings_min_row, COLUMN()) & ":" & ADDRESS(savings_max_row, COLUMN())))} -> 0 | FX66: {=SUM(INDIRECT(ADDRESS(savings_min_row, COLUMN()) & ":" & ADDRESS(savings_max_row, COLUMN())))} -> 0 | ... GC66: {=SUM(INDIRECT(ADDRESS(savings_min_row, COLUMN()) & ":" & ADDRESS(savings_max_row, COLUMN())))} -> 0 | GE66: {=SUM(INDIRECT(ADDRESS(savings_min_row, COLUMN()) & ":" & ADDRESS(savings_max_row, COLUMN())))} -> 0 | GF66: {=SUM(INDIRECT(ADDRESS(savings_min_row, COLUMN()) & ":" & ADDRESS(savings_max_row, COLUMN())))} -> 0 | GG66: {=SUM(INDIRECT(ADDRESS(savings_min_row, COLUMN()) & ":" & ADDRESS(savings_max_row, COLUMN())))} -> 0 | GH66: {=SUM(INDIRECT(ADDRESS(savings_min_row, COLUMN()) & ":" & ADDRESS(savings_max_row, COLUMN())))} -> 0 | GI66: {=SUM(INDIRECT(ADDRESS(savings_min_row, COLUMN()) & ":" & ADDRESS(savings_max_row, COLUMN())))} -> 0 | GJ66: {=SUM(INDIRECT(ADDRESS(savings_min_row, COLUMN()) & ":" & ADDRESS(savings_max_row, COLUMN())))} -> 0 | GK66: {=SUM(INDIRECT(ADDRESS(savings_min_row, COLUMN()) & ":" & ADDRESS(savings_max_row, COLUMN())))} -> 0 | GL66: {=SUM(INDIRECT(ADDRESS(savings_min_row, COLUMN()) & ":" & ADDRESS(savings_max_row, COLUMN())))} -> 0 | ... GQ66: {=SUM(INDIRECT(ADDRESS(savings_min_row, COLUMN()) & ":" & ADDRESS(savings_max_row, COLUMN())))} -> 0 | GS66: {=SUM(INDIRECT(ADDRESS(savings_min_row, COLUMN()) & ":" & ADDRESS(savings_max_row, COLUMN())))} -> 0 | GT66: {=SUM(INDIRECT(ADDRESS(savings_min_row, COLUMN()) & ":" & ADDRESS(savings_max_row, COLUMN())))} -> 0 | GU66: {=SUM(INDIRECT(ADDRESS(savings_min_row, COLUMN()) & ":" & ADDRESS(savings_max_row, COLUMN())))} -> 0 | GV66: {=SUM(INDIRECT(ADDRESS(savings_min_row, COLUMN()) & ":" & ADDRESS(savings_max_row, COLUMN())))} -> 0 | GW66: {=SUM(INDIRECT(ADDRESS(savings_min_row, COLUMN()) & ":" & ADDRESS(savings_max_row, COLUMN())))} -> 0 | GX66: {=SUM(INDIRECT(ADDRESS(savings_min_row, COLUMN()) & ":" & ADDRESS(savings_max_row, COLUMN())))} -> 0 | GY66: {=SUM(INDIRECT(ADDRESS(savings_min_row, COLUMN()) & ":" & ADDRESS(savings_max_row, COLUMN())))} -> 0 | GZ66: {=SUM(INDIRECT(ADDRESS(savings_min_row, COLUMN()) & ":" & ADDRESS(savings_max_row, COLUMN())))} -> 0 | ... HE66: {=SUM(INDIRECT(ADDRESS(savings_min_row, COLUMN()) & ":" & ADDRESS(savings_max_row, COLUMN())))} -> 0 | HG66: {=SUM(INDIRECT(ADDRESS(savings_min_row, COLUMN()) & ":" & ADDRESS(savings_max_row, COLUMN())))} -> 0 | HH66: {=SUM(INDIRECT(ADDRESS(savings_min_row, COLUMN()) & ":" & ADDRESS(savings_max_row, COLUMN())))} -> 0 | HI66: {=SUM(INDIRECT(ADDRESS(savings_min_row, COLUMN()) & ":" & ADDRESS(savings_max_row, COLUMN())))} -> 0 | HJ66: {=SUM(INDIRECT(ADDRESS(savings_min_row, COLUMN()) & ":" & ADDRESS(savings_max_row, COLUMN())))} -> 0 | HK66: {=SUM(INDIRECT(ADDRESS(savings_min_row, COLUMN()) & ":" & ADDRESS(savings_max_row, COLUMN())))} -> 0 | HL66: {=SUM(INDIRECT(ADDRESS(savings_min_row, COLUMN()) & ":" & ADDRESS(savings_max_row, COLUMN())))} -> 0 | HM66: {=SUM(INDIRECT(ADDRESS(savings_min_row, COLUMN()) & ":" & ADDRESS(savings_max_row, COLUMN())))} -> 0 | HN66: {=SUM(INDIRECT(ADDRESS(savings_min_row, COLUMN()) & ":" & ADDRESS(savings_max_row, COLUMN())))} -> 0 | ... HS66: {=SUM(INDIRECT(ADDRESS(savings_min_row, COLUMN()) & ":" & ADDRESS(savings_max_row, COLUMN())))} -> 0 | HU66: {=SUM(INDIRECT(ADDRESS(savings_min_row, COLUMN()) & ":" & ADDRESS(savings_max_row, COLUMN())))} -> 0 | HV66: {=SUM(INDIRECT(ADDRESS(savings_min_row, COLUMN()) & ":" & ADDRESS(savings_max_row, COLUMN())))} -> 0 | HW66: {=SUM(INDIRECT(ADDRESS(savings_min_row, COLUMN()) & ":" & ADDRESS(savings_max_row, COLUMN())))} -> 0 | HX66: {=SUM(INDIRECT(ADDRESS(savings_min_row, COLUMN()) & ":" & ADDRESS(savings_max_row, COLUMN())))} -> 0 | HY66: {=SUM(INDIRECT(ADDRESS(savings_min_row, COLUMN()) & ":" & ADDRESS(savings_max_row, COLUMN())))} -> 0 | HZ66: {=SUM(INDIRECT(ADDRESS(savings_min_row, COLUMN()) & ":" & ADDRESS(savings_max_row, COLUMN())))} -> 0 | IA66: {=SUM(INDIRECT(ADDRESS(savings_min_row, COLUMN()) & ":" & ADDRESS(savings_max_row, COLUMN())))} -> 0 | IB66: {=SUM(INDIRECT(ADDRESS(savings_min_row, COLUMN()) & ":" & ADDRESS(savings_max_row, COLUMN())))} -> 0 | ... IG66: {=SUM(INDIRECT(ADDRESS(savings_min_row, COLUMN()) & ":" & ADDRESS(savings_max_row, COLUMN())))} -> 0

Sheet Budget Dashboard
C2: Budget Dashboard | Y2: Budget Dashboard
AQ5: Year
AN6: Select the year to view → | AQ6: 2025
AQ8: Period
AN9: Select the period to view → | AQ9: Total Year
Y11: ="Breakdown - " & IF(selected_period="Total Year", selected_year & " (Total Year)", selected_period_display & " " & selected_year) -> Breakdown - 2025 (Total Year) | AF11: ="Summary - " & IF(selected_period="Total Year", selected_year & "(Total Year)", selected_period_display & " " & selected_year) -> Summary - 2025(Total Year)
C12: row_id | D12: header_row_id | E12: is_header | F12: is_cat | G12: is_total | H12: is_empty | I12: type | J12: item | K12: tracked | L12: budget | M12: sort_min_row | N12: sort_max_row | O12: tracked_range | P12: tracked_rank | Q12: budget_range | R12: budget_rank | S12: comb_rank | T12: comb_rank_range | U12: comb_rank_norm | V12: comb_rank_norm_run_range | W12: comb_rank_unique | X12: sorted_row_id [Lookup]
C13: {=income_header_row} -> 12 | D13: =IF(is_header, row_id, IF(NOT(is_empty), D12, -1)) -> 12 | E13: {=1*OR(row_id=income_header_row, row_id=expenses_header_row, row_id=savings_header_row)} -> 1 | F13: =1*NOT(OR(is_header, is_total, is_empty)) -> 0 | G13: {=1*OR(row_id=income_total_row, row_id=expenses_total_row, row_id=savings_total_row)} -> 0 | H13: =1*OR(row_id="/1", row_id="/2", row_id=-1) -> 0 | I13: {=IFERROR(INDEX('Budget Planning'!$C:$C,header_row_id)," ")} -> Income | J13: {=IFERROR(INDEX('Budget Planning'!$C:$C, row_id), " ")} -> Income | K13: {=IF(OR(is_header, is_empty), "", IF(is_total, IF(selected_period="Total Year", SUM( Tracking[Amount] * (Tracking[Type]=type)*(YEAR(Tracking[Effective Date])=selected_year)), SUM( Tracking[Amount] * (Tracking[Type]=type)*(YEAR(Tracking[Effective Date])=selected_year)*(MONTH(Tracking[Effective Date])=selected_period) )), IF(selected_period="Total Year", SUM( Tracking[Amount] * (Tracking[Type]=type)*(Tracking[Category]=item)*(YEAR(Tracking[Effective Date])=selected_year)), SUM( Tracking[Amount] * (Tracking[Type]=type)*(Tracking[Category]=item)*(YEAR(Tracking[Effective Date])=selected_year)*(MONTH(Tracking[Effective Date])=selected_period))) ) )} | L13: {=IF(OR(is_header, is_empty), "", INDEX('Budget Planning'!$E:$IG, row_id, MATCH(IF(selected_period="Total Year", selected_year, DATE(selected_year, selected_period, 1)), 'Budget Planning'!$E$12:$IG$12, 0)))} | M13: {=IF(is_cat, IF(header_row_id=income_header_row, MATCH(income_min_row, $C:$C,0), IF(header_row_id=expenses_header_row, MATCH(expenses_min_row, $C:$C,0), IF(header_row_id=savings_header_row, MATCH(savings_min_row, $C:$C,0), ""))), "")} | N13: {=IF(is_cat, IF(header_row_id=income_header_row, MATCH(income_max_row, $C:$C,0), IF(header_row_id=expenses_header_row, MATCH(expenses_max_row, $C:$C,0), IF(header_row_id=savings_header_row, MATCH(savings_max_row, $C:$C,0), ""))), "")} | O13: =IF(is_cat, ADDRESS(sort_min_row, COLUMN(tracked)) & ":" & ADDRESS(sort_max_row, COLUMN(tracked)), "") | P13: =IF(is_cat, RANK(tracked, INDIRECT(tracked_range), 0), "") | Q13: =IF(is_cat, ADDRESS(sort_min_row, COLUMN(budget)) & ":" & ADDRESS(sort_max_row, COLUMN(budget)), "") | R13: =IF(is_cat, RANK(budget, INDIRECT(budget_range), 0), "") | S13: =IF(is_cat, _xlfn.NUMBERVALUE(tracked_rank & budget_rank), "") | T13: =IF(is_cat, ADDRESS(sort_min_row, COLUMN(comb_rank)) & ":" & ADDRESS(sort_max_row, COLUMN(comb_rank)), "") | U13: =IF(is_cat, RANK(comb_rank, INDIRECT(comb_rank_range), 1), "") | V13: =IF(is_cat, ADDRESS(sort_min_row, COLUMN(comb_rank_norm)) & ":" & ADDRESS(ROW(), COLUMN(comb_rank_norm)), "") | W13: =IF(is_cat, comb_rank_norm +COUNTIF(INDIRECT(comb_rank_norm_run_range), comb_rank_norm)-1, "") | X13: =IF(is_cat, header_row_id + comb_rank_unique, row_id) -> 12 | Y13: =IF(is_empty, "", INDEX($J:$J, MATCH(row_id, $X:$X, 0))) -> Income | Z13: =IF(is_empty, "", IF(is_header, "Tracked", INDEX($K:$K, MATCH(row_id, $X:$X,0)))) -> Tracked | AA13: =IF(is_empty, "", IF(is_header, "Budget", INDEX($L:$L, MATCH(row_id, $X:$X,0)))) -> Budget | AB13: =IF(is_empty, "", IF(is_header, "% Compl.", IFERROR(out_tracked / out_budget, "-"))) -> % Compl. | AC13: =IF(is_empty, "", IF(is_header, "Remaining", IF(out_budget - out_tracked > 0, out_budget - out_tracked, 0))) -> Remaining | AD13: =IF(is_empty, "", IF(is_header, "Excess", IF(out_budget - out_tracked < 0, out_tracked - out_budget, 0))) -> Excess
C14: {=IF(C13=-1, -1, IF(C13<income_max_row, C13+1, IF(C13=income_max_row, income_total_row, IF(C13=income_total_row, "/1", IF(C13="/1", expenses_header_row, IF(C13<expenses_max_row, C13+1, IF(C13=expenses_max_row, expenses_total_row, IF(C13=expenses_total_row, "/2", IF(C13="/2", savings_header_row, IF(C13<savings_max_row, C13+1, IF(C13=savings_max_row, savings_total_row, -1)))))))))))} -> 13 | D14: =IF(is_header, row_id, IF(NOT(is_empty), D13, -1)) -> 12 | E14: {=1*OR(row_id=income_header_row, row_id=expenses_header_row, row_id=savings_header_row)} -> 0 | F14: =1*NOT(OR(is_header, is_total, is_empty)) -> 1 | G14: {=1*OR(row_id=income_total_row, row_id=expenses_total_row, row_id=savings_total_row)} -> 0 | H14: =1*OR(row_id="/1", row_id="/2", row_id=-1) -> 0 | I14: {=IFERROR(INDEX('Budget Planning'!$C:$C,header_row_id)," ")} -> Income | J14: {=IFERROR(INDEX('Budget Planning'!$C:$C, row_id), " ")} -> Employment | K14: {=IF(OR(is_header, is_empty), "", IF(is_total, IF(selected_period="Total Year", SUM( Tracking[Amount] * (Tracking[Type]=type)*(YEAR(Tracking[Effective Date])=selected_year)), SUM( Tracking[Amount] * (Tracking[Type]=type)*(YEAR(Tracking[Effective Date])=selected_year)*(MONTH(Tracking[Effective Date])=selected_period) )), IF(selected_period="Total Year", SUM( Tracking[Amount] * (Tracking[Type]=type)*(Tracking[Category]=item)*(YEAR(Tracking[Effective Date])=selected_year)), SUM( Tracking[Amount] * (Tracking[Type]=type)*(Tracking[Category]=item)*(YEAR(Tracking[Effective Date])=selected_year)*(MONTH(Tracking[Effective Date])=selected_period))) ) )} -> 36745.9 | L14: {=IF(OR(is_header, is_empty), "", INDEX('Budget Planning'!$E:$IG, row_id, MATCH(IF(selected_period="Total Year", selected_year, DATE(selected_year, selected_period, 1)), 'Budget Planning'!$E$12:$IG$12, 0)))} -> 36406.5 | M14: {=IF(is_cat, IF(header_row_id=income_header_row, MATCH(income_min_row, $C:$C,0), IF(header_row_id=expenses_header_row, MATCH(expenses_min_row, $C:$C,0), IF(header_row_id=savings_header_row, MATCH(savings_min_row, $C:$C,0), ""))), "")} -> 14 | N14: {=IF(is_cat, IF(header_row_id=income_header_row, MATCH(income_max_row, $C:$C,0), IF(header_row_id=expenses_header_row, MATCH(expenses_max_row, $C:$C,0), IF(header_row_id=savings_header_row, MATCH(savings_max_row, $C:$C,0), ""))), "")} -> 17 | O14: =IF(is_cat, ADDRESS(sort_min_row, COLUMN(tracked)) & ":" & ADDRESS(sort_max_row, COLUMN(tracked)), "") -> $K$14:$K$17 | P14: =IF(is_cat, RANK(tracked, INDIRECT(tracked_range), 0), "") -> 1 | Q14: =IF(is_cat, ADDRESS(sort_min_row, COLUMN(budget)) & ":" & ADDRESS(sort_max_row, COLUMN(budget)), "") -> $L$14:$L$17 | R14: =IF(is_cat, RANK(budget, INDIRECT(budget_range), 0), "") -> 1 | S14: =IF(is_cat, _xlfn.NUMBERVALUE(tracked_rank & budget_rank), "") -> 11 | T14: =IF(is_cat, ADDRESS(sort_min_row, COLUMN(comb_rank)) & ":" & ADDRESS(sort_max_row, COLUMN(comb_rank)), "") -> $S$14:$S$17 | U14: =IF(is_cat, RANK(comb_rank, INDIRECT(comb_rank_range), 1), "") -> 1 | V14: =IF(is_cat, ADDRESS(sort_min_row, COLUMN(comb_rank_norm)) & ":" & ADDRESS(ROW(), COLUMN(comb_rank_norm)), "") -> $U$14:$U$14 | W14: =IF(is_cat, comb_rank_norm +COUNTIF(INDIRECT(comb_rank_norm_run_range), comb_rank_norm)-1, "") -> 1 | X14: =IF(is_cat, header_row_id + comb_rank_unique, row_id) -> 13 | Y14: =IF(is_empty, "", INDEX($J:$J, MATCH(row_id, $X:$X, 0))) -> Employment | Z14: =IF(is_empty, "", IF(is_header, "Tracked", INDEX($K:$K, MATCH(row_id, $X:$X,0)))) -> 36745.9 | AA14: =IF(is_empty, "", IF(is_header, "Budget", INDEX($L:$L, MATCH(row_id, $X:$X,0)))) -> 36406.5 | AB14: =IF(is_empty, "", IF(is_header, "% Compl.", IFERROR(out_tracked / out_budget, "-"))) -> 1.0093225 | AC14: =IF(is_empty, "", IF(is_header, "Remaining", IF(out_budget - out_tracked > 0, out_budget - out_tracked, 0))) -> 0 | AD14: =IF(is_empty, "", IF(is_header, "Excess", IF(out_budget - out_tracked < 0, out_tracked - out_budget, 0))) -> 339.4
C15: {=IF(C14=-1, -1, IF(C14<income_max_row, C14+1, IF(C14=income_max_row, income_total_row, IF(C14=income_total_row, "/1", IF(C14="/1", expenses_header_row, IF(C14<expenses_max_row, C14+1, IF(C14=expenses_max_row, expenses_total_row, IF(C14=expenses_total_row, "/2", IF(C14="/2", savings_header_row, IF(C14<savings_max_row, C14+1, IF(C14=savings_max_row, savings_total_row, -1)))))))))))} -> 14 | D15: =IF(is_header, row_id, IF(NOT(is_empty), D14, -1)) -> 12 | E15: {=1*OR(row_id=income_header_row, row_id=expenses_header_row, row_id=savings_header_row)} -> 0 | F15: =1*NOT(OR(is_header, is_total, is_empty)) -> 1 | G15: {=1*OR(row_id=income_total_row, row_id=expenses_total_row, row_id=savings_total_row)} -> 0 | H15: =1*OR(row_id="/1", row_id="/2", row_id=-1) -> 0 | I15: {=IFERROR(INDEX('Budget Planning'!$C:$C,header_row_id)," ")} -> Income | J15: {=IFERROR(INDEX('Budget Planning'!$C:$C, row_id), " ")} -> Grant Payment | K15: {=IF(OR(is_header, is_empty), "", IF(is_total, IF(selected_period="Total Year", SUM( Tracking[Amount] * (Tracking[Type]=type)*(YEAR(Tracking[Effective Date])=selected_year)), SUM( Tracking[Amount] * (Tracking[Type]=type)*(YEAR(Tracking[Effective Date])=selected_year)*(MONTH(Tracking[Effective Date])=selected_period) )), IF(selected_period="Total Year", SUM( Tracking[Amount] * (Tracking[Type]=type)*(Tracking[Category]=item)*(YEAR(Tracking[Effective Date])=selected_year)), SUM( Tracking[Amount] * (Tracking[Type]=type)*(Tracking[Category]=item)*(YEAR(Tracking[Effective Date])=selected_year)*(MONTH(Tracking[Effective Date])=selected_period))) ) )} -> 4000 | L15: {=IF(OR(is_header, is_empty), "", INDEX('Budget Planning'!$E:$IG, row_id, MATCH(IF(selected_period="Total Year", selected_year, DATE(selected_year, selected_period, 1)), 'Budget Planning'!$E$12:$IG$12, 0)))} -> 4000 | M15: {=IF(is_cat, IF(header_row_id=income_header_row, MATCH(income_min_row, $C:$C,0), IF(header_row_id=expenses_header_row, MATCH(expenses_min_row, $C:$C,0), IF(header_row_id=savings_header_row, MATCH(savings_min_row, $C:$C,0), ""))), "")} -> 14 | N15: {=IF(is_cat, IF(header_row_id=income_header_row, MATCH(income_max_row, $C:$C,0), IF(header_row_id=expenses_header_row, MATCH(expenses_max_row, $C:$C,0), IF(header_row_id=savings_header_row, MATCH(savings_max_row, $C:$C,0), ""))), "")} -> 17 | O15: =IF(is_cat, ADDRESS(sort_min_row, COLUMN(tracked)) & ":" & ADDRESS(sort_max_row, COLUMN(tracked)), "") -> $K$14:$K$17 | P15: =IF(is_cat, RANK(tracked, INDIRECT(tracked_range), 0), "") -> 3 | Q15: =IF(is_cat, ADDRESS(sort_min_row, COLUMN(budget)) & ":" & ADDRESS(sort_max_row, COLUMN(budget)), "") -> $L$14:$L$17 | R15: =IF(is_cat, RANK(budget, INDIRECT(budget_range), 0), "") -> 3 | S15: =IF(is_cat, _xlfn.NUMBERVALUE(tracked_rank & budget_rank), "") -> 33 | T15: =IF(is_cat, ADDRESS(sort_min_row, COLUMN(comb_rank)) & ":" & ADDRESS(sort_max_row, COLUMN(comb_rank)), "") -> $S$14:$S$17 | U15: =IF(is_cat, RANK(comb_rank, INDIRECT(comb_rank_range), 1), "") -> 3 | V15: =IF(is_cat, ADDRESS(sort_min_row, COLUMN(comb_rank_norm)) & ":" & ADDRESS(ROW(), COLUMN(comb_rank_norm)), "") -> $U$14:$U$15 | W15: =IF(is_cat, comb_rank_norm +COUNTIF(INDIRECT(comb_rank_norm_run_range), comb_rank_norm)-1, "") -> 3 | X15: =IF(is_cat, header_row_id + comb_rank_unique, row_id) -> 15 | Y15: =IF(is_empty, "", INDEX($J:$J, MATCH(row_id, $X:$X, 0))) -> Side Hustle | Z15: =IF(is_empty, "", IF(is_header, "Tracked", INDEX($K:$K, MATCH(row_id, $X:$X,0)))) -> 6013.2 | AA15: =IF(is_empty, "", IF(is_header, "Budget", INDEX($L:$L, MATCH(row_id, $X:$X,0)))) -> 6013.2 | AB15: =IF(is_empty, "", IF(is_header, "% Compl.", IFERROR(out_tracked / out_budget, "-"))) -> 1 | AC15: =IF(is_empty, "", IF(is_header, "Remaining", IF(out_budget - out_tracked > 0, out_budget - out_tracked, 0))) -> 9.094947e-13 | AD15: =IF(is_empty, "", IF(is_header, "Excess", IF(out_budget - out_tracked < 0, out_tracked - out_budget, 0))) -> 0
C16: {=IF(C15=-1, -1, IF(C15<income_max_row, C15+1, IF(C15=income_max_row, income_total_row, IF(C15=income_total_row, "/1", IF(C15="/1", expenses_header_row, IF(C15<expenses_max_row, C15+1, IF(C15=expenses_max_row, expenses_total_row, IF(C15=expenses_total_row, "/2", IF(C15="/2", savings_header_row, IF(C15<savings_max_row, C15+1, IF(C15=savings_max_row, savings_total_row, -1)))))))))))} -> 15 | D16: =IF(is_header, row_id, IF(NOT(is_empty), D15, -1)) -> 12 | E16: {=1*OR(row_id=income_header_row, row_id=expenses_header_row, row_id=savings_header_row)} -> 0 | F16: =1*NOT(OR(is_header, is_total, is_empty)) -> 1 | G16: {=1*OR(row_id=income_total_row, row_id=expenses_total_row, row_id=savings_total_row)} -> 0 | H16: =1*OR(row_id="/1", row_id="/2", row_id=-1) -> 0 | I16: {=IFERROR(INDEX('Budget Planning'!$C:$C,header_row_id)," ")} -> Income | J16: {=IFERROR(INDEX('Budget Planning'!$C:$C, row_id), " ")} -> Side Hustle | K16: {=IF(OR(is_header, is_empty), "", IF(is_total, IF(selected_period="Total Year", SUM( Tracking[Amount] * (Tracking[Type]=type)*(YEAR(Tracking[Effective Date])=selected_year)), SUM( Tracking[Amount] * (Tracking[Type]=type)*(YEAR(Tracking[Effective Date])=selected_year)*(MONTH(Tracking[Effective Date])=selected_period) )), IF(selected_period="Total Year", SUM( Tracking[Amount] * (Tracking[Type]=type)*(Tracking[Category]=item)*(YEAR(Tracking[Effective Date])=selected_year)), SUM( Tracking[Amount] * (Tracking[Type]=type)*(Tracking[Category]=item)*(YEAR(Tracking[Effective Date])=selected_year)*(MONTH(Tracking[Effective Date])=selected_period))) ) )} -> 6013.2 | L16: {=IF(OR(is_header, is_empty), "", INDEX('Budget Planning'!$E:$IG, row_id, MATCH(IF(selected_period="Total Year", selected_year, DATE(selected_year, selected_period, 1)), 'Budget Planning'!$E$12:$IG$12, 0)))} -> 6013.2 | M16: {=IF(is_cat, IF(header_row_id=income_header_row, MATCH(income_min_row, $C:$C,0), IF(header_row_id=expenses_header_row, MATCH(expenses_min_row, $C:$C,0), IF(header_row_id=savings_header_row, MATCH(savings_min_row, $C:$C,0), ""))), "")} -> 14 | N16: {=IF(is_cat, IF(header_row_id=income_header_row, MATCH(income_max_row, $C:$C,0), IF(header_row_id=expenses_header_row, MATCH(expenses_max_row, $C:$C,0), IF(header_row_id=savings_header_row, MATCH(savings_max_row, $C:$C,0), ""))), "")} -> 17 | O16: =IF(is_cat, ADDRESS(sort_min_row, COLUMN(tracked)) & ":" & ADDRESS(sort_max_row, COLUMN(tracked)), "") -> $K$14:$K$17 | P16: =IF(is_cat, RANK(tracked, INDIRECT(tracked_range), 0), "") -> 2 | Q16: =IF(is_cat, ADDRESS(sort_min_row, COLUMN(budget)) & ":" & ADDRESS(sort_max_row, COLUMN(budget)), "") -> $L$14:$L$17 | R16: =IF(is_cat, RANK(budget, INDIRECT(budget_range), 0), "") -> 2 | S16: =IF(is_cat, _xlfn.NUMBERVALUE(tracked_rank & budget_rank), "") -> 22 | T16: =IF(is_cat, ADDRESS(sort_min_row, COLUMN(comb_rank)) & ":" & ADDRESS(sort_max_row, COLUMN(comb_rank)), "") -> $S$14:$S$17 | U16: =IF(is_cat, RANK(comb_rank, INDIRECT(comb_rank_range), 1), "") -> 2 | V16: =IF(is_cat, ADDRESS(sort_min_row, COLUMN(comb_rank_norm)) & ":" & ADDRESS(ROW(), COLUMN(comb_rank_norm)), "") -> $U$14:$U$16 | W16: =IF(is_cat, comb_rank_norm +COUNTIF(INDIRECT(comb_rank_norm_run_range), comb_rank_norm)-1, "") -> 2 | X16: =IF(is_cat, header_row_id + comb_rank_unique, row_id) -> 14 | Y16: =IF(is_empty, "", INDEX($J:$J, MATCH(row_id, $X:$X, 0))) -> Grant Payment | Z16: =IF(is_empty, "", IF(is_header, "Tracked", INDEX($K:$K, MATCH(row_id, $X:$X,0)))) -> 4000 | AA16: =IF(is_empty, "", IF(is_header, "Budget", INDEX($L:$L, MATCH(row_id, $X:$X,0)))) -> 4000 | AB16: =IF(is_empty, "", IF(is_header, "% Compl.", IFERROR(out_tracked / out_budget, "-"))) -> 1 | AC16: =IF(is_empty, "", IF(is_header, "Remaining", IF(out_budget - out_tracked > 0, out_budget - out_tracked, 0))) -> 0 | AD16: =IF(is_empty, "", IF(is_header, "Excess", IF(out_budget - out_tracked < 0, out_tracked - out_budget, 0))) -> 0 | AI16: =Calculations!E35 -> Employment | AJ16: =Calculations!F35 -> 36745.9
C17: {=IF(C16=-1, -1, IF(C16<income_max_row, C16+1, IF(C16=income_max_row, income_total_row, IF(C16=income_total_row, "/1", IF(C16="/1", expenses_header_row, IF(C16<expenses_max_row, C16+1, IF(C16=expenses_max_row, expenses_total_row, IF(C16=expenses_total_row, "/2", IF(C16="/2", savings_header_row, IF(C16<savings_max_row, C16+1, IF(C16=savings_max_row, savings_total_row, -1)))))))))))} -> 16 | D17: =IF(is_header, row_id, IF(NOT(is_empty), D16, -1)) -> 12 | E17: {=1*OR(row_id=income_header_row, row_id=expenses_header_row, row_id=savings_header_row)} -> 0 | F17: =1*NOT(OR(is_header, is_total, is_empty)) -> 1 | G17: {=1*OR(row_id=income_total_row, row_id=expenses_total_row, row_id=savings_total_row)} -> 0 | H17: =1*OR(row_id="/1", row_id="/2", row_id=-1) -> 0 | I17: {=IFERROR(INDEX('Budget Planning'!$C:$C,header_row_id)," ")} -> Income | J17: {=IFERROR(INDEX('Budget Planning'!$C:$C, row_id), " ")} -> Extras / Twint Chargeback | K17: {=IF(OR(is_header, is_empty), "", IF(is_total, IF(selected_period="Total Year", SUM( Tracking[Amount] * (Tracking[Type]=type)*(YEAR(Tracking[Effective Date])=selected_year)), SUM( Tracking[Amount] * (Tracking[Type]=type)*(YEAR(Tracking[Effective Date])=selected_year)*(MONTH(Tracking[Effective Date])=selected_period) )), IF(selected_period="Total Year", SUM( Tracking[Amount] * (Tracking[Type]=type)*(Tracking[Category]=item)*(YEAR(Tracking[Effective Date])=selected_year)), SUM( Tracking[Amount] * (Tracking[Type]=type)*(Tracking[Category]=item)*(YEAR(Tracking[Effective Date])=selected_year)*(MONTH(Tracking[Effective Date])=selected_period))) ) )} -> 1160.25 | L17: {=IF(OR(is_header, is_empty), "", INDEX('Budget Planning'!$E:$IG, row_id, MATCH(IF(selected_period="Total Year", selected_year, DATE(selected_year, selected_period, 1)), 'Budget Planning'!$E$12:$IG$12, 0)))} -> 1160.25 | M17: {=IF(is_cat, IF(header_row_id=income_header_row, MATCH(income_min_row, $C:$C,0), IF(header_row_id=expenses_header_row, MATCH(expenses_min_row, $C:$C,0), IF(header_row_id=savings_header_row, MATCH(savings_min_row, $C:$C,0), ""))), "")} -> 14 | N17: {=IF(is_cat, IF(header_row_id=income_header_row, MATCH(income_max_row, $C:$C,0), IF(header_row_id=expenses_header_row, MATCH(expenses_max_row, $C:$C,0), IF(header_row_id=savings_header_row, MATCH(savings_max_row, $C:$C,0), ""))), "")} -> 17 | O17: =IF(is_cat, ADDRESS(sort_min_row, COLUMN(tracked)) & ":" & ADDRESS(sort_max_row, COLUMN(tracked)), "") -> $K$14:$K$17 | P17: =IF(is_cat, RANK(tracked, INDIRECT(tracked_range), 0), "") -> 4 | Q17: =IF(is_cat, ADDRESS(sort_min_row, COLUMN(budget)) & ":" & ADDRESS(sort_max_row, COLUMN(budget)), "") -> $L$14:$L$17 | R17: =IF(is_cat, RANK(budget, INDIRECT(budget_range), 0), "") -> 4 | S17: =IF(is_cat, _xlfn.NUMBERVALUE(tracked_rank & budget_rank), "") -> 44 | T17: =IF(is_cat, ADDRESS(sort_min_row, COLUMN(comb_rank)) & ":" & ADDRESS(sort_max_row, COLUMN(comb_rank)), "") -> $S$14:$S$17 | U17: =IF(is_cat, RANK(comb_rank, INDIRECT(comb_rank_range), 1), "") -> 4 | V17: =IF(is_cat, ADDRESS(sort_min_row, COLUMN(comb_rank_norm)) & ":" & ADDRESS(ROW(), COLUMN(comb_rank_norm)), "") -> $U$14:$U$17 | W17: =IF(is_cat, comb_rank_norm +COUNTIF(INDIRECT(comb_rank_norm_run_range), comb_rank_norm)-1, "") -> 4 | X17: =IF(is_cat, header_row_id + comb_rank_unique, row_id) -> 16 | Y17: =IF(is_empty, "", INDEX($J:$J, MATCH(row_id, $X:$X, 0))) -> Extras / Twint Chargeback | Z17: =IF(is_empty, "", IF(is_header, "Tracked", INDEX($K:$K, MATCH(row_id, $X:$X,0)))) -> 1160.25 | AA17: =IF(is_empty, "", IF(is_header, "Budget", INDEX($L:$L, MATCH(row_id, $X:$X,0)))) -> 1160.25 | AB17: =IF(is_empty, "", IF(is_header, "% Compl.", IFERROR(out_tracked / out_budget, "-"))) -> 1 | AC17: =IF(is_empty, "", IF(is_header, "Remaining", IF(out_budget - out_tracked > 0, out_budget - out_tracked, 0))) -> 0 | AD17: =IF(is_empty, "", IF(is_header, "Excess", IF(out_budget - out_tracked < 0, out_tracked - out_budget, 0))) -> 0 | AI17: =Calculations!E36 -> Side Hustle | AJ17: =Calculations!F36 -> 6013.2
C18: {=IF(C17=-1, -1, IF(C17<income_max_row, C17+1, IF(C17=income_max_row, income_total_row, IF(C17=income_total_row, "/1", IF(C17="/1", expenses_header_row, IF(C17<expenses_max_row, C17+1, IF(C17=expenses_max_row, expenses_total_row, IF(C17=expenses_total_row, "/2", IF(C17="/2", savings_header_row, IF(C17<savings_max_row, C17+1, IF(C17=savings_max_row, savings_total_row, -1)))))))))))} -> 24 | D18: =IF(is_header, row_id, IF(NOT(is_empty), D17, -1)) -> 12 | E18: {=1*OR(row_id=income_header_row, row_id=expenses_header_row, row_id=savings_header_row)} -> 0 | F18: =1*NOT(OR(is_header, is_total, is_empty)) -> 0 | G18: {=1*OR(row_id=income_total_row, row_id=expenses_total_row, row_id=savings_total_row)} -> 1 | H18: =1*OR(row_id="/1", row_id="/2", row_id=-1) -> 0 | I18: {=IFERROR(INDEX('Budget Planning'!$C:$C,header_row_id)," ")} -> Income | J18: {=IFERROR(INDEX('Budget Planning'!$C:$C, row_id), " ")} -> Total | K18: {=IF(OR(is_header, is_empty), "", IF(is_total, IF(selected_period="Total Year", SUM( Tracking[Amount] * (Tracking[Type]=type)*(YEAR(Tracking[Effective Date])=selected_year)), SUM( Tracking[Amount] * (Tracking[Type]=type)*(YEAR(Tracking[Effective Date])=selected_year)*(MONTH(Tracking[Effective Date])=selected_period) )), IF(selected_period="Total Year", SUM( Tracking[Amount] * (Tracking[Type]=type)*(Tracking[Category]=item)*(YEAR(Tracking[Effective Date])=selected_year)), SUM( Tracking[Amount] * (Tracking[Type]=type)*(Tracking[Category]=item)*(YEAR(Tracking[Effective Date])=selected_year)*(MONTH(Tracking[Effective Date])=selected_period))) ) )} -> 47919.35 | L18: {=IF(OR(is_header, is_empty), "", INDEX('Budget Planning'!$E:$IG, row_id, MATCH(IF(selected_period="Total Year", selected_year, DATE(selected_year, selected_period, 1)), 'Budget Planning'!$E$12:$IG$12, 0)))} -> 47579.95 | M18: {=IF(is_cat, IF(header_row_id=income_header_row, MATCH(income_min_row, $C:$C,0), IF(header_row_id=expenses_header_row, MATCH(expenses_min_row, $C:$C,0), IF(header_row_id=savings_header_row, MATCH(savings_min_row, $C:$C,0), ""))), "")} | N18: {=IF(is_cat, IF(header_row_id=income_header_row, MATCH(income_max_row, $C:$C,0), IF(header_row_id=expenses_header_row, MATCH(expenses_max_row, $C:$C,0), IF(header_row_id=savings_header_row, MATCH(savings_max_row, $C:$C,0), ""))), "")} | O18: =IF(is_cat, ADDRESS(sort_min_row, COLUMN(tracked)) & ":" & ADDRESS(sort_max_row, COLUMN(tracked)), "") | P18: =IF(is_cat, RANK(tracked, INDIRECT(tracked_range), 0), "") | Q18: =IF(is_cat, ADDRESS(sort_min_row, COLUMN(budget)) & ":" & ADDRESS(sort_max_row, COLUMN(budget)), "") | R18: =IF(is_cat, RANK(budget, INDIRECT(budget_range), 0), "") | S18: =IF(is_cat, _xlfn.NUMBERVALUE(tracked_rank & budget_rank), "") | T18: =IF(is_cat, ADDRESS(sort_min_row, COLUMN(comb_rank)) & ":" & ADDRESS(sort_max_row, COLUMN(comb_rank)), "") | U18: =IF(is_cat, RANK(comb_rank, INDIRECT(comb_rank_range), 1), "") | V18: =IF(is_cat, ADDRESS(sort_min_row, COLUMN(comb_rank_norm)) & ":" & ADDRESS(ROW(), COLUMN(comb_rank_norm)), "") | W18: =IF(is_cat, comb_rank_norm +COUNTIF(INDIRECT(comb_rank_norm_run_range), comb_rank_norm)-1, "") | X18: =IF(is_cat, header_row_id + comb_rank_unique, row_id) -> 24 | Y18: =IF(is_empty, "", INDEX($J:$J, MATCH(row_id, $X:$X, 0))) -> Total | Z18: =IF(is_empty, "", IF(is_header, "Tracked", INDEX($K:$K, MATCH(row_id, $X:$X,0)))) -> 47919.35 | AA18: =IF(is_empty, "", IF(is_header, "Budget", INDEX($L:$L, MATCH(row_id, $X:$X,0)))) -> 47579.95 | AB18: =IF(is_empty, "", IF(is_header, "% Compl.", IFERROR(out_tracked / out_budget, "-"))) -> 1.0071333 | AC18: =IF(is_empty, "", IF(is_header, "Remaining", IF(out_budget - out_tracked > 0, out_budget - out_tracked, 0))) -> 0 | AD18: =IF(is_empty, "", IF(is_header, "Excess", IF(out_budget - out_tracked < 0, out_tracked - out_budget, 0))) -> 339.4 | AI18: =Calculations!E37 -> Grant Payment | AJ18: =Calculations!F37 -> 4000
C19: {=IF(C18=-1, -1, IF(C18<income_max_row, C18+1, IF(C18=income_max_row, income_total_row, IF(C18=income_total_row, "/1", IF(C18="/1", expenses_header_row, IF(C18<expenses_max_row, C18+1, IF(C18=expenses_max_row, expenses_total_row, IF(C18=expenses_total_row, "/2", IF(C18="/2", savings_header_row, IF(C18<savings_max_row, C18+1, IF(C18=savings_max_row, savings_total_row, -1)))))))))))} -> /1 | D19: =IF(is_header, row_id, IF(NOT(is_empty), D18, -1)) -> -1 | E19: {=1*OR(row_id=income_header_row, row_id=expenses_header_row, row_id=savings_header_row)} -> 0 | F19: =1*NOT(OR(is_header, is_total, is_empty)) -> 0 | G19: {=1*OR(row_id=income_total_row, row_id=expenses_total_row, row_id=savings_total_row)} -> 0 | H19: =1*OR(row_id="/1", row_id="/2", row_id=-1) -> 1 | I19: {=IFERROR(INDEX('Budget Planning'!$C:$C,header_row_id)," ")} | J19: {=IFERROR(INDEX('Budget Planning'!$C:$C, row_id), " ")} | K19: {=IF(OR(is_header, is_empty), "", IF(is_total, IF(selected_period="Total Year", SUM( Tracking[Amount] * (Tracking[Type]=type)*(YEAR(Tracking[Effective Date])=selected_year)), SUM( Tracking[Amount] * (Tracking[Type]=type)*(YEAR(Tracking[Effective Date])=selected_year)*(MONTH(Tracking[Effective Date])=selected_period) )), IF(selected_period="Total Year", SUM( Tracking[Amount] * (Tracking[Type]=type)*(Tracking[Category]=item)*(YEAR(Tracking[Effective Date])=selected_year)), SUM( Tracking[Amount] * (Tracking[Type]=type)*(Tracking[Category]=item)*(YEAR(Tracking[Effective Date])=selected_year)*(MONTH(Tracking[Effective Date])=selected_period))) ) )} | L19: {=IF(OR(is_header, is_empty), "", INDEX('Budget Planning'!$E:$IG, row_id, MATCH(IF(selected_period="Total Year", selected_year, DATE(selected_year, selected_period, 1)), 'Budget Planning'!$E$12:$IG$12, 0)))} | M19: {=IF(is_cat, IF(header_row_id=income_header_row, MATCH(income_min_row, $C:$C,0), IF(header_row_id=expenses_header_row, MATCH(expenses_min_row, $C:$C,0), IF(header_row_id=savings_header_row, MATCH(savings_min_row, $C:$C,0), ""))), "")} | N19: {=IF(is_cat, IF(header_row_id=income_header_row, MATCH(income_max_row, $C:$C,0), IF(header_row_id=expenses_header_row, MATCH(expenses_max_row, $C:$C,0), IF(header_row_id=savings_header_row, MATCH(savings_max_row, $C:$C,0), ""))), "")} | O19: =IF(is_cat, ADDRESS(sort_min_row, COLUMN(tracked)) & ":" & ADDRESS(sort_max_row, COLUMN(tracked)), "") | P19: =IF(is_cat, RANK(tracked, INDIRECT(tracked_range), 0), "") | Q19: =IF(is_cat, ADDRESS(sort_min_row, COLUMN(budget)) & ":" & ADDRESS(sort_max_row, COLUMN(budget)), "") | R19: =IF(is_cat, RANK(budget, INDIRECT(budget_range), 0), "") | S19: =IF(is_cat, _xlfn.NUMBERVALUE(tracked_rank & budget_rank), "") | T19: =IF(is_cat, ADDRESS(sort_min_row, COLUMN(comb_rank)) & ":" & ADDRESS(sort_max_row, COLUMN(comb_rank)), "") | U19: =IF(is_cat, RANK(comb_rank, INDIRECT(comb_rank_range), 1), "") | V19: =IF(is_cat, ADDRESS(sort_min_row, COLUMN(comb_rank_norm)) & ":" & ADDRESS(ROW(), COLUMN(comb_rank_norm)), "") | W19: =IF(is_cat, comb_rank_norm +COUNTIF(INDIRECT(comb_rank_norm_run_range), comb_rank_norm)-1, "") | X19: =IF(is_cat, header_row_id + comb_rank_unique, row_id) -> /1 | Y19: =IF(is_empty, "", INDEX($J:$J, MATCH(row_id, $X:$X, 0))) | Z19: =IF(is_empty, "", IF(is_header, "Tracked", INDEX($K:$K, MATCH(row_id, $X:$X,0)))) | AA19: =IF(is_empty, "", IF(is_header, "Budget", INDEX($L:$L, MATCH(row_id, $X:$X,0)))) | AB19: =IF(is_empty, "", IF(is_header, "% Compl.", IFERROR(out_tracked / out_budget, "-"))) | AC19: =IF(is_empty, "", IF(is_header, "Remaining", IF(out_budget - out_tracked > 0, out_budget - out_tracked, 0))) | AD19: =IF(is_empty, "", IF(is_header, "Excess", IF(out_budget - out_tracked < 0, out_tracked - out_budget, 0))) | AI19: =Calculations!E38 -> Extras / Twint Chargeback | AJ19: =Calculations!F38 -> 1160.25
C20: {=IF(C19=-1, -1, IF(C19<income_max_row, C19+1, IF(C19=income_max_row, income_total_row, IF(C19=income_total_row, "/1", IF(C19="/1", expenses_header_row, IF(C19<expenses_max_row, C19+1, IF(C19=expenses_max_row, expenses_total_row, IF(C19=expenses_total_row, "/2", IF(C19="/2", savings_header_row, IF(C19<savings_max_row, C19+1, IF(C19=savings_max_row, savings_total_row, -1)))))))))))} -> 26 | D20: =IF(is_header, row_id, IF(NOT(is_empty), D19, -1)) -> 26 | E20: {=1*OR(row_id=income_header_row, row_id=expenses_header_row, row_id=savings_header_row)} -> 1 | F20: =1*NOT(OR(is_header, is_total, is_empty)) -> 0 | G20: {=1*OR(row_id=income_total_row, row_id=expenses_total_row, row_id=savings_total_row)} -> 0 | H20: =1*OR(row_id="/1", row_id="/2", row_id=-1) -> 0 | I20: {=IFERROR(INDEX('Budget Planning'!$C:$C,header_row_id)," ")} -> Expenses | J20: {=IFERROR(INDEX('Budget Planning'!$C:$C, row_id), " ")} -> Expenses | K20: {=IF(OR(is_header, is_empty), "", IF(is_total, IF(selected_period="Total Year", SUM( Tracking[Amount] * (Tracking[Type]=type)*(YEAR(Tracking[Effective Date])=selected_year)), SUM( Tracking[Amount] * (Tracking[Type]=type)*(YEAR(Tracking[Effective Date])=selected_year)*(MONTH(Tracking[Effective Date])=selected_period) )), IF(selected_period="Total Year", SUM( Tracking[Amount] * (Tracking[Type]=type)*(Tracking[Category]=item)*(YEAR(Tracking[Effective Date])=selected_year)), SUM( Tracking[Amount] * (Tracking[Type]=type)*(Tracking[Category]=item)*(YEAR(Tracking[Effective Date])=selected_year)*(MONTH(Tracking[Effective Date])=selected_period))) ) )} | L20: {=IF(OR(is_header, is_empty), "", INDEX('Budget Planning'!$E:$IG, row_id, MATCH(IF(selected_period="Total Year", selected_year, DATE(selected_year, selected_period, 1)), 'Budget Planning'!$E$12:$IG$12, 0)))} | M20: {=IF(is_cat, IF(header_row_id=income_header_row, MATCH(income_min_row, $C:$C,0), IF(header_row_id=expenses_header_row, MATCH(expenses_min_row, $C:$C,0), IF(header_row_id=savings_header_row, MATCH(savings_min_row, $C:$C,0), ""))), "")} | N20: {=IF(is_cat, IF(header_row_id=income_header_row, MATCH(income_max_row, $C:$C,0), IF(header_row_id=expenses_header_row, MATCH(expenses_max_row, $C:$C,0), IF(header_row_id=savings_header_row, MATCH(savings_max_row, $C:$C,0), ""))), "")} | O20: =IF(is_cat, ADDRESS(sort_min_row, COLUMN(tracked)) & ":" & ADDRESS(sort_max_row, COLUMN(tracked)), "") | P20: =IF(is_cat, RANK(tracked, INDIRECT(tracked_range), 0), "") | Q20: =IF(is_cat, ADDRESS(sort_min_row, COLUMN(budget)) & ":" & ADDRESS(sort_max_row, COLUMN(budget)), "") | R20: =IF(is_cat, RANK(budget, INDIRECT(budget_range), 0), "") | S20: =IF(is_cat, _xlfn.NUMBERVALUE(tracked_rank & budget_rank), "") | T20: =IF(is_cat, ADDRESS(sort_min_row, COLUMN(comb_rank)) & ":" & ADDRESS(sort_max_row, COLUMN(comb_rank)), "") | U20: =IF(is_cat, RANK(comb_rank, INDIRECT(comb_rank_range), 1), "") | V20: =IF(is_cat, ADDRESS(sort_min_row, COLUMN(comb_rank_norm)) & ":" & ADDRESS(ROW(), COLUMN(comb_rank_norm)), "") | W20: =IF(is_cat, comb_rank_norm +COUNTIF(INDIRECT(comb_rank_norm_run_range), comb_rank_norm)-1, "") | X20: =IF(is_cat, header_row_id + comb_rank_unique, row_id) -> 26 | Y20: =IF(is_empty, "", INDEX($J:$J, MATCH(row_id, $X:$X, 0))) -> Expenses | Z20: =IF(is_empty, "", IF(is_header, "Tracked", INDEX($K:$K, MATCH(row_id, $X:$X,0)))) -> Tracked | AA20: =IF(is_empty, "", IF(is_header, "Budget", INDEX($L:$L, MATCH(row_id, $X:$X,0)))) -> Budget | AB20: =IF(is_empty, "", IF(is_header, "% Compl.", IFERROR(out_tracked / out_budget, "-"))) -> % Compl. | AC20: =IF(is_empty, "", IF(is_header, "Remaining", IF(out_budget - out_tracked > 0, out_budget - out_tracked, 0))) -> Remaining | AD20: =IF(is_empty, "", IF(is_header, "Excess", IF(out_budget - out_tracked < 0, out_tracked - out_budget, 0))) -> Excess | AI20: =Calculations!E39 | AJ20: =Calculations!F39
C21: {=IF(C20=-1, -1, IF(C20<income_max_row, C20+1, IF(C20=income_max_row, income_total_row, IF(C20=income_total_row, "/1", IF(C20="/1", expenses_header_row, IF(C20<expenses_max_row, C20+1, IF(C20=expenses_max_row, expenses_total_row, IF(C20=expenses_total_row, "/2", IF(C20="/2", savings_header_row, IF(C20<savings_max_row, C20+1, IF(C20=savings_max_row, savings_total_row, -1)))))))))))} -> 27 | D21: =IF(is_header, row_id, IF(NOT(is_empty), D20, -1)) -> 26 | E21: {=1*OR(row_id=income_header_row, row_id=expenses_header_row, row_id=savings_header_row)} -> 0 | F21: =1*NOT(OR(is_header, is_total, is_empty)) -> 1 | G21: {=1*OR(row_id=income_total_row, row_id=expenses_total_row, row_id=savings_total_row)} -> 0 | H21: =1*OR(row_id="/1", row_id="/2", row_id=-1) -> 0 | I21: {=IFERROR(INDEX('Budget Planning'!$C:$C,header_row_id)," ")} -> Expenses | J21: {=IFERROR(INDEX('Budget Planning'!$C:$C, row_id), " ")} -> Housing | K21: {=IF(OR(is_header, is_empty), "", IF(is_total, IF(selected_period="Total Year", SUM( Tracking[Amount] * (Tracking[Type]=type)*(YEAR(Tracking[Effective Date])=selected_year)), SUM( Tracking[Amount] * (Tracking[Type]=type)*(YEAR(Tracking[Effective Date])=selected_year)*(MONTH(Tracking[Effective Date])=selected_period) )), IF(selected_period="Total Year", SUM( Tracking[Amount] * (Tracking[Type]=type)*(Tracking[Category]=item)*(YEAR(Tracking[Effective Date])=selected_year)), SUM( Tracking[Amount] * (Tracking[Type]=type)*(Tracking[Category]=item)*(YEAR(Tracking[Effective Date])=selected_year)*(MONTH(Tracking[Effective Date])=selected_period))) ) )} -> 9148 | L21: {=IF(OR(is_header, is_empty), "", INDEX('Budget Planning'!$E:$IG, row_id, MATCH(IF(selected_period="Total Year", selected_year, DATE(selected_year, selected_period, 1)), 'Budget Planning'!$E$12:$IG$12, 0)))} -> 9148 | M21: {=IF(is_cat, IF(header_row_id=income_header_row, MATCH(income_min_row, $C:$C,0), IF(header_row_id=expenses_header_row, MATCH(expenses_min_row, $C:$C,0), IF(header_row_id=savings_header_row, MATCH(savings_min_row, $C:$C,0), ""))), "")} -> 21 | N21: {=IF(is_cat, IF(header_row_id=income_header_row, MATCH(income_max_row, $C:$C,0), IF(header_row_id=expenses_header_row, MATCH(expenses_max_row, $C:$C,0), IF(header_row_id=savings_header_row, MATCH(savings_max_row, $C:$C,0), ""))), "")} -> 41 | O21: =IF(is_cat, ADDRESS(sort_min_row, COLUMN(tracked)) & ":" & ADDRESS(sort_max_row, COLUMN(tracked)), "") -> $K$21:$K$41 | P21: =IF(is_cat, RANK(tracked, INDIRECT(tracked_range), 0), "") -> 1 | Q21: =IF(is_cat, ADDRESS(sort_min_row, COLUMN(budget)) & ":" & ADDRESS(sort_max_row, COLUMN(budget)), "") -> $L$21:$L$41 | R21: =IF(is_cat, RANK(budget, INDIRECT(budget_range), 0), "") -> 1 | S21: =IF(is_cat, _xlfn.NUMBERVALUE(tracked_rank & budget_rank), "") -> 11 | T21: =IF(is_cat, ADDRESS(sort_min_row, COLUMN(comb_rank)) & ":" & ADDRESS(sort_max_row, COLUMN(comb_rank)), "") -> $S$21:$S$41 | U21: =IF(is_cat, RANK(comb_rank, INDIRECT(comb_rank_range), 1), "") -> 1 | V21: =IF(is_cat, ADDRESS(sort_min_row, COLUMN(comb_rank_norm)) & ":" & ADDRESS(ROW(), COLUMN(comb_rank_norm)), "") -> $U$21:$U$21 | W21: =IF(is_cat, comb_rank_norm +COUNTIF(INDIRECT(comb_rank_norm_run_range), comb_rank_norm)-1, "") -> 1 | X21: =IF(is_cat, header_row_id + comb_rank_unique, row_id) -> 27 | Y21: =IF(is_empty, "", INDEX($J:$J, MATCH(row_id, $X:$X, 0))) -> Housing | Z21: =IF(is_empty, "", IF(is_header, "Tracked", INDEX($K:$K, MATCH(row_id, $X:$X,0)))) -> 9148 | AA21: =IF(is_empty, "", IF(is_header, "Budget", INDEX($L:$L, MATCH(row_id, $X:$X,0)))) -> 9148 | AB21: =IF(is_empty, "", IF(is_header, "% Compl.", IFERROR(out_tracked / out_budget, "-"))) -> 1 | AC21: =IF(is_empty, "", IF(is_header, "Remaining", IF(out_budget - out_tracked > 0, out_budget - out_tracked, 0))) -> 0 | AD21: =IF(is_empty, "", IF(is_header, "Excess", IF(out_budget - out_tracked < 0, out_tracked - out_budget, 0))) -> 0 | AI21: =Calculations!E40 | AJ21: =Calculations!F40
C22: {=IF(C21=-1, -1, IF(C21<income_max_row, C21+1, IF(C21=income_max_row, income_total_row, IF(C21=income_total_row, "/1", IF(C21="/1", expenses_header_row, IF(C21<expenses_max_row, C21+1, IF(C21=expenses_max_row, expenses_total_row, IF(C21=expenses_total_row, "/2", IF(C21="/2", savings_header_row, IF(C21<savings_max_row, C21+1, IF(C21=savings_max_row, savings_total_row, -1)))))))))))} -> 28 | D22: =IF(is_header, row_id, IF(NOT(is_empty), D21, -1)) -> 26 | E22: {=1*OR(row_id=income_header_row, row_id=expenses_header_row, row_id=savings_header_row)} -> 0 | F22: =1*NOT(OR(is_header, is_total, is_empty)) -> 1 | G22: {=1*OR(row_id=income_total_row, row_id=expenses_total_row, row_id=savings_total_row)} -> 0 | H22: =1*OR(row_id="/1", row_id="/2", row_id=-1) -> 0 | I22: {=IFERROR(INDEX('Budget Planning'!$C:$C,header_row_id)," ")} -> Expenses | J22: {=IFERROR(INDEX('Budget Planning'!$C:$C, row_id), " ")} -> Home Utils | K22: {=IF(OR(is_header, is_empty), "", IF(is_total, IF(selected_period="Total Year", SUM( Tracking[Amount] * (Tracking[Type]=type)*(YEAR(Tracking[Effective Date])=selected_year)), SUM( Tracking[Amount] * (Tracking[Type]=type)*(YEAR(Tracking[Effective Date])=selected_year)*(MONTH(Tracking[Effective Date])=selected_period) )), IF(selected_period="Total Year", SUM( Tracking[Amount] * (Tracking[Type]=type)*(Tracking[Category]=item)*(YEAR(Tracking[Effective Date])=selected_year)), SUM( Tracking[Amount] * (Tracking[Type]=type)*(Tracking[Category]=item)*(YEAR(Tracking[Effective Date])=selected_year)*(MONTH(Tracking[Effective Date])=selected_period))) ) )} -> 655.35 | L22: {=IF(OR(is_header, is_empty), "", INDEX('Budget Planning'!$E:$IG, row_id, MATCH(IF(selected_period="Total Year", selected_year, DATE(selected_year, selected_period, 1)), 'Budget Planning'!$E$12:$IG$12, 0)))} -> 175 | M22: {=IF(is_cat, IF(header_row_id=income_header_row, MATCH(income_min_row, $C:$C,0), IF(header_row_id=expenses_header_row, MATCH(expenses_min_row, $C:$C,0), IF(header_row_id=savings_header_row, MATCH(savings_min_row, $C:$C,0), ""))), "")} -> 21 | N22: {=IF(is_cat, IF(header_row_id=income_header_row, MATCH(income_max_row, $C:$C,0), IF(header_row_id=expenses_header_row, MATCH(expenses_max_row, $C:$C,0), IF(header_row_id=savings_header_row, MATCH(savings_max_row, $C:$C,0), ""))), "")} -> 41 | O22: =IF(is_cat, ADDRESS(sort_min_row, COLUMN(tracked)) & ":" & ADDRESS(sort_max_row, COLUMN(tracked)), "") -> $K$21:$K$41 | P22: =IF(is_cat, RANK(tracked, INDIRECT(tracked_range), 0), "") -> 10 | Q22: =IF(is_cat, ADDRESS(sort_min_row, COLUMN(budget)) & ":" & ADDRESS(sort_max_row, COLUMN(budget)), "") -> $L$21:$L$41 | R22: =IF(is_cat, RANK(budget, INDIRECT(budget_range), 0), "") -> 18 | S22: =IF(is_cat, _xlfn.NUMBERVALUE(tracked_rank & budget_rank), "") -> 1018 | T22: =IF(is_cat, ADDRESS(sort_min_row, COLUMN(comb_rank)) & ":" & ADDRESS(sort_max_row, COLUMN(comb_rank)), "") -> $S$21:$S$41 | U22: =IF(is_cat, RANK(comb_rank, INDIRECT(comb_rank_range), 1), "") -> 12 | V22: =IF(is_cat, ADDRESS(sort_min_row, COLUMN(comb_rank_norm)) & ":" & ADDRESS(ROW(), COLUMN(comb_rank_norm)), "") -> $U$21:$U$22 | W22: =IF(is_cat, comb_rank_norm +COUNTIF(INDIRECT(comb_rank_norm_run_range), comb_rank_norm)-1, "") -> 12 | X22: =IF(is_cat, header_row_id + comb_rank_unique, row_id) -> 38 | Y22: =IF(is_empty, "", INDEX($J:$J, MATCH(row_id, $X:$X, 0))) -> Restaurants | Z22: =IF(is_empty, "", IF(is_header, "Tracked", INDEX($K:$K, MATCH(row_id, $X:$X,0)))) -> 3150.13 | AA22: =IF(is_empty, "", IF(is_header, "Budget", INDEX($L:$L, MATCH(row_id, $X:$X,0)))) -> 3000 | AB22: =IF(is_empty, "", IF(is_header, "% Compl.", IFERROR(out_tracked / out_budget, "-"))) -> 1.0500433 | AC22: =IF(is_empty, "", IF(is_header, "Remaining", IF(out_budget - out_tracked > 0, out_budget - out_tracked, 0))) -> 0 | AD22: =IF(is_empty, "", IF(is_header, "Excess", IF(out_budget - out_tracked < 0, out_tracked - out_budget, 0))) -> 150.13 | AI22: =Calculations!E41 -> Total | AJ22: =Calculations!F41 -> 47919.35
C23: {=IF(C22=-1, -1, IF(C22<income_max_row, C22+1, IF(C22=income_max_row, income_total_row, IF(C22=income_total_row, "/1", IF(C22="/1", expenses_header_row, IF(C22<expenses_max_row, C22+1, IF(C22=expenses_max_row, expenses_total_row, IF(C22=expenses_total_row, "/2", IF(C22="/2", savings_header_row, IF(C22<savings_max_row, C22+1, IF(C22=savings_max_row, savings_total_row, -1)))))))))))} -> 29 | D23: =IF(is_header, row_id, IF(NOT(is_empty), D22, -1)) -> 26 | E23: {=1*OR(row_id=income_header_row, row_id=expenses_header_row, row_id=savings_header_row)} -> 0 | F23: =1*NOT(OR(is_header, is_total, is_empty)) -> 1 | G23: {=1*OR(row_id=income_total_row, row_id=expenses_total_row, row_id=savings_total_row)} -> 0 | H23: =1*OR(row_id="/1", row_id="/2", row_id=-1) -> 0 | I23: {=IFERROR(INDEX('Budget Planning'!$C:$C,header_row_id)," ")} -> Expenses | J23: {=IFERROR(INDEX('Budget Planning'!$C:$C, row_id), " ")} -> Home Furnitures | K23: {=IF(OR(is_header, is_empty), "", IF(is_total, IF(selected_period="Total Year", SUM( Tracking[Amount] * (Tracking[Type]=type)*(YEAR(Tracking[Effective Date])=selected_year)), SUM( Tracking[Amount] * (Tracking[Type]=type)*(YEAR(Tracking[Effective Date])=selected_year)*(MONTH(Tracking[Effective Date])=selected_period) )), IF(selected_period="Total Year", SUM( Tracking[Amount] * (Tracking[Type]=type)*(Tracking[Category]=item)*(YEAR(Tracking[Effective Date])=selected_year)), SUM( Tracking[Amount] * (Tracking[Type]=type)*(Tracking[Category]=item)*(YEAR(Tracking[Effective Date])=selected_year)*(MONTH(Tracking[Effective Date])=selected_period))) ) )} -> 1509.6 | L23: {=IF(OR(is_header, is_empty), "", INDEX('Budget Planning'!$E:$IG, row_id, MATCH(IF(selected_period="Total Year", selected_year, DATE(selected_year, selected_period, 1)), 'Budget Planning'!$E$12:$IG$12, 0)))} -> 1509.6 | M23: {=IF(is_cat, IF(header_row_id=income_header_row, MATCH(income_min_row, $C:$C,0), IF(header_row_id=expenses_header_row, MATCH(expenses_min_row, $C:$C,0), IF(header_row_id=savings_header_row, MATCH(savings_min_row, $C:$C,0), ""))), "")} -> 21 | N23: {=IF(is_cat, IF(header_row_id=income_header_row, MATCH(income_max_row, $C:$C,0), IF(header_row_id=expenses_header_row, MATCH(expenses_max_row, $C:$C,0), IF(header_row_id=savings_header_row, MATCH(savings_max_row, $C:$C,0), ""))), "")} -> 41 | O23: =IF(is_cat, ADDRESS(sort_min_row, COLUMN(tracked)) & ":" & ADDRESS(sort_max_row, COLUMN(tracked)), "") -> $K$21:$K$41 | P23: =IF(is_cat, RANK(tracked, INDIRECT(tracked_range), 0), "") -> 6 | Q23: =IF(is_cat, ADDRESS(sort_min_row, COLUMN(budget)) & ":" & ADDRESS(sort_max_row, COLUMN(budget)), "") -> $L$21:$L$41 | R23: =IF(is_cat, RANK(budget, INDIRECT(budget_range), 0), "") -> 7 | S23: =IF(is_cat, _xlfn.NUMBERVALUE(tracked_rank & budget_rank), "") -> 67 | T23: =IF(is_cat, ADDRESS(sort_min_row, COLUMN(comb_rank)) & ":" & ADDRESS(sort_max_row, COLUMN(comb_rank)), "") -> $S$21:$S$41 | U23: =IF(is_cat, RANK(comb_rank, INDIRECT(comb_rank_range), 1), "") -> 6 | V23: =IF(is_cat, ADDRESS(sort_min_row, COLUMN(comb_rank_norm)) & ":" & ADDRESS(ROW(), COLUMN(comb_rank_norm)), "") -> $U$21:$U$23 | W23: =IF(is_cat, comb_rank_norm +COUNTIF(INDIRECT(comb_rank_norm_run_range), comb_rank_norm)-1, "") -> 6 | X23: =IF(is_cat, header_row_id + comb_rank_unique, row_id) -> 32 | Y23: =IF(is_empty, "", INDEX($J:$J, MATCH(row_id, $X:$X, 0))) -> Debt | Z23: =IF(is_empty, "", IF(is_header, "Tracked", INDEX($K:$K, MATCH(row_id, $X:$X,0)))) -> 2756.85 | AA23: =IF(is_empty, "", IF(is_header, "Budget", INDEX($L:$L, MATCH(row_id, $X:$X,0)))) -> 4000 | AB23: =IF(is_empty, "", IF(is_header, "% Compl.", IFERROR(out_tracked / out_budget, "-"))) -> 0.6892125 | AC23: =IF(is_empty, "", IF(is_header, "Remaining", IF(out_budget - out_tracked > 0, out_budget - out_tracked, 0))) -> 1243.15 | AD23: =IF(is_empty, "", IF(is_header, "Excess", IF(out_budget - out_tracked < 0, out_tracked - out_budget, 0))) -> 0
C24: {=IF(C23=-1, -1, IF(C23<income_max_row, C23+1, IF(C23=income_max_row, income_total_row, IF(C23=income_total_row, "/1", IF(C23="/1", expenses_header_row, IF(C23<expenses_max_row, C23+1, IF(C23=expenses_max_row, expenses_total_row, IF(C23=expenses_total_row, "/2", IF(C23="/2", savings_header_row, IF(C23<savings_max_row, C23+1, IF(C23=savings_max_row, savings_total_row, -1)))))))))))} -> 30 | D24: =IF(is_header, row_id, IF(NOT(is_empty), D23, -1)) -> 26 | E24: {=1*OR(row_id=income_header_row, row_id=expenses_header_row, row_id=savings_header_row)} -> 0 | F24: =1*NOT(OR(is_header, is_total, is_empty)) -> 1 | G24: {=1*OR(row_id=income_total_row, row_id=expenses_total_row, row_id=savings_total_row)} -> 0 | H24: =1*OR(row_id="/1", row_id="/2", row_id=-1) -> 0 | I24: {=IFERROR(INDEX('Budget Planning'!$C:$C,header_row_id)," ")} -> Expenses | J24: {=IFERROR(INDEX('Budget Planning'!$C:$C, row_id), " ")} -> Groceries | K24: {=IF(OR(is_header, is_empty), "", IF(is_total, IF(selected_period="Total Year", SUM( Tracking[Amount] * (Tracking[Type]=type)*(YEAR(Tracking[Effective Date])=selected_year)), SUM( Tracking[Amount] * (Tracking[Type]=type)*(YEAR(Tracking[Effective Date])=selected_year)*(MONTH(Tracking[Effective Date])=selected_period) )), IF(selected_period="Total Year", SUM( Tracking[Amount] * (Tracking[Type]=type)*(Tracking[Category]=item)*(YEAR(Tracking[Effective Date])=selected_year)), SUM( Tracking[Amount] * (Tracking[Type]=type)*(Tracking[Category]=item)*(YEAR(Tracking[Effective Date])=selected_year)*(MONTH(Tracking[Effective Date])=selected_period))) ) )} -> 1326.26 | L24: {=IF(OR(is_header, is_empty), "", INDEX('Budget Planning'!$E:$IG, row_id, MATCH(IF(selected_period="Total Year", selected_year, DATE(selected_year, selected_period, 1)), 'Budget Planning'!$E$12:$IG$12, 0)))} -> 2500 | M24: {=IF(is_cat, IF(header_row_id=income_header_row, MATCH(income_min_row, $C:$C,0), IF(header_row_id=expenses_header_row, MATCH(expenses_min_row, $C:$C,0), IF(header_row_id=savings_header_row, MATCH(savings_min_row, $C:$C,0), ""))), "")} -> 21 | N24: {=IF(is_cat, IF(header_row_id=income_header_row, MATCH(income_max_row, $C:$C,0), IF(header_row_id=expenses_header_row, MATCH(expenses_max_row, $C:$C,0), IF(header_row_id=savings_header_row, MATCH(savings_max_row, $C:$C,0), ""))), "")} -> 41 | O24: =IF(is_cat, ADDRESS(sort_min_row, COLUMN(tracked)) & ":" & ADDRESS(sort_max_row, COLUMN(tracked)), "") -> $K$21:$K$41 | P24: =IF(is_cat, RANK(tracked, INDIRECT(tracked_range), 0), "") -> 7 | Q24: =IF(is_cat, ADDRESS(sort_min_row, COLUMN(budget)) & ":" & ADDRESS(sort_max_row, COLUMN(budget)), "") -> $L$21:$L$41 | R24: =IF(is_cat, RANK(budget, INDIRECT(budget_range), 0), "") -> 5 | S24: =IF(is_cat, _xlfn.NUMBERVALUE(tracked_rank & budget_rank), "") -> 75 | T24: =IF(is_cat, ADDRESS(sort_min_row, COLUMN(comb_rank)) & ":" & ADDRESS(sort_max_row, COLUMN(comb_rank)), "") -> $S$21:$S$41 | U24: =IF(is_cat, RANK(comb_rank, INDIRECT(comb_rank_range), 1), "") -> 7 | V24: =IF(is_cat, ADDRESS(sort_min_row, COLUMN(comb_rank_norm)) & ":" & ADDRESS(ROW(), COLUMN(comb_rank_norm)), "") -> $U$21:$U$24 | W24: =IF(is_cat, comb_rank_norm +COUNTIF(INDIRECT(comb_rank_norm_run_range), comb_rank_norm)-1, "") -> 7 | X24: =IF(is_cat, header_row_id + comb_rank_unique, row_id) -> 33 | Y24: =IF(is_empty, "", INDEX($J:$J, MATCH(row_id, $X:$X, 0))) -> Travel | Z24: =IF(is_empty, "", IF(is_header, "Tracked", INDEX($K:$K, MATCH(row_id, $X:$X,0)))) -> 2751.55 | AA24: =IF(is_empty, "", IF(is_header, "Budget", INDEX($L:$L, MATCH(row_id, $X:$X,0)))) -> 2000 | AB24: =IF(is_empty, "", IF(is_header, "% Compl.", IFERROR(out_tracked / out_budget, "-"))) -> 1.375775 | AC24: =IF(is_empty, "", IF(is_header, "Remaining", IF(out_budget - out_tracked > 0, out_budget - out_tracked, 0))) -> 0 | AD24: =IF(is_empty, "", IF(is_header, "Excess", IF(out_budget - out_tracked < 0, out_tracked - out_budget, 0))) -> 751.55
C25: {=IF(C24=-1, -1, IF(C24<income_max_row, C24+1, IF(C24=income_max_row, income_total_row, IF(C24=income_total_row, "/1", IF(C24="/1", expenses_header_row, IF(C24<expenses_max_row, C24+1, IF(C24=expenses_max_row, expenses_total_row, IF(C24=expenses_total_row, "/2", IF(C24="/2", savings_header_row, IF(C24<savings_max_row, C24+1, IF(C24=savings_max_row, savings_total_row, -1)))))))))))} -> 31 | D25: =IF(is_header, row_id, IF(NOT(is_empty), D24, -1)) -> 26 | E25: {=1*OR(row_id=income_header_row, row_id=expenses_header_row, row_id=savings_header_row)} -> 0 | F25: =1*NOT(OR(is_header, is_total, is_empty)) -> 1 | G25: {=1*OR(row_id=income_total_row, row_id=expenses_total_row, row_id=savings_total_row)} -> 0 | H25: =1*OR(row_id="/1", row_id="/2", row_id=-1) -> 0 | I25: {=IFERROR(INDEX('Budget Planning'!$C:$C,header_row_id)," ")} -> Expenses | J25: {=IFERROR(INDEX('Budget Planning'!$C:$C, row_id), " ")} -> Restaurants | K25: {=IF(OR(is_header, is_empty), "", IF(is_total, IF(selected_period="Total Year", SUM( Tracking[Amount] * (Tracking[Type]=type)*(YEAR(Tracking[Effective Date])=selected_year)), SUM( Tracking[Amount] * (Tracking[Type]=type)*(YEAR(Tracking[Effective Date])=selected_year)*(MONTH(Tracking[Effective Date])=selected_period) )), IF(selected_period="Total Year", SUM( Tracking[Amount] * (Tracking[Type]=type)*(Tracking[Category]=item)*(YEAR(Tracking[Effective Date])=selected_year)), SUM( Tracking[Amount] * (Tracking[Type]=type)*(Tracking[Category]=item)*(YEAR(Tracking[Effective Date])=selected_year)*(MONTH(Tracking[Effective Date])=selected_period))) ) )} -> 3150.13 | L25: {=IF(OR(is_header, is_empty), "", INDEX('Budget Planning'!$E:$IG, row_id, MATCH(IF(selected_period="Total Year", selected_year, DATE(selected_year, selected_period, 1)), 'Budget Planning'!$E$12:$IG$12, 0)))} -> 3000 | M25: {=IF(is_cat, IF(header_row_id=income_header_row, MATCH(income_min_row, $C:$C,0), IF(header_row_id=expenses_header_row, MATCH(expenses_min_row, $C:$C,0), IF(header_row_id=savings_header_row, MATCH(savings_min_row, $C:$C,0), ""))), "")} -> 21 | N25: {=IF(is_cat, IF(header_row_id=income_header_row, MATCH(income_max_row, $C:$C,0), IF(header_row_id=expenses_header_row, MATCH(expenses_max_row, $C:$C,0), IF(header_row_id=savings_header_row, MATCH(savings_max_row, $C:$C,0), ""))), "")} -> 41 | O25: =IF(is_cat, ADDRESS(sort_min_row, COLUMN(tracked)) & ":" & ADDRESS(sort_max_row, COLUMN(tracked)), "") -> $K$21:$K$41 | P25: =IF(is_cat, RANK(tracked, INDIRECT(tracked_range), 0), "") -> 2 | Q25: =IF(is_cat, ADDRESS(sort_min_row, COLUMN(budget)) & ":" & ADDRESS(sort_max_row, COLUMN(budget)), "") -> $L$21:$L$41 | R25: =IF(is_cat, RANK(budget, INDIRECT(budget_range), 0), "") -> 3 | S25: =IF(is_cat, _xlfn.NUMBERVALUE(tracked_rank & budget_rank), "") -> 23 | T25: =IF(is_cat, ADDRESS(sort_min_row, COLUMN(comb_rank)) & ":" & ADDRESS(sort_max_row, COLUMN(comb_rank)), "") -> $S$21:$S$41 | U25: =IF(is_cat, RANK(comb_rank, INDIRECT(comb_rank_range), 1), "") -> 2 | V25: =IF(is_cat, ADDRESS(sort_min_row, COLUMN(comb_rank_norm)) & ":" & ADDRESS(ROW(), COLUMN(comb_rank_norm)), "") -> $U$21:$U$25 | W25: =IF(is_cat, comb_rank_norm +COUNTIF(INDIRECT(comb_rank_norm_run_range), comb_rank_norm)-1, "") -> 2 | X25: =IF(is_cat, header_row_id + comb_rank_unique, row_id) -> 28 | Y25: =IF(is_empty, "", INDEX($J:$J, MATCH(row_id, $X:$X, 0))) -> Health Insurance | Z25: =IF(is_empty, "", IF(is_header, "Tracked", INDEX($K:$K, MATCH(row_id, $X:$X,0)))) -> 2506.75 | AA25: =IF(is_empty, "", IF(is_header, "Budget", INDEX($L:$L, MATCH(row_id, $X:$X,0)))) -> 2506.75 | AB25: =IF(is_empty, "", IF(is_header, "% Compl.", IFERROR(out_tracked / out_budget, "-"))) -> 1 | AC25: =IF(is_empty, "", IF(is_header, "Remaining", IF(out_budget - out_tracked > 0, out_budget - out_tracked, 0))) -> 0 | AD25: =IF(is_empty, "", IF(is_header, "Excess", IF(out_budget - out_tracked < 0, out_tracked - out_budget, 0))) -> 0
C26: {=IF(C25=-1, -1, IF(C25<income_max_row, C25+1, IF(C25=income_max_row, income_total_row, IF(C25=income_total_row, "/1", IF(C25="/1", expenses_header_row, IF(C25<expenses_max_row, C25+1, IF(C25=expenses_max_row, expenses_total_row, IF(C25=expenses_total_row, "/2", IF(C25="/2", savings_header_row, IF(C25<savings_max_row, C25+1, IF(C25=savings_max_row, savings_total_row, -1)))))))))))} -> 32 | D26: =IF(is_header, row_id, IF(NOT(is_empty), D25, -1)) -> 26 | E26: {=1*OR(row_id=income_header_row, row_id=expenses_header_row, row_id=savings_header_row)} -> 0 | F26: =1*NOT(OR(is_header, is_total, is_empty)) -> 1 | G26: {=1*OR(row_id=income_total_row, row_id=expenses_total_row, row_id=savings_total_row)} -> 0 | H26: =1*OR(row_id="/1", row_id="/2", row_id=-1) -> 0 | I26: {=IFERROR(INDEX('Budget Planning'!$C:$C,header_row_id)," ")} -> Expenses | J26: {=IFERROR(INDEX('Budget Planning'!$C:$C, row_id), " ")} -> Train | K26: {=IF(OR(is_header, is_empty), "", IF(is_total, IF(selected_period="Total Year", SUM( Tracking[Amount] * (Tracking[Type]=type)*(YEAR(Tracking[Effective Date])=selected_year)), SUM( Tracking[Amount] * (Tracking[Type]=type)*(YEAR(Tracking[Effective Date])=selected_year)*(MONTH(Tracking[Effective Date])=selected_period) )), IF(selected_period="Total Year", SUM( Tracking[Amount] * (Tracking[Type]=type)*(Tracking[Category]=item)*(YEAR(Tracking[Effective Date])=selected_year)), SUM( Tracking[Amount] * (Tracking[Type]=type)*(Tracking[Category]=item)*(YEAR(Tracking[Effective Date])=selected_year)*(MONTH(Tracking[Effective Date])=selected_period))) ) )} -> 791.4 | L26: {=IF(OR(is_header, is_empty), "", INDEX('Budget Planning'!$E:$IG, row_id, MATCH(IF(selected_period="Total Year", selected_year, DATE(selected_year, selected_period, 1)), 'Budget Planning'!$E$12:$IG$12, 0)))} -> 1300 | M26: {=IF(is_cat, IF(header_row_id=income_header_row, MATCH(income_min_row, $C:$C,0), IF(header_row_id=expenses_header_row, MATCH(expenses_min_row, $C:$C,0), IF(header_row_id=savings_header_row, MATCH(savings_min_row, $C:$C,0), ""))), "")} -> 21 | N26: {=IF(is_cat, IF(header_row_id=income_header_row, MATCH(income_max_row, $C:$C,0), IF(header_row_id=expenses_header_row, MATCH(expenses_max_row, $C:$C,0), IF(header_row_id=savings_header_row, MATCH(savings_max_row, $C:$C,0), ""))), "")} -> 41 | O26: =IF(is_cat, ADDRESS(sort_min_row, COLUMN(tracked)) & ":" & ADDRESS(sort_max_row, COLUMN(tracked)), "") -> $K$21:$K$41 | P26: =IF(is_cat, RANK(tracked, INDIRECT(tracked_range), 0), "") -> 9 | Q26: =IF(is_cat, ADDRESS(sort_min_row, COLUMN(budget)) & ":" & ADDRESS(sort_max_row, COLUMN(budget)), "") -> $L$21:$L$41 | R26: =IF(is_cat, RANK(budget, INDIRECT(budget_range), 0), "") -> 8 | S26: =IF(is_cat, _xlfn.NUMBERVALUE(tracked_rank & budget_rank), "") -> 98 | T26: =IF(is_cat, ADDRESS(sort_min_row, COLUMN(comb_rank)) & ":" & ADDRESS(sort_max_row, COLUMN(comb_rank)), "") -> $S$21:$S$41 | U26: =IF(is_cat, RANK(comb_rank, INDIRECT(comb_rank_range), 1), "") -> 9 | V26: =IF(is_cat, ADDRESS(sort_min_row, COLUMN(comb_rank_norm)) & ":" & ADDRESS(ROW(), COLUMN(comb_rank_norm)), "") -> $U$21:$U$26 | W26: =IF(is_cat, comb_rank_norm +COUNTIF(INDIRECT(comb_rank_norm_run_range), comb_rank_norm)-1, "") -> 9 | X26: =IF(is_cat, header_row_id + comb_rank_unique, row_id) -> 35 | Y26: =IF(is_empty, "", INDEX($J:$J, MATCH(row_id, $X:$X, 0))) -> Home Furnitures | Z26: =IF(is_empty, "", IF(is_header, "Tracked", INDEX($K:$K, MATCH(row_id, $X:$X,0)))) -> 1509.6 | AA26: =IF(is_empty, "", IF(is_header, "Budget", INDEX($L:$L, MATCH(row_id, $X:$X,0)))) -> 1509.6 | AB26: =IF(is_empty, "", IF(is_header, "% Compl.", IFERROR(out_tracked / out_budget, "-"))) -> 1 | AC26: =IF(is_empty, "", IF(is_header, "Remaining", IF(out_budget - out_tracked > 0, out_budget - out_tracked, 0))) -> 0 | AD26: =IF(is_empty, "", IF(is_header, "Excess", IF(out_budget - out_tracked < 0, out_tracked - out_budget, 0))) -> 2.2737368e-13
C27: {=IF(C26=-1, -1, IF(C26<income_max_row, C26+1, IF(C26=income_max_row, income_total_row, IF(C26=income_total_row, "/1", IF(C26="/1", expenses_header_row, IF(C26<expenses_max_row, C26+1, IF(C26=expenses_max_row, expenses_total_row, IF(C26=expenses_total_row, "/2", IF(C26="/2", savings_header_row, IF(C26<savings_max_row, C26+1, IF(C26=savings_max_row, savings_total_row, -1)))))))))))} -> 33 | D27: =IF(is_header, row_id, IF(NOT(is_empty), D26, -1)) -> 26 | E27: {=1*OR(row_id=income_header_row, row_id=expenses_header_row, row_id=savings_header_row)} -> 0 | F27: =1*NOT(OR(is_header, is_total, is_empty)) -> 1 | G27: {=1*OR(row_id=income_total_row, row_id=expenses_total_row, row_id=savings_total_row)} -> 0 | H27: =1*OR(row_id="/1", row_id="/2", row_id=-1) -> 0 | I27: {=IFERROR(INDEX('Budget Planning'!$C:$C,header_row_id)," ")} -> Expenses | J27: {=IFERROR(INDEX('Budget Planning'!$C:$C, row_id), " ")} -> Internet + Mobile | K27: {=IF(OR(is_header, is_empty), "", IF(is_total, IF(selected_period="Total Year", SUM( Tracking[Amount] * (Tracking[Type]=type)*(YEAR(Tracking[Effective Date])=selected_year)), SUM( Tracking[Amount] * (Tracking[Type]=type)*(YEAR(Tracking[Effective Date])=selected_year)*(MONTH(Tracking[Effective Date])=selected_period) )), IF(selected_period="Total Year", SUM( Tracking[Amount] * (Tracking[Type]=type)*(Tracking[Category]=item)*(YEAR(Tracking[Effective Date])=selected_year)), SUM( Tracking[Amount] * (Tracking[Type]=type)*(Tracking[Category]=item)*(YEAR(Tracking[Effective Date])=selected_year)*(MONTH(Tracking[Effective Date])=selected_period))) ) )} -> 390.05 | L27: {=IF(OR(is_header, is_empty), "", INDEX('Budget Planning'!$E:$IG, row_id, MATCH(IF(selected_period="Total Year", selected_year, DATE(selected_year, selected_period, 1)), 'Budget Planning'!$E$12:$IG$12, 0)))} -> 400 | M27: {=IF(is_cat, IF(header_row_id=income_header_row, MATCH(income_min_row, $C:$C,0), IF(header_row_id=expenses_header_row, MATCH(expenses_min_row, $C:$C,0), IF(header_row_id=savings_header_row, MATCH(savings_min_row, $C:$C,0), ""))), "")} -> 21 | N27: {=IF(is_cat, IF(header_row_id=income_header_row, MATCH(income_max_row, $C:$C,0), IF(header_row_id=expenses_header_row, MATCH(expenses_max_row, $C:$C,0), IF(header_row_id=savings_header_row, MATCH(savings_max_row, $C:$C,0), ""))), "")} -> 41 | O27: =IF(is_cat, ADDRESS(sort_min_row, COLUMN(tracked)) & ":" & ADDRESS(sort_max_row, COLUMN(tracked)), "") -> $K$21:$K$41 | P27: =IF(is_cat, RANK(tracked, INDIRECT(tracked_range), 0), "") -> 13 | Q27: =IF(is_cat, ADDRESS(sort_min_row, COLUMN(budget)) & ":" & ADDRESS(sort_max_row, COLUMN(budget)), "") -> $L$21:$L$41 | R27: =IF(is_cat, RANK(budget, INDIRECT(budget_range), 0), "") -> 16 | S27: =IF(is_cat, _xlfn.NUMBERVALUE(tracked_rank & budget_rank), "") -> 1316 | T27: =IF(is_cat, ADDRESS(sort_min_row, COLUMN(comb_rank)) & ":" & ADDRESS(sort_max_row, COLUMN(comb_rank)), "") -> $S$21:$S$41 | U27: =IF(is_cat, RANK(comb_rank, INDIRECT(comb_rank_range), 1), "") -> 14 | V27: =IF(is_cat, ADDRESS(sort_min_row, COLUMN(comb_rank_norm)) & ":" & ADDRESS(ROW(), COLUMN(comb_rank_norm)), "") -> $U$21:$U$27 | W27: =IF(is_cat, comb_rank_norm +COUNTIF(INDIRECT(comb_rank_norm_run_range), comb_rank_norm)-1, "") -> 14 | X27: =IF(is_cat, header_row_id + comb_rank_unique, row_id) -> 40 | Y27: =IF(is_empty, "", INDEX($J:$J, MATCH(row_id, $X:$X, 0))) -> Groceries | Z27: =IF(is_empty, "", IF(is_header, "Tracked", INDEX($K:$K, MATCH(row_id, $X:$X,0)))) -> 1326.26 | AA27: =IF(is_empty, "", IF(is_header, "Budget", INDEX($L:$L, MATCH(row_id, $X:$X,0)))) -> 2500 | AB27: =IF(is_empty, "", IF(is_header, "% Compl.", IFERROR(out_tracked / out_budget, "-"))) -> 0.530504 | AC27: =IF(is_empty, "", IF(is_header, "Remaining", IF(out_budget - out_tracked > 0, out_budget - out_tracked, 0))) -> 1173.74 | AD27: =IF(is_empty, "", IF(is_header, "Excess", IF(out_budget - out_tracked < 0, out_tracked - out_budget, 0))) -> 0
C28: {=IF(C27=-1, -1, IF(C27<income_max_row, C27+1, IF(C27=income_max_row, income_total_row, IF(C27=income_total_row, "/1", IF(C27="/1", expenses_header_row, IF(C27<expenses_max_row, C27+1, IF(C27=expenses_max_row, expenses_total_row, IF(C27=expenses_total_row, "/2", IF(C27="/2", savings_header_row, IF(C27<savings_max_row, C27+1, IF(C27=savings_max_row, savings_total_row, -1)))))))))))} -> 34 | D28: =IF(is_header, row_id, IF(NOT(is_empty), D27, -1)) -> 26 | E28: {=1*OR(row_id=income_header_row, row_id=expenses_header_row, row_id=savings_header_row)} -> 0 | F28: =1*NOT(OR(is_header, is_total, is_empty)) -> 1 | G28: {=1*OR(row_id=income_total_row, row_id=expenses_total_row, row_id=savings_total_row)} -> 0 | H28: =1*OR(row_id="/1", row_id="/2", row_id=-1) -> 0 | I28: {=IFERROR(INDEX('Budget Planning'!$C:$C,header_row_id)," ")} -> Expenses | J28: {=IFERROR(INDEX('Budget Planning'!$C:$C, row_id), " ")} -> Car | K28: {=IF(OR(is_header, is_empty), "", IF(is_total, IF(selected_period="Total Year", SUM( Tracking[Amount] * (Tracking[Type]=type)*(YEAR(Tracking[Effective Date])=selected_year)), SUM( Tracking[Amount] * (Tracking[Type]=type)*(YEAR(Tracking[Effective Date])=selected_year)*(MONTH(Tracking[Effective Date])=selected_period) )), IF(selected_period="Total Year", SUM( Tracking[Amount] * (Tracking[Type]=type)*(Tracking[Category]=item)*(YEAR(Tracking[Effective Date])=selected_year)), SUM( Tracking[Amount] * (Tracking[Type]=type)*(Tracking[Category]=item)*(YEAR(Tracking[Effective Date])=selected_year)*(MONTH(Tracking[Effective Date])=selected_period))) ) )} -> 242.22 | L28: {=IF(OR(is_header, is_empty), "", INDEX('Budget Planning'!$E:$IG, row_id, MATCH(IF(selected_period="Total Year", selected_year, DATE(selected_year, selected_period, 1)), 'Budget Planning'!$E$12:$IG$12, 0)))} -> 250 | M28: {=IF(is_cat, IF(header_row_id=income_header_row, MATCH(income_min_row, $C:$C,0), IF(header_row_id=expenses_header_row, MATCH(expenses_min_row, $C:$C,0), IF(header_row_id=savings_header_row, MATCH(savings_min_row, $C:$C,0), ""))), "")} -> 21 | N28: {=IF(is_cat, IF(header_row_id=income_header_row, MATCH(income_max_row, $C:$C,0), IF(header_row_id=expenses_header_row, MATCH(expenses_max_row, $C:$C,0), IF(header_row_id=savings_header_row, MATCH(savings_max_row, $C:$C,0), ""))), "")} -> 41 | O28: =IF(is_cat, ADDRESS(sort_min_row, COLUMN(tracked)) & ":" & ADDRESS(sort_max_row, COLUMN(tracked)), "") -> $K$21:$K$41 | P28: =IF(is_cat, RANK(tracked, INDIRECT(tracked_range), 0), "") -> 16 | Q28: =IF(is_cat, ADDRESS(sort_min_row, COLUMN(budget)) & ":" & ADDRESS(sort_max_row, COLUMN(budget)), "") -> $L$21:$L$41 | R28: =IF(is_cat, RANK(budget, INDIRECT(budget_range), 0), "") -> 17 | S28: =IF(is_cat, _xlfn.NUMBERVALUE(tracked_rank & budget_rank), "") -> 1617 | T28: =IF(is_cat, ADDRESS(sort_min_row, COLUMN(comb_rank)) & ":" & ADDRESS(sort_max_row, COLUMN(comb_rank)), "") -> $S$21:$S$41 | U28: =IF(is_cat, RANK(comb_rank, INDIRECT(comb_rank_range), 1), "") -> 16 | V28: =IF(is_cat, ADDRESS(sort_min_row, COLUMN(comb_rank_norm)) & ":" & ADDRESS(ROW(), COLUMN(comb_rank_norm)), "") -> $U$21:$U$28 | W28: =IF(is_cat, comb_rank_norm +COUNTIF(INDIRECT(comb_rank_norm_run_range), comb_rank_norm)-1, "") -> 16 | X28: =IF(is_cat, header_row_id + comb_rank_unique, row_id) -> 42 | Y28: =IF(is_empty, "", INDEX($J:$J, MATCH(row_id, $X:$X, 0))) -> Extras | Z28: =IF(is_empty, "", IF(is_header, "Tracked", INDEX($K:$K, MATCH(row_id, $X:$X,0)))) -> 858.9 | AA28: =IF(is_empty, "", IF(is_header, "Budget", INDEX($L:$L, MATCH(row_id, $X:$X,0)))) -> 1000 | AB28: =IF(is_empty, "", IF(is_header, "% Compl.", IFERROR(out_tracked / out_budget, "-"))) -> 0.8589 | AC28: =IF(is_empty, "", IF(is_header, "Remaining", IF(out_budget - out_tracked > 0, out_budget - out_tracked, 0))) -> 141.1 | AD28: =IF(is_empty, "", IF(is_header, "Excess", IF(out_budget - out_tracked < 0, out_tracked - out_budget, 0))) -> 0
